Workbook

Sheet Règles
B1: Domaines | C1: Elément | D1: Défense | E1: Type | G1: Attributs | H1: Fort contre | I1: Faible contre | J1: Ressources + | K1: Ressources - | L1: Condition + | M1: Condition - | N1: Climat | O1: Caractéristique + | P1: Caractéristique - | Q1: Compétence
A2: 🔥 | B2: Feu | C2: (énergie) chaleur, (continue) feu | D2: vs FOR | E2: Physique | F2: Intangible | G2: Force, Charisme | J2: Rage | K2: Garde | N2: Température + | O2: Puissance (x1), Dégats (x2)
A3: ❄️ | B3: Glace | C3: (énergie) froid, (continue) glace | D3: vs DEX | E3: Physique | F3: Intangible | G3: Dextérité, Intelligence | J3: Garde | K3: Rage | N3: Température - | O3: Absorption (x2), Contournement (x3)
A4: ⚡ | B4: Foudre | C4: (énergie) éléctricité, (continue) foudre | D4: vs AGI | E4: Physique | F4: Intangible | G4: Agilité, Ruse | J4: Adrénaline | K4: Adrénaline | O4: Vitesse (x1), Rapidité (x1), Perforation (x2)
A5: 🪨 | B5: Terre | C5: (physique) Terre | D5: vs CON | E5: Physique | F5: Tangible | G5: Force, Charisme | K5: Initiative | O5: Protection (x1), Déviation (x2)
A6: 💧 | B6: Eau | C6: (physique) eau | D6: vs CON | E6: Physique | F6: Tangible | G6: Dextérité, Intelligence | K6: Initiative | O6: Défense vs tactiques (x1), impact (x2)
A7: 🌪️ | B7: Air | C7: (physique) air | D7: vs CON | E7: Physique | F7: Tangible | G7: Agilité, Ruse | K7: Initiative | L7: Initiative | O7: Défense vs attaques (x1), ALure (x0.5)
A8: ☀️ | B8: Lumière | C8: (primordial) lumière | D8: vs PER | E8: Physique | F8: Intangible | O8: Adresse (x1), Visée (x0.5), Précision (x1), Criticité (x1)
A9: 🌑 | B9: Ombre | C9: (primordial) ombre | D9: vs PER | E9: Physique | F9: Intangible | O9: Maladresse (x1)
A10: ⚖️ | B10: Loi | C10: (fondamental) loi | D10: vs VOL | E10: Physique | F10: Intangible | G10: Chance
A11: 🌀 | B11: Chaos | C11: (fondamental) chaos | D11: vs VOL | E11: Physique | F11: Intangible | G11: Chance | O11: Fortune
A12: ✨ | B12: Sacre | C12: (origine) sacré | D12: vs SAG | E12: Physique | F12: Intangible | J12: Karma
A13: 🩸 | B13: Impie | C13: (origine) impie | D13: vs RUS | E13: Physique | F13: Intangible | K13: Karma
A14: ❤️ | B14: Vie | C14: (cycle) vie | D14: vs CON | E14: Physique | J14: Vitalité
A15: ☠️ | B15: Mort | C15: (cycle) mort | D15: vs CON | E15: Physique | F15: Tangible | K15: Vitalité | O15: Gravité (x2)
A16: ⚕️ | B16: Corps | G16: Les 5 Corps, Stature, Taille | J16: Vitalité | K16: Vitalité | O16: Récup Physique (x1), Robustesse, Réflexes
A17: 🧠 | B17: Esprit | G17: Les 5 Esprits, Ego, Apparence | J17: Psyché | K17: Psyché | O17: Récup Mentale (x1), Détermination, Sang Froid
A18: 🐗 | B18: Faune | G18: Les 5 Corps
A19: 🌿 | B19: Flore | C19: (physique) flore | D19: vs PER | F19: Tangible
A20: 🧩 | B20: Mental | C20: (mental) psy | D20: vs CON | G20: Les 5 Esprits | J20: Psyché | O20: Mémoire (x2), Puissance S, Resistance S, Perforation S, Absorption S
A21: ⚜️ | B21: Charme | K21: Psyché | O21: Malice S, Prestige
A22: ✡️ | B22: Arcane | C22: (arcanique) arcane, (force) force | D22: vs MAG | E22: Physique | F22: Intangible
A23: 🔮 | B23: Magie | G23: Magie | J23: Mana | K23: Mana | O23: Puissance M, Perforation M, Malice M
A24: 🪷 | B24: Nature | G24: Equilibre | J24: Chi | K24: Chi | O24: Résistance M, Absorption M, Intuition, Opposition
A25: ☢️ | B25: Toxique | C25: (continue) poison, sang, acide | D25: vs CON, FOR, PER | E25: Physique
A26: 🎭 | B26: Illusion | C26: (iLusoir) Illusion | D26: vs VOL | E26: Mental
A27: 📚 | B27: Savoir
A28: 👁️ | B28: Vision
A29: ⚔️ | B29: Acier | C29: (physique) acier | D29: vs DEX, FOR, AGI, CON, PER | E29: Physique | F29: Tangible
A30: 🛡️ | B30: Guerre | O30: Allonge (x1), Résistance (x1), Pénétration (x1), Jet critique (x2) | P30: Allonge (x1), Résistance (x1), Pénétration (x1), Jet critique (x2)
A31: 💢 | B31: Vide | C31: (origine) gravité | D31: vs EQU | E31: Physique
B32: Mixte
A33: Type de mots
A34: Base | B34: Définit les mécanismes fondamentaux sur lesquels se base le sort
A35: Liaison | B35: Associé à une base, forme ou effet, en altère les effets
A36: Forme | B36: Confère une forme plus avancé à un sort, par défaut les sorts se lance au contact
A37: Effet | B37: Définit l'effet du sort, au moins un effet est nécessaire
A38: Clé | B38: Précise un élément clé d'un effet de sort, se rattache donc forcément à un effet
A40: Un test d'incantation se confronte à la difficulté d'un sort
A41: Un sort a une difficulté basé sur la difficulté de sa base + les difficultés des autres mots
A42: Selon la forme du sort le test d'incantation se confronte aussi à une défense passive qui est déterminé par la forme, cette difficulté peut être override par l'effet
A43: Le jet d'un sort détermine sa magnétude (qui définit la puissance des effets) ET, si c'est un effet persistant, sa charge (qui définit la durée)
A44: La criticité du sort est basé sur la défense la plus haute
A46: un sort négatif peux toujours être résisté via Opposition (mi magnitude si réussie, etc)
A47: Tous les tests de sauvegarde se font contre 10 + mATT (de tradition)
A48: Tous les tests de compétence (genre acuité pour voir l'Illusion) se font contre la difficulté arcanique du sort (10 + 2 x Niv du sort)
E50: division => | F50: un mot pour diviser la charge ?
A51: Type d'effet persistants | E51: diminution => | F51: un mot global pour dimunuer les charges, moins efficace que les autres ci dessous par contre, bien plus vénère mais ciblé
A52: Conjurations (enchantements neutre) | E52: <= dissipation
A53: Enchantements négatif (affecte l'hôte négativement) | E53: <= libération
A54: Enchantements positif (affecte l'hôte positivement) | E54: <= dispertion
A55: Invocations (qui sont aussi des enchantements, mais spécifiques) | E55: <= révocation
A57: Magnitudes | B57: par catégorie | C57: moyenne (crit) | F57: par catégorie | G57: moyenne (crit) | K57: Possibilités classé par magnitude par catégories
A58: Très minoré | B58: d6-1 | C58: 2,5 (5) | E58: Très Limité | F58: d6 (max 3) +1 | G58: 3,5 (4) | K58: Très limité, très minoré | M58: 1.5
A59: Minoré | B59: d6 | C59: 3,5 (6) | E59: Limité | F59: d6 (max 4) +1 | G59: 4 (5) | K59: Très minoré & limité | M59: 2
A60: Normale | B60: d6+1 | C60: 4,5 (7) | E60: Normal | G60: 4,5 (7) | K60: Très limité & minoré | M60: 2.5
A61: Majoré | B61: d6+2 | C61: 5,5 (8) | E61: Assuré | F61: d6 (min 3) +1 | G61: 5 (7) | K61: Limité & Minoré | M61: 3
A62: Très Majoré | B62: d6+3 | C62: 6,5 (9) | E62: Très Assuré | F62: d6 (min 4) +1 | G62: 5,5 (7) | K62: Minoré | M62: 3.5
K63: Limité | M63: 4
K64: Normal | M64: 4.5
K65: Assuré | M65: 5
K66: Majoré | M66: 5.5
K67: Assuré & Majoré | M67: 6
K68: Très assuré & majoré | M68: 6.5
K69: Très majoré & assuré | M69: 7
K70: Très majoré & très assuré | M70: 7.5
A72: Drain minimum sur mana propre | D72: Nv Sort + 2
B73: 0 | C73: 1 | D73: 2 | E73: 3 | F73: 4 | G73: 5 | H73: Spell level (with NO aDitional drain cost)
A74: 4 | B74: =(10+2*B73-A74)/2 | C74: =(10+2*$C$87-A74)/2 | D74: =(10+2*$D$87-$A74)/2 | E74: =(10+2*$E$87-C74)/2 | F74: =(10+2*$F$87-$A74)/2 | G74: =(10+2*$G$87-$A74)/2
A75: 5 | B75: =(10+2*B73-A75)/2 | C75: =(10+2*$C$87-A75)/2 | D75: =(10+2*$D$87-$A75)/2 | E75: =(10+2*$E$87-$A75)/2 | F75: =(10+2*$F$87-$A75)/2 | G75: =(10+2*$G$87-$A75)/2
A76: 6 | B76: =(10+2*B73-A76)/2 | C76: =(10+2*$C$87-A76)/2 | D76: =(10+2*$D$87-$A76)/2 | E76: =(10+2*$E$87-$A76)/2 | F76: =(10+2*$F$87-$A76)/2 | G76: =(10+2*$G$87-$A76)/2
A77: 7 | B77: =(10+2*B$87-A77)/2 | C77: =(10+2*$C$87-A77)/2 | D77: =(10+2*$D$87-$A77)/2 | E77: =(10+2*$E$87-$A77)/2 | F77: =(10+2*$F$87-$A77)/2 | G77: =(10+2*$G$87-$A77)/2
A78: 8 | B78: =(10+2*B$87-A78)/2 | C78: =(10+2*$C$87-A78)/2 | D78: =(10+2*$D$87-$A78)/2 | E78: =(10+2*$E$87-$A78)/2 | F78: =(10+2*$F$87-$A78)/2 | G78: =(10+2*$G$87-$A78)/2
A79: 9 | B79: =(10+2*B$87-A79)/2 | C79: =(10+2*$C$87-A79)/2 | D79: =(10+2*$D$87-$A79)/2 | E79: =(10+2*$E$87-$A79)/2 | F79: =(10+2*$F$87-$A79)/2 | G79: =(10+2*$G$87-$A79)/2
A80: 10 | B80: =(10+2*B$87-A80)/2 | C80: =(10+2*$C$87-A80)/2 | D80: =(10+2*$D$87-$A80)/2 | E80: =(10+2*$E$87-$A80)/2 | F80: =(10+2*$F$87-$A80)/2 | G80: =(10+2*$G$87-$A80)/2
A81: mATT | B81: min 2 | C81: min 3 | D81: min 4 | E81: min 5 | F81: min 6 | G81: min 7
A84: Niveau Max d'un sort | C84: (Groupe + Compétence)/2 (arr inf) | E84: (+1 si job adéquat, +1 si rituel, +1 si pratique magique employée, virtuellement pas de niveau maximum)
A89: Destruction | B89: Détruire le matériel et l'immatériel. | H89: Verbe: Détruire
A90: Restauration | B90: Restaurer l'état des êtres vivants. | H90: Verbe: Soigner
A91: Bénédiction | B91: Appliquer des enchantements maintenus qui renforcent ou améliorent les capacités et confèrent des avantages positifs. | H91: Verbe: Augmenter | J91: Buff
A92: Malédiction | B92: Appliquer des enchantements maintenus qui affaiblissent, gênent ou réduisent les capacités par des effets négatifs. | H92: Verbe: Diminuer | J92: Dbuff
A93: Invocation | B93: Faire apparaître un être autonome (créature, esprit ou serviteur). | H93: Verbe: Appeler
A94: Abjuration | B94: Protéger ou interrompre les agressions magiques ou physiques grâce à des barrières ou des interruptions. En gros: Interruption/Annulation/Barrières et enchantements de négation. | H94: Verbe: Refuser
A95: Divination | B95: Découvrir, percevoir ou obtenir des connaissances ou des informations à travers des sorts de vision ou de sens. | H95: Verbe: Connaitre
A96: Évocation | B96: Manipuler directement la réalité ou des objets (ex. : déplacer, générer des sons, activer des mécanismes), créer de la matière. | H96: Verbe: Agir | J96: Création de matière, etc
A97: Conjuration | B97: Conjurer de la magie pure sous formes diverses (arme, mur, zone magique), toujours via des enchantements dits neutre/utilitaires. | H97: Verbe: Conjurer | J97: Neutre, enchantement de lieu/zone, enchantement qui matérialise quelque chose (arme, mur, etc)
A98: Altération | B98: Modifier les conditions physiques ou mentales d’une cible existante (conditions postives ou négatives), restaurer et modifier la matière, les objets ou la magie, enchantements qui modifient l’apparence ou l’état intrinsèque d’une cible. | H98: Verbe: Altérer | J98: Changements permanent ou temporaire (conditions, matières, etc)
D100: Fort contre (x1.5) | G100: Faible contre (x0.5)
A101: Energie | C101: Feu | D101: Froid | E101: Bois | F101: Cuir (*) | G101: Eau | H101: Terre | I101: Metal (*) | J101: FOR | K101: Intangible
A102: Energie | C102: Froid | D102: Eau | E102: Bois | F102: Tissu (*) | G102: Feu | H102: Terre | I102: Cuir (*) | J102: DEX | K102: Intangible
A103: Energie | C103: Elec | D103: Air | E103: Eau | F103: Metal (*) | G103: Bois | H103: Terre | I103: Tissu (*) | J103: AGI | K103: Intangible
A104: Matière | C104: Terre | D104: Terre | E104: Electricité | F104: Au sol | G104: Air | I104: Dans les airs | J104: FOR | K104: Tangible
A105: Matière | C105: Eau | D105: Feu | E105: Acide | F105: Dans l'eau | G105: Froid | H105: Bois | J105: DEX | K105: Tangible
A106: Matière | C106: Air | D106: Feu | E106: Electricité | F106: Dans les airs | G106: Terre | H106: Bois | I106: Au sol | J106: AGI | K106: Tangible
A107: Prime | B107: Divin | C107: Lumière | D107: Energies | G107: Matières | J107: PER | K107: Intangible
A108: Prime | B108: Occulte | C108: Ombre | D108: Energies | G108: Matières | J108: PER | K108: Intangible
A109: Origine | B109: Divin | C109: Loi | E109: Coupables (*) | F109: Chaotiques (*) | G109: Illusions | H109: Psyché | J109: VOL | K109: Intangible
A110: Origine | B110: Occulte | C110: Chaos | E110: Victimes (*) | F110: Loyalistes (*) | G110: Illusions | H110: Psyché | J110: VOL | K110: Intangible
A111: Eternel | B111: Divin | C111: Sacré | D111: Occultes | G111: ??? | J111: SAG | K111: Intangible
A112: Eternel | B112: Occulte | C112: Impie | D112: Divins | G112: ??? | J112: RUS | K112: Intangible
...

Sheet Idées
B2: Bénédiction qui a x% (magnitude) d'éviter la magie
B3: Animation d'arme (si elle est dans les mains d'un individus alors il y a un test de sauvegarde)
B4: Magie restraure un membre perdu
B5: La cible peux se statufier à volonté (pour s'endurcir ou passer inaperçu)
B6: Renvoie des projectiles x%
B7: Entendre les pensées superficielles environnantes
B8: La cible ne peux pas être attaquée | E8: Dans la zone on ne peux pas attaquer
B9: La cible ne peux pas être défendue | E9: Dans la zone on ne peux pas se défendre
B10: La cible ne peux pas se mouvoir | E10: Dans la zone on ne peux pas se déplacer
B11: Réduit la qualité d'un objet
B12: Sommeil (réveil si incident)
B13: Prédestination : Buff de l'arme contre une cible unique
B14: Séisme : dégats sur objets/structures, x tests de solidités ?
B15: imperméabilité totale (invisible à tous les sens) vs un type de cible donné
B16: La cible "pu" et inflige des pénalités à tous les individus alentours sauf si test robu réussis (pénalités réduites ?)
B17: Début du round : test de réflexes ou perte de x actions S
B18: Chaque action réalisée a x% de chance de perdre l'action
B19: Chaque action réalisée a x% de chance de ne pas consommer d'action (ou rendre ACTS ?)
B20: Achève une créature qui a moins de x PV / PS
B21: Champs de force qui empêche d'approcher/dépasser, peux être forcé via test approprié de muscu réussis
B22: Maladie + via toxique
... B37: Ench qui permet de lock une porte à ceux qui ont pas le mdp

Sheet Linguistique
A1: Structure linguistique magique :
B2: Préfixes = écoles (le moyen)
B3: Racines = effets (le quoi)
B4: Suffixes = domaines (le comment)
B5: « J’agis par [École], pour [Effet], sur [Domaine]. »
A7: École | B7: Lettre-clé | C7: Préfixes (4 variantes) | E7: Phonétique / Sens | H7: Symbole
A8: Destruction | C8: Ka-, Kor-, Kra-, Kru- | D8: Kel-, Kin- | E8: Sec, dur, explosif — frappe, brise, pulvérise | H8: ✸
A9: Restauration | C9: Re-, Ren-, Ras-, Rho- | D9: Rel-, Ryu- | E9: Doux, fluide, réparateur — soigne, restaure | H9: ⌖
A10: Bénédiction | C10: Lu-, Lux-, Lem-, Lir- | D10: Lok-, Lyn- | E10: Clair, lumineux, pur — élève, éclaire | H10: ✧
A11: Malédiction | C11: Mal-, Mor-, Mug-, Mun- | D11: Maz-, Myd- | E11: Grave, sombre, guttural — corrompt, oppresse | H11: ⧖
A12: Invocation | C12: Vo-, Van-, Vor-, Vas- | D12: Vel-, Vyn- | E12: Appel, convocation, souffle vital — fait venir | H12: ✪
A13: Abjuration | C13: Bar-, Bel-, Bas-, Bren- | D13: Bor-, Bri- | E13: Tranchant, protecteur, ferme — bloque, nie | H13: ⛊
A14: Divination | C14: Di-, Dor-, Del-, Dar- | D14: Den-, Dra- | E14: Clair, observant, précis — perçoit, révèle | H14: ⊙
A15: Évocation | C15: Ev-, En-, Elo-, Eru- | D15: Ekl-, Etr- | E15: Énergique, jaillissant — exprime, manifeste | H15: ⧉
A16: Conjuration | C16: Con-, Cen-, Col-, Car- | D16: Cym-, Cal- | E16: Formel, rituel, lié — lie, invoque, rassemble | H16: ⧗
A17: Altération | C17: Al-, Ar-, As-, Aen- | D17: Aka-, Atr- | E17: Malléable, mouvant, changeant — transforme | H17: ≈
A19: Domaine | B19: Suffixe | C19: Sens / texture sonore
A20: Feu | B20: -ar | C20: vif, sec, ardent
A21: Glace | B21: -is | C21: tranchant, froid
A22: Foudre | B22: -or | C22: claquant, électrique
A23: Terre | B23: -um | C23: massif, solide
A24: Eau | B24: -yn | C24: fluide, doux
A25: Air | B25: -el | C25: aérien, léger
A26: Lumière | B26: -ion | C26: pur, céleste
A27: Ombre | B27: -oth | C27: grave, mystérieux
A28: Loi | B28: -em | C28: structuré, rigide
A29: Chaos | B29: -ix | C29: erratique, fluide
A30: Sacre | B30: -iel | C30: harmonieux, divin
... A49: Vide | B49: -arh | C49: abyssal, neutre

Sheet Stuff
A2: Focalisateurs | B2: Catégories | C2: Capacité | D2: Prix | E2: Description capacité | H2: Notes | K2: Matières en + | L2: Améliorations uniques ?
K3: de la magicite
A5: Tatouage | B5: 0 | C5: Osmose | E5: Rapidité +5, ne peux être désarmé etc | H5: Niveau maximum des sorts = qualités | K5: Sans
A6: Bâtons | B6: 2~4 | C6: Puissance | E6: Puissance du sort augmentée (de 1 par niveau du sort) | H6: Niveau maximum des sorts = qualités | K6: Metal ou Bois | L6: Perforation +2
A7: Sceptre | B7: 2~3 | C7: Maitrise | E7: Désavantages aux défenses adverses | H7: Niveau maximum des sorts = qualités | K7: Metal ou Bois
A8: Baguettes | B8: 1~2 | C8: Malice | E8: Désavantages aux sauvegardes adverses | H8: Niveau maximum des sorts = qualités | K8: Metal ou Bois
A9: Orbes | B9: 1~3 | C9: Tactique | E9: Portée des Sorts +3 | H9: Niveau maximum des sorts = qualités | K9: Minéral | L9: Les sorts de contact peuvent utiliser la portée intégrée au focalisateur à la place
A10: Totems | B10: 1~3 | C10: Lien | E10: Peux maintenir un sort sans focus | H10: Niveau maximum des sorts = qualités | K10: Bois | L10: Réduit la corruption (sur la cible) du sort maintenue de 1 par améliorations
A11: Kriss | B11: 1~3 | C11: Versatile | E11: Considéré comme un focalisateur ET une arme de mếlée | H11: Niveau maximum des sorts = qualités | K11: Metal | L11: Opp désavantagée (si cast)
A12: Grimoire | B12: 1~3 | C12: Catalogue | E12: Peux contenir (pour usage) jusqu'à 4 sorts | H12: Niveau maximum des sorts = qualités | K12: n/a | L12: Deux sorts de plus par améliorations
A13: Focus | B13: 1~3 | C13: Stockage | E13: Peux stocker (pour lancer en ACTS) jusqu'à 2 sorts | H13: Niveau maximum des sorts = qualités | K13: Metal ou Bois | L13: Un sort de plus par améliorations
A14: Talisman | B14: 1~2 | C14: Optimisation | E14: Réduit jusquà 2 le drain minimum des sorts, le drain minimum ne peux être inférieur à 2 (ce qui est 1 en deça de la règle de base) | H14: Niveau maximum des sorts = qualités | K14: Metal
A15: Canne | B15: 2~4 | C15: Arcanes | E15: Difficultés & Tests arcaniques +2 | H15: Niveau maximum des sorts = qualités | K15: Metal
A16: Abraxas | B16: 1~3 | C16: Symbiose | E16: Les soins produisent 2 points de fatigue de moins | H16: Niveau maximum des sorts = qualités | K16: Metal
A17: Charme | B17: 1~3 | C17: Conteneur | E17: Considéré comme un focalisateur ET un catalyseur (contient des sorts prédéfinies) | H17: Niveau maximum des sorts = qualités | K17: Metal ou Bois
A18: Gantelet | B18: 1~2 | C18: Rapidité | E18: Temps de cast réduit (de 1 par niveau du sort) | H18: Niveau maximum des sorts = qualités | K18: Metal ou Tissu

Sheet Rules
D1: Moitié puis moitié puis moitié = 100+50+50+50 = 250%
A3: Enchantement de lieu | D3: De base la zone d'effet est de une case, il faut donc octroyer une zone à cet effet pour l'étendre, la cible est toujours un point dans l'espace (généralement sur le sol)
A5: Mur (élémentaire)
A6: Mur (tous) | D6: Un mur peux être placé de façon longiligne ou en cercle
A7: Mur Tangible | D7: Le mur peux être détruit et ne peux être traversé, il fait (sauf contre indications) alors [Magnitude/4] cases, la catégorie de la structure dépends du type de mur, bloque la vision
A8: Mur Intangible | D8: Le mur ne peux être détruit sauf via un élément opposé, peux être traversé, il fait (sauf contre indications) alors [Magnitude/2] cases, gêne la vision mais ne la bloque pas, considéré comme un couvert de 2 pour les tirs passant à travers, les effets sont déclanchés une fois par cible lorsque cette dernière entre dans une case ou débute son tour dedans, les dégats sont considérés comme des dégats de zone
D9: Sauf si préciser les effets sont appliqués avec [Magnitude]
D10: Si une cible subit plusieurs fois les effets d'un sol, chaques nouvelles instances augmente l'effet initial de 1/4 (et subit en une fois)
D12: Mur
A13: Intangible | B13: 🔥 | C13: Feu (feu) | D13: Provoque des dégats physiques (feu) et la condition brûlure
A14: Solide | B14: 🔥 | C14: Feu (magma) | D14: Structure de catégorie [Magnitude/8], chaque attaque reçu inflige la condition brûlure avec [Magnitude/2]
A15: Intangible | B15: ❄️ | C15: Froid (froid) | D15: Provoque des dégats physiques (froid) et la condition gel
A16: Solide | B16: ❄️ | C16: Froid (glace) | D16: Structure de catégorie [Magnitude/8], chaque attaque reçu inflige la condition gel avec [Magnitude/2]
A17: Intangible | B17: ⚡ | C17: Foudre | D17: Provoque des dégats physiques (elec) et la condition paralysie
A18: Solide | B18: 🪨 | C18: Terre | D18: Structure de catégorie [Magnitude/6], taille réduite à [Magnitude/6] cases
A19: Intangible | B19: 💧 | C19: Eau | D19: Agit comme l'action tactique de renversement avec un jet de [Magnitude]
A20: Intangible | B20: 🌪️ | C20: Air | D20: Agit comme l'action tactique de repoussement avec un jet de [Magnitude]
A21: Intangible | B21: ☀️ | C21: Lumière | D21: Provoque la condition aveugle sous sa forme avancée, bloque la vision, le couvert est de 5 à la place
A22: Intangible | B22: 🌑 | C22: Ombre | D22: Provoque la condition aveugle sous sa forme avancée, bloque la vision, le couvert est de 5 à la place
A23: Intangible | B23: ⚖️ | C23: Loi
A24: Intangible | B24: 🌀 | C24: Chaos | D24: Provoque deux conditions aléatoires (issus de la liste globale des conditions)
A25: Intangible | B25: ✨ | C25: Sacre | D25: Provoque des dégats physiques (sacré), de plus la cible subit des dégats d'attrition de [Magnitude/3]
A26: Intangible | B26: 🩸 | C26: Impie | D26: Provoque des dégats physiques (sacré), de plus la cible subit des dégats mortels de [Magnitude/4]
A27: Intangible | B27: ❤️ | C27: Vie | D27: Provoque [Magnitude] dégats physiques transperçant (vie), n'affecte que les créatures faible à cet élément (mort vivant compris)
A28: Solide | B28: ☠️ | C28: Mort | D28: Structure de catégorie [Magnitude/10], le mur régénère son intégrité de [Magnitude/2] à chaque rounds
A29: Solide | B29: 🌿 | C29: Flore (ronces) | D29: Structure de catégorie [Magnitude/10], chaque attaque reçu inflige [Magnitude/2] de dégats physique (flore)
A30: Solide | B30: 🌿 | C30: Flore (fleurs) | D30: Structure de catégorie [Magnitude/12], chaque attaque reçu inflige la condition "Spore" et "Poison"
A31: Intangible | B31: ✡️ | C31: Arcane | D31: Les sorts qui passent à travers ce mur (même par manifestation) sont augmentés de [Magnitude/5] dans un sens et réduit dans l'autre OU sont augmentés de [Magnitude/3] quelques soit le sens OU sont réduits de [Magnitude/3] quelques soit le sens, au choix du lanceur de sort
A32: Intangible | B32: 🎭 | C32: Illusion | D32: Provoque des dégats mentaux (illusion) et la condition confusion
A33: Solide | B33: ⚔️ | C33: Acier (lisse) | D33: Structure de catégorie [Magnitude/5], taille réduite à [Magnitude/8] cases, les outils subissent également un test de solidité si utilisés contre ce mur, les armes subissent en prime un désavantage à ces tests
A34: Solide | B34: ⚔️ | C34: Acier (lame) | D34: Structure de catégorie [Magnitude/5], taille réduite à [Magnitude/8] cases, chaque attaque reçu inflige des dégats physiques de [Magnitude/4], chaque attaque reçu inflige la condition saignement avec [Magnitude/4]
A35: Intangible | B35: 💢 | C35: Vide | D35: Le mur ne génère pas de couverture dans un sens (choisis au lancement) et impose une couverture augmentée de [Magnitude/6] dans l'autre
A37: Sol (élémentaire)
A38: Sol (tous) | D38: Un sol peux être placé de façon libre mais nécessairement concentrique (et à peu près répartie uniformément, en tout cas pas sous forme de ligne)
A39: Sol tangible | D39: Le sol peux est considéré comme un terrain difficile, il fait alors [Magnitude/2] cases
A40: Sol intangible | D40: Le sol n'est pas un terrain difficile, il fait alors [Magnitude] cases
D41: Sauf si préciser les effets sont appliqués avec [Magnitude/2]
D42: Si une cible subit plusieurs fois les effets d'un sol, chaques nouvelles instances augmente l'effet initial de 1/4 (et subit en une fois)
D43: Il est évidemment possible de "sauter" par dessus une surface afin de réduire la zone d'exposition en la traversant (voir les règles de sauts)
D44: Tous les effets sont modifiés par un test de réflexe (de la façon prévu par les règles de base), ce test est désavantagé si la cible est au sol ou mise au sol
D46: Sol
A47: Intangible | B47: 🔥 | C47: Feu | D47: Provoque des dégats physiques (feu) et la condition brûlure
A48: Tangible | B48: ❄️ | C48: Glace | D48: Agit comme l'action tactique de renversement avec un jet de [Magnitude]
A49: Intangible | B49: ⚡ | C49: Foudre | D49: Provoque des dégats physiques (elec) et la condition paralysie
A50: Tangible | B50: 🪨 | C50: Terre | D50: Le terrain est très difficile (allure divisée par 3 à la place)
A51: Tangible | B51: 💧 | C51: Eau | D51: La zone couverte est de [Magnitude x 2] à la place, les individus sur ces surfaces sont considérées comme faible à l'éléctricité
A52: Intangible | B52: 🌪️ | C52: Air | D52: Agit comme l'action tactique de repoussement avec un jet de [Magnitude/2], la direction de ce repoussement est aléatoire
A53: Intangible | B53: ☀️ | C53: Lumière | D53: Sur la surface il est également difficile de se cacher, imposant un désavantage aux tests de discrétion (quelque soit la forme) des cibles évoluant sur cette surface
A54: Intangible | B54: 🌑 | C54: Ombre | D54: Sur la surface il est également difficile de percevoir, imposant un désavantage aux tests d'acuité (quelque soit la forme) visant une cible évoluant sur cette surface
A55: Intangible | B55: ⚖️ | C55: Loi
A56: Intangible | B56: 🌀 | C56: Chaos | D56: Le test de réflexe est remplacé par un test de détermination, le test est effectué à chaque action de déplacement entreprise ou débutée dans la surface et en cas d'échec le personnage va dans une direction aléatoire (elle peux s'interrompre après un minimum de 3 cases)
A57: Intangible | B57: ✨ | C57: Sacre
A58: Intangible | B58: 🩸 | C58: Impie (sang) | D58: Le sang perdu est doublé (donc les PVs, mais aussi les DOTs tel que saignement) maximum [Magnitude/3], les soins de la vitalité sont réduits de moitié avec un maximum de réduction de [Magnitude/3] (mais la fatigue est calculé à partir du montant non réduit), le gain de ressources temporaire est réduit de moitié avec un maximum de réduction de [Magnitude/3]
A59: Intangible | B59: 🩸 | C59: Impie (impie) | D59: Provoque la condition malédiction et toutes les conditions (dont celle ci) voient leurs charges augmenter de [Magnitude/3]
A60: Intangible | B60: ❤️ | C60: Vie
A61: Tangible | B61: ☠️ | C61: Mort (os)
A62: Tangible | B62: 🌿 | C62: Flore (ronces) | D62: Provoque la condition infirmité et saignement, les individus sur ces surfaces sont considérées comme faible au feu
A63: Tangible | B63: 🌿 | C63: Flore (lianes) | D63: Agit comme l'action tactique de contraindre avec un jet de [Magnitude], les individus sur ces surfaces sont considérées comme faible au feu
A64: Tangible | B64: 🌿 | C64: Flore (fleurs) | D64: Provoque la condition confusion et aveugle, les individus sur ces surfaces sont considérées comme faible au feu
A65: Intangible | B65: ✡️ | C65: Arcane | D65: Le test de réflexe est remplacé par un test d'opposition, dans la zone l'usage de la magie est difficile et implique une pénalité de [Magnitude/4] aux tests, les brûlures de mana liées à un échec sont augmentées d'autant
A66: Intangible | B66: 🎭 | C66: Illusion | D66: Pas de test de sauvegarde sauf pour percer l'illusion à jour, le sol est illusoire et peux donc cacher un précipice ou autre
A67: Tangible | B67: ⚔️ | C67: Acier | D67: Provoque des dégats physique et la condition saignement
A68: Tangible | B68: ☢️ | C68: Toxique | D68: Provoque la condition poison et acide
A69: Tangible | B69: 🪷 | C69: Nature
A70: Intangible | B70: 🛡️ | C70: Guerre
D72: A revoir avec Magnitude (en dessous)
A74: Mains (élémentaires) | B74: Enchantement | C74: Base | D74: Les mains du personnage reçoivent une armure élémentaire de catégorie équivalante au niveau du sort (pour parer, etc)
C75: Energie: Immatérielle | D75: L'arme naturelle de la cible inflige désormais, en plus de ses dégats normaux, jusqu'à 2 points de dégats élémentaire par niveau de sort
C76: Matière: Matériel | D76: L'arme naturelle de la cible inflige désormais, en plus de ses dégats normaux, jusqu'à 1 points de dégats élémentaire et 1 point de dégats d'arme en plus par niveau de sort
A78: Auras (élémentaires) | B78: Enchantement | C78: Base | D78: Les cibles à moins de 2 de distance avec la cible (première occurence par tour) subit des dégats élémentaires (très limité, max 3 par dés) de représailles de catégorie (-2) équivalants au niveau du sort
D79: Si plusieurs sources de dégats de représailles sont actives alors on applique les plus élevées et y ajoute la moitié des autres uniquement
A81: Manteau (élémentaire) | B81: Enchantement | C81: Base | D81: L'adversaire qui attaque la cible en mêlée subit des dégats élémentaires de représailles de catégorie 0, ajoute 2 de perforation par niveaux, que le coup touche ou pas
D82: Les dégats de renvoie s'ajoutent en prenant le maximum en compte avec la moitié du reste
D83: DD arcanique en réflexe pour réduire les dégats de moitié
A85: Bouclier (élémentaire) | B85: Enchantement | C85: Base | D85: L'adversaire dont l'attaque de mêlée est parée par le bouclier enchanté subit des dégats élémentaires de représailles de catégorie (-1) équivalants au niveau du sort
D86: Si plusieurs sources de dégats de représailles sont actives alors on applique les plus élevées et y ajoute la moitié des autres uniquement
A88: Armure (élémentaire) | B88: Evocation | C88: Base | D88: Invoque une armure magique
D89: Durée basée sur les charges
D90: Qualité de l'arme invoquée équivalante au niveau du sort
D91: Armure de catégorie 1 (difficulté +0), 2 (+2), 3 (+4) ou 4 (+6)
D92: Absorption à l'élément +2 par niveau du sort
D93: Absorption aux éléments opposés +1 par niveau du sort
C94: Energie: Immatérielle | D94: Catégorie maximale 2
D95: Absorption +1 par niveau du sort
D96: Pas de pénalité de catégorie
C97: Matière: Matériel | D97: Catégorie maximale 4
D98: Si attaqué et touché alors dégats de représailles de catégorie (-2)
D99: Résistance, absorption et protection +1 par niveau du sort
A101: Bouclier (élémentaire) | B101: Evocation | C101: Base | D101: Invoque un bouclier magique
D102: Durée basée sur les charges
D103: Qualité du bouclier invoquée équivalante au niveau du sort
D104: Armure de catégorie 1 (difficulté +0), 2 (+2), 3 (+4) ou 4 (+6)
C105: Energie: Immatérielle | D105: Catégorie maximale 2
D106: Sur un blocage: Absorption +1 par niveau du sort, doublé si réussie
D107: Pas de pénalité de catégorie
C108: Matière: Matériel | D108: Catégorie maximale 4
D109: Si blocage réussie alors dégats de représailles de catégorie (-2)
D110: Sur un blocage: Résistance, absorption et protection +1 par niveau du sort, doublé si réussite
A112: Barrière (élémentaire) | B112: Abjuration | C112: Base | D112: Dégats des éléments opposés ou physique sont réduits de 1/3 ou -3 (le plus élevé des deux)
A113: Energies uniquement | D113: Dégats de l'élément divisés par deux ou -5 (le plus élevé des deux)
...

Sheet Stats
D1: TODO : ajouter la Guerre sur les stats (je l'ai fait uniquement sur le premier tableau, c'était simple, les autres j'ai pas trop eu le temps de comprendre la formule), sachant que Guerre est en SAG/VOL et Acier VOL/RUS désormais
D2: ★ / 2 | E2: ★ / 2 | F2: ★ / 3 | G2: ★ / 4 | H2: ★ / 4 | I2: ★ / 4 | J2: ★ / 1 | K2: ★ / 2 | L2: ★ / 4 | M2: ★ / 3
A3: Colonne 1 | B3: Domaine | C3: Total | D3: Destruction | E3: Restauration | F3: Evocation | G3: Abjuration | H3: Bénédiction | I3: Malédiction | J3: Invocation | K3: Divination | L3: Conjuration | M3: Altération | N3: Liaison | O3: Total 2
A4: 🧠 | B4: Esprit | C4: =Sum(D4:N4) | D4: =COUNTIF(Dest!I:I,CONCAT(CONCAT("*",A4),"*")) | E4: =COUNTIF(Rest!$I:$I,CONCAT(CONCAT("*",$A4),"*")) | F4: =COUNTIF(Evoc!$I:$I,CONCAT(CONCAT("*",$A4),"*")) | G4: =COUNTIF(Abju!$I:$I,CONCAT(CONCAT("*",$A4),"*")) | H4: =COUNTIF('Béné'!$I:$I,CONCAT(CONCAT("*",$A4),"*")) | I4: =COUNTIF('Malé'!$I:$I,CONCAT(CONCAT("*",$A4),"*")) | J4: =COUNTIF(Invoc!$I:$I,CONCAT(CONCAT("*",$A4),"*")) | K4: =COUNTIF(Divi!$I:$I,CONCAT(CONCAT("*",$A4),"*")) | L4: =COUNTIF(Conj!$I:$I,CONCAT(CONCAT("*",$A4),"*")) | M4: =COUNTIF('Alté'!$I:$I,CONCAT(CONCAT("*",$A4),"*")) | N4: =COUNTIF(L!$G:$G,CONCAT(CONCAT("*",$A4),"*")) | O4: =SUM(D4:M4)
A5: ⚕️ | B5: Corps | C5: =Sum(D5:N5) | D5: =COUNTIF(Dest!I:I,CONCAT(CONCAT("*",A5),"*")) | E5: =COUNTIF(Rest!$I:$I,CONCAT(CONCAT("*",$A5),"*")) | F5: =COUNTIF(Evoc!$I:$I,CONCAT(CONCAT("*",$A5),"*")) | G5: =COUNTIF(Abju!$I:$I,CONCAT(CONCAT("*",$A5),"*")) | H5: =COUNTIF('Béné'!$I:$I,CONCAT(CONCAT("*",$A5),"*")) | I5: =COUNTIF('Malé'!$I:$I,CONCAT(CONCAT("*",$A5),"*")) | J5: =COUNTIF(Invoc!$I:$I,CONCAT(CONCAT("*",$A5),"*")) | K5: =COUNTIF(Divi!$I:$I,CONCAT(CONCAT("*",$A5),"*")) | L5: =COUNTIF(Conj!$I:$I,CONCAT(CONCAT("*",$A5),"*")) | M5: =COUNTIF('Alté'!$I:$I,CONCAT(CONCAT("*",$A5),"*")) | N5: =COUNTIF(L!$G:$G,CONCAT(CONCAT("*",$A5),"*")) | O5: =SUM(D5:M5)
A6: 🎭 | B6: Illusion | C6: =Sum(D6:N6) | D6: =COUNTIF(Dest!I:I,CONCAT(CONCAT("*",A6),"*")) | E6: =COUNTIF(Rest!$I:$I,CONCAT(CONCAT("*",$A6),"*")) | F6: =COUNTIF(Evoc!$I:$I,CONCAT(CONCAT("*",$A6),"*")) | G6: =COUNTIF(Abju!$I:$I,CONCAT(CONCAT("*",$A6),"*")) | H6: =COUNTIF('Béné'!$I:$I,CONCAT(CONCAT("*",$A6),"*")) | I6: =COUNTIF('Malé'!$I:$I,CONCAT(CONCAT("*",$A6),"*")) | J6: =COUNTIF(Invoc!$I:$I,CONCAT(CONCAT("*",$A6),"*")) | K6: =COUNTIF(Divi!$I:$I,CONCAT(CONCAT("*",$A6),"*")) | L6: =COUNTIF(Conj!$I:$I,CONCAT(CONCAT("*",$A6),"*")) | M6: =COUNTIF('Alté'!$I:$I,CONCAT(CONCAT("*",$A6),"*")) | N6: =COUNTIF(L!$G:$G,CONCAT(CONCAT("*",$A6),"*")) | O6: =SUM(D6:M6)
A7: 🛡️ | B7: Guerre | C7: =Sum(D7:N7) | D7: =COUNTIF(Dest!I:I,CONCAT(CONCAT("*",A7),"*")) | E7: =COUNTIF(Rest!$I:$I,CONCAT(CONCAT("*",$A7),"*")) | F7: =COUNTIF(Evoc!$I:$I,CONCAT(CONCAT("*",$A7),"*")) | G7: =COUNTIF(Abju!$I:$I,CONCAT(CONCAT("*",$A7),"*")) | H7: =COUNTIF('Béné'!$I:$I,CONCAT(CONCAT("*",$A7),"*")) | I7: =COUNTIF('Malé'!$I:$I,CONCAT(CONCAT("*",$A7),"*")) | J7: =COUNTIF(Invoc!$I:$I,CONCAT(CONCAT("*",$A7),"*")) | K7: =COUNTIF(Divi!$I:$I,CONCAT(CONCAT("*",$A7),"*")) | L7: =COUNTIF(Conj!$I:$I,CONCAT(CONCAT("*",$A7),"*")) | M7: =COUNTIF('Alté'!$I:$I,CONCAT(CONCAT("*",$A7),"*")) | N7: =COUNTIF(L!$G:$G,CONCAT(CONCAT("*",$A7),"*")) | O7: =SUM(D7:M7)
A8: 🐗 | B8: Faune | C8: =Sum(D8:N8) | D8: =COUNTIF(Dest!I:I,CONCAT(CONCAT("*",A8),"*")) | E8: =COUNTIF(Rest!$I:$I,CONCAT(CONCAT("*",$A8),"*")) | F8: =COUNTIF(Evoc!$I:$I,CONCAT(CONCAT("*",$A8),"*")) | G8: =COUNTIF(Abju!$I:$I,CONCAT(CONCAT("*",$A8),"*")) | H8: =COUNTIF('Béné'!$I:$I,CONCAT(CONCAT("*",$A8),"*")) | I8: =COUNTIF('Malé'!$I:$I,CONCAT(CONCAT("*",$A8),"*")) | J8: =COUNTIF(Invoc!$I:$I,CONCAT(CONCAT("*",$A8),"*")) | K8: =COUNTIF(Divi!$I:$I,CONCAT(CONCAT("*",$A8),"*")) | L8: =COUNTIF(Conj!$I:$I,CONCAT(CONCAT("*",$A8),"*")) | M8: =COUNTIF('Alté'!$I:$I,CONCAT(CONCAT("*",$A8),"*")) | N8: =COUNTIF(L!$G:$G,CONCAT(CONCAT("*",$A8),"*")) | O8: =SUM(D8:M8)
A9: 💧 | B9: Eau | C9: =Sum(D9:N9) | D9: =COUNTIF(Dest!I:I,CONCAT(CONCAT("*",A9),"*")) | E9: =COUNTIF(Rest!$I:$I,CONCAT(CONCAT("*",$A9),"*")) | F9: =COUNTIF(Evoc!$I:$I,CONCAT(CONCAT("*",$A9),"*")) | G9: =COUNTIF(Abju!$I:$I,CONCAT(CONCAT("*",$A9),"*")) | H9: =COUNTIF('Béné'!$I:$I,CONCAT(CONCAT("*",$A9),"*")) | I9: =COUNTIF('Malé'!$I:$I,CONCAT(CONCAT("*",$A9),"*")) | J9: =COUNTIF(Invoc!$I:$I,CONCAT(CONCAT("*",$A9),"*")) | K9: =COUNTIF(Divi!$I:$I,CONCAT(CONCAT("*",$A9),"*")) | L9: =COUNTIF(Conj!$I:$I,CONCAT(CONCAT("*",$A9),"*")) | M9: =COUNTIF('Alté'!$I:$I,CONCAT(CONCAT("*",$A9),"*")) | N9: =COUNTIF(L!$G:$G,CONCAT(CONCAT("*",$A9),"*")) | O9: =SUM(D9:M9)
A10: ✨ | B10: Sacre | C10: =Sum(D10:N10) | D10: =COUNTIF(Dest!I:I,CONCAT(CONCAT("*",A10),"*")) | E10: =COUNTIF(Rest!$I:$I,CONCAT(CONCAT("*",$A10),"*")) | F10: =COUNTIF(Evoc!$I:$I,CONCAT(CONCAT("*",$A10),"*")) | G10: =COUNTIF(Abju!$I:$I,CONCAT(CONCAT("*",$A10),"*")) | H10: =COUNTIF('Béné'!$I:$I,CONCAT(CONCAT("*",$A10),"*")) | I10: =COUNTIF('Malé'!$I:$I,CONCAT(CONCAT("*",$A10),"*")) | J10: =COUNTIF(Invoc!$I:$I,CONCAT(CONCAT("*",$A10),"*")) | K10: =COUNTIF(Divi!$I:$I,CONCAT(CONCAT("*",$A10),"*")) | L10: =COUNTIF(Conj!$I:$I,CONCAT(CONCAT("*",$A10),"*")) | M10: =COUNTIF('Alté'!$I:$I,CONCAT(CONCAT("*",$A10),"*")) | N10: =COUNTIF(L!$G:$G,CONCAT(CONCAT("*",$A10),"*")) | O10: =SUM(D10:M10)
A11: 🌑 | B11: Ombre | C11: =Sum(D11:N11) | D11: =COUNTIF(Dest!I:I,CONCAT(CONCAT("*",A11),"*")) | E11: =COUNTIF(Rest!$I:$I,CONCAT(CONCAT("*",$A11),"*")) | F11: =COUNTIF(Evoc!$I:$I,CONCAT(CONCAT("*",$A11),"*")) | G11: =COUNTIF(Abju!$I:$I,CONCAT(CONCAT("*",$A11),"*")) | H11: =COUNTIF('Béné'!$I:$I,CONCAT(CONCAT("*",$A11),"*")) | I11: =COUNTIF('Malé'!$I:$I,CONCAT(CONCAT("*",$A11),"*")) | J11: =COUNTIF(Invoc!$I:$I,CONCAT(CONCAT("*",$A11),"*")) | K11: =COUNTIF(Divi!$I:$I,CONCAT(CONCAT("*",$A11),"*")) | L11: =COUNTIF(Conj!$I:$I,CONCAT(CONCAT("*",$A11),"*")) | M11: =COUNTIF('Alté'!$I:$I,CONCAT(CONCAT("*",$A11),"*")) | N11: =COUNTIF(L!$G:$G,CONCAT(CONCAT("*",$A11),"*")) | O11: =SUM(D11:M11)
A12: ⚡ | B12: Foudre | C12: =Sum(D12:N12) | D12: =COUNTIF(Dest!I:I,CONCAT(CONCAT("*",A12),"*")) | E12: =COUNTIF(Rest!$I:$I,CONCAT(CONCAT("*",$A12),"*")) | F12: =COUNTIF(Evoc!$I:$I,CONCAT(CONCAT("*",$A12),"*")) | G12: =COUNTIF(Abju!$I:$I,CONCAT(CONCAT("*",$A12),"*")) | H12: =COUNTIF('Béné'!$I:$I,CONCAT(CONCAT("*",$A12),"*")) | I12: =COUNTIF('Malé'!$I:$I,CONCAT(CONCAT("*",$A12),"*")) | J12: =COUNTIF(Invoc!$I:$I,CONCAT(CONCAT("*",$A12),"*")) | K12: =COUNTIF(Divi!$I:$I,CONCAT(CONCAT("*",$A12),"*")) | L12: =COUNTIF(Conj!$I:$I,CONCAT(CONCAT("*",$A12),"*")) | M12: =COUNTIF('Alté'!$I:$I,CONCAT(CONCAT("*",$A12),"*")) | N12: =COUNTIF(L!$G:$G,CONCAT(CONCAT("*",$A12),"*")) | O12: =SUM(D12:M12)
A13: ❄️ | B13: Glace | C13: =Sum(D13:N13) | D13: =COUNTIF(Dest!I:I,CONCAT(CONCAT("*",A13),"*")) | E13: =COUNTIF(Rest!$I:$I,CONCAT(CONCAT("*",$A13),"*")) | F13: =COUNTIF(Evoc!$I:$I,CONCAT(CONCAT("*",$A13),"*")) | G13: =COUNTIF(Abju!$I:$I,CONCAT(CONCAT("*",$A13),"*")) | H13: =COUNTIF('Béné'!$I:$I,CONCAT(CONCAT("*",$A13),"*")) | I13: =COUNTIF('Malé'!$I:$I,CONCAT(CONCAT("*",$A13),"*")) | J13: =COUNTIF(Invoc!$I:$I,CONCAT(CONCAT("*",$A13),"*")) | K13: =COUNTIF(Divi!$I:$I,CONCAT(CONCAT("*",$A13),"*")) | L13: =COUNTIF(Conj!$I:$I,CONCAT(CONCAT("*",$A13),"*")) | M13: =COUNTIF('Alté'!$I:$I,CONCAT(CONCAT("*",$A13),"*")) | N13: =COUNTIF(L!$G:$G,CONCAT(CONCAT("*",$A13),"*")) | O13: =SUM(D13:M13)
A14: 📚 | B14: Savoir | C14: =Sum(D14:N14) | D14: =COUNTIF(Dest!I:I,CONCAT(CONCAT("*",A14),"*")) | E14: =COUNTIF(Rest!$I:$I,CONCAT(CONCAT("*",$A14),"*")) | F14: =COUNTIF(Evoc!$I:$I,CONCAT(CONCAT("*",$A14),"*")) | G14: =COUNTIF(Abju!$I:$I,CONCAT(CONCAT("*",$A14),"*")) | H14: =COUNTIF('Béné'!$I:$I,CONCAT(CONCAT("*",$A14),"*")) | I14: =COUNTIF('Malé'!$I:$I,CONCAT(CONCAT("*",$A14),"*")) | J14: =COUNTIF(Invoc!$I:$I,CONCAT(CONCAT("*",$A14),"*")) | K14: =COUNTIF(Divi!$I:$I,CONCAT(CONCAT("*",$A14),"*")) | L14: =COUNTIF(Conj!$I:$I,CONCAT(CONCAT("*",$A14),"*")) | M14: =COUNTIF('Alté'!$I:$I,CONCAT(CONCAT("*",$A14),"*")) | N14: =COUNTIF(L!$G:$G,CONCAT(CONCAT("*",$A14),"*")) | O14: =SUM(D14:M14)
A15: 🔥 | B15: Feu | C15: =Sum(D15:N15) | D15: =COUNTIF(Dest!I:I,CONCAT(CONCAT("*",A15),"*")) | E15: =COUNTIF(Rest!$I:$I,CONCAT(CONCAT("*",$A15),"*")) | F15: =COUNTIF(Evoc!$I:$I,CONCAT(CONCAT("*",$A15),"*")) | G15: =COUNTIF(Abju!$I:$I,CONCAT(CONCAT("*",$A15),"*")) | H15: =COUNTIF('Béné'!$I:$I,CONCAT(CONCAT("*",$A15),"*")) | I15: =COUNTIF('Malé'!$I:$I,CONCAT(CONCAT("*",$A15),"*")) | J15: =COUNTIF(Invoc!$I:$I,CONCAT(CONCAT("*",$A15),"*")) | K15: =COUNTIF(Divi!$I:$I,CONCAT(CONCAT("*",$A15),"*")) | L15: =COUNTIF(Conj!$I:$I,CONCAT(CONCAT("*",$A15),"*")) | M15: =COUNTIF('Alté'!$I:$I,CONCAT(CONCAT("*",$A15),"*")) | N15: =COUNTIF(L!$G:$G,CONCAT(CONCAT("*",$A15),"*")) | O15: =SUM(D15:M15)
... A33: ☠️ | B33: Mort | C33: =Sum(D33:N33) | D33: =COUNTIF(Dest!I:I,CONCAT(CONCAT("*",A33),"*")) | E33: =COUNTIF(Rest!$I:$I,CONCAT(CONCAT("*",$A33),"*")) | F33: =COUNTIF(Evoc!$I:$I,CONCAT(CONCAT("*",$A33),"*")) | G33: =COUNTIF(Abju!$I:$I,CONCAT(CONCAT("*",$A33),"*")) | H33: =COUNTIF('Béné'!$I:$I,CONCAT(CONCAT("*",$A33),"*")) | I33: =COUNTIF('Malé'!$I:$I,CONCAT(CONCAT("*",$A33),"*")) | J33: =COUNTIF(Invoc!$I:$I,CONCAT(CONCAT("*",$A33),"*")) | K33: =COUNTIF(Divi!$I:$I,CONCAT(CONCAT("*",$A33),"*")) | L33: =COUNTIF(Conj!$I:$I,CONCAT(CONCAT("*",$A33),"*")) | M33: =COUNTIF('Alté'!$I:$I,CONCAT(CONCAT("*",$A33),"*")) | N33: =COUNTIF(L!$G:$G,CONCAT(CONCAT("*",$A33),"*")) | O33: =SUM(D33:M33)
B34: Total | C34: =Sum(D34:N34) | D34: =SUM(D3:D33) | E34: =SUM(E3:E33) | F34: =SUM(F3:F33) | G34: =SUM(G3:G33) | H34: =SUM(H3:H33) | I34: =SUM(I3:I33) | J34: =SUM(J3:J33) | K34: =SUM(K3:K33) | ... M34: =SUM(M3:M33) | N34: =COUNTIF(L!$G:$G,CONCAT(CONCAT("*",$A34),"*")) | O34: =SUM(D34:M34)
B37: SAG | C37: INT | D37: VOL | E37: RUS | F37: CHA
B38: =B82+Tableau1[[#TOTALS],[SAG]] | C38: =C82+Tableau1[[#TOTALS],[INT]] | D38: =D82+Tableau1[[#TOTALS],[VOL]] | E38: =E82+Tableau1[[#TOTALS],[RUS]] | F38: =F82+Tableau1[[#TOTALS],[CHA]]
A52: Domaine | B52: SAG | C52: INT | D52: VOL | E52: RUS | F52: CHA
A53: Feu | B53: =if(LOOKUP($A53,Stats!$A$115:$A$143,Stats!B$115:B$143)=1,VLOOKUP($A53,$B$4:$C$32,2,FALSE),0) | C53: =if(LOOKUP($A53,Stats!$A$115:$A$143,Stats!C$115:C$143)=1,VLOOKUP($A53,$B$4:$C$33,2,FALSE),0) | D53: =if(LOOKUP($A53,Stats!$A$115:$A$143,Stats!D$115:D$143)=1,VLOOKUP($A53,$B$4:$C$32,2,FALSE),0) | E53: =if(LOOKUP($A53,Stats!$A$115:$A$143,Stats!E$115:E$143)=1,VLOOKUP($A53,$B$4:$C$33,2,FALSE),0) | F53: =if(LOOKUP($A53,Stats!$A$115:$A$143,Stats!F$115:F$143)=1,VLOOKUP($A53,$B$4:$C$32,2,FALSE),0)
A54: Glace | B54: =if(LOOKUP($A54,Stats!$A$115:$A$143,Stats!B$115:B$143)=1,VLOOKUP($A54,$B$4:$C$32,2,FALSE),0) | C54: =if(LOOKUP($A54,Stats!$A$115:$A$143,Stats!C$115:C$143)=1,VLOOKUP($A54,$B$4:$C$33,2,FALSE),0) | D54: =if(LOOKUP($A54,Stats!$A$115:$A$143,Stats!D$115:D$143)=1,VLOOKUP($A54,$B$4:$C$32,2,FALSE),0) | E54: =if(LOOKUP($A54,Stats!$A$115:$A$143,Stats!E$115:E$143)=1,VLOOKUP($A54,$B$4:$C$33,2,FALSE),0) | F54: =if(LOOKUP($A54,Stats!$A$115:$A$143,Stats!F$115:F$143)=1,VLOOKUP($A54,$B$4:$C$32,2,FALSE),0)
A55: Foudre | B55: =if(LOOKUP($A55,Stats!$A$115:$A$143,Stats!B$115:B$143)=1,VLOOKUP($A55,$B$4:$C$32,2,FALSE),0) | C55: =if(LOOKUP($A55,Stats!$A$115:$A$143,Stats!C$115:C$143)=1,VLOOKUP($A55,$B$4:$C$33,2,FALSE),0) | D55: =if(LOOKUP($A55,Stats!$A$115:$A$143,Stats!D$115:D$143)=1,VLOOKUP($A55,$B$4:$C$32,2,FALSE),0) | E55: =if(LOOKUP($A55,Stats!$A$115:$A$143,Stats!E$115:E$143)=1,VLOOKUP($A55,$B$4:$C$33,2,FALSE),0) | F55: =if(LOOKUP($A55,Stats!$A$115:$A$143,Stats!F$115:F$143)=1,VLOOKUP($A55,$B$4:$C$32,2,FALSE),0)
A56: Terre | B56: =if(LOOKUP($A56,Stats!$A$115:$A$143,Stats!B$115:B$143)=1,VLOOKUP($A56,$B$4:$C$32,2,FALSE),0) | C56: =if(LOOKUP($A56,Stats!$A$115:$A$143,Stats!C$115:C$143)=1,VLOOKUP($A56,$B$4:$C$33,2,FALSE),0) | D56: =if(LOOKUP($A56,Stats!$A$115:$A$143,Stats!D$115:D$143)=1,VLOOKUP($A56,$B$4:$C$32,2,FALSE),0) | E56: =if(LOOKUP($A56,Stats!$A$115:$A$143,Stats!E$115:E$143)=1,VLOOKUP($A56,$B$4:$C$33,2,FALSE),0) | F56: =if(LOOKUP($A56,Stats!$A$115:$A$143,Stats!F$115:F$143)=1,VLOOKUP($A56,$B$4:$C$32,2,FALSE),0)
A57: Eau | B57: =if(LOOKUP($A57,Stats!$A$115:$A$143,Stats!B$115:B$143)=1,VLOOKUP($A57,$B$4:$C$32,2,FALSE),0) | C57: =if(LOOKUP($A57,Stats!$A$115:$A$143,Stats!C$115:C$143)=1,VLOOKUP($A57,$B$4:$C$33,2,FALSE),0) | D57: =if(LOOKUP($A57,Stats!$A$115:$A$143,Stats!D$115:D$143)=1,VLOOKUP($A57,$B$4:$C$32,2,FALSE),0) | E57: =if(LOOKUP($A57,Stats!$A$115:$A$143,Stats!E$115:E$143)=1,VLOOKUP($A57,$B$4:$C$33,2,FALSE),0) | F57: =if(LOOKUP($A57,Stats!$A$115:$A$143,Stats!F$115:F$143)=1,VLOOKUP($A57,$B$4:$C$32,2,FALSE),0)
A58: Air | B58: =if(LOOKUP($A58,Stats!$A$115:$A$143,Stats!B$115:B$143)=1,VLOOKUP($A58,$B$4:$C$32,2,FALSE),0) | C58: =if(LOOKUP($A58,Stats!$A$115:$A$143,Stats!C$115:C$143)=1,VLOOKUP($A58,$B$4:$C$33,2,FALSE),0) | D58: =if(LOOKUP($A58,Stats!$A$115:$A$143,Stats!D$115:D$143)=1,VLOOKUP($A58,$B$4:$C$32,2,FALSE),0) | E58: =if(LOOKUP($A58,Stats!$A$115:$A$143,Stats!E$115:E$143)=1,VLOOKUP($A58,$B$4:$C$33,2,FALSE),0) | F58: =if(LOOKUP($A58,Stats!$A$115:$A$143,Stats!F$115:F$143)=1,VLOOKUP($A58,$B$4:$C$32,2,FALSE),0)
A59: Lumière | B59: =if(LOOKUP($A59,Stats!$A$115:$A$143,Stats!B$115:B$143)=1,VLOOKUP($A59,$B$4:$C$32,2,FALSE),0) | C59: =if(LOOKUP($A59,Stats!$A$115:$A$143,Stats!C$115:C$143)=1,VLOOKUP($A59,$B$4:$C$33,2,FALSE),0) | D59: =if(LOOKUP($A59,Stats!$A$115:$A$143,Stats!D$115:D$143)=1,VLOOKUP($A59,$B$4:$C$32,2,FALSE),0) | E59: =if(LOOKUP($A59,Stats!$A$115:$A$143,Stats!E$115:E$143)=1,VLOOKUP($A59,$B$4:$C$33,2,FALSE),0) | F59: =if(LOOKUP($A59,Stats!$A$115:$A$143,Stats!F$115:F$143)=1,VLOOKUP($A59,$B$4:$C$32,2,FALSE),0)
A60: Ombre | B60: =if(LOOKUP($A60,Stats!$A$115:$A$143,Stats!B$115:B$143)=1,VLOOKUP($A60,$B$4:$C$32,2,FALSE),0) | C60: =if(LOOKUP($A60,Stats!$A$115:$A$143,Stats!C$115:C$143)=1,VLOOKUP($A60,$B$4:$C$33,2,FALSE),0) | D60: =if(LOOKUP($A60,Stats!$A$115:$A$143,Stats!D$115:D$143)=1,VLOOKUP($A60,$B$4:$C$32,2,FALSE),0) | E60: =if(LOOKUP($A60,Stats!$A$115:$A$143,Stats!E$115:E$143)=1,VLOOKUP($A60,$B$4:$C$33,2,FALSE),0) | F60: =if(LOOKUP($A60,Stats!$A$115:$A$143,Stats!F$115:F$143)=1,VLOOKUP($A60,$B$4:$C$32,2,FALSE),0)
A61: Loi | B61: =if(LOOKUP($A61,Stats!$A$115:$A$143,Stats!B$115:B$143)=1,VLOOKUP($A61,$B$4:$C$32,2,FALSE),0) | C61: =if(LOOKUP($A61,Stats!$A$115:$A$143,Stats!C$115:C$143)=1,VLOOKUP($A61,$B$4:$C$33,2,FALSE),0) | D61: =if(LOOKUP($A61,Stats!$A$115:$A$143,Stats!D$115:D$143)=1,VLOOKUP($A61,$B$4:$C$32,2,FALSE),0) | E61: =if(LOOKUP($A61,Stats!$A$115:$A$143,Stats!E$115:E$143)=1,VLOOKUP($A61,$B$4:$C$33,2,FALSE),0) | F61: =if(LOOKUP($A61,Stats!$A$115:$A$143,Stats!F$115:F$143)=1,VLOOKUP($A61,$B$4:$C$32,2,FALSE),0)
A62: Chaos | B62: =if(LOOKUP($A62,Stats!$A$115:$A$143,Stats!B$115:B$143)=1,VLOOKUP($A62,$B$4:$C$32,2,FALSE),0) | C62: =if(LOOKUP($A62,Stats!$A$115:$A$143,Stats!C$115:C$143)=1,VLOOKUP($A62,$B$4:$C$33,2,FALSE),0) | D62: =if(LOOKUP($A62,Stats!$A$115:$A$143,Stats!D$115:D$143)=1,VLOOKUP($A62,$B$4:$C$32,2,FALSE),0) | E62: =if(LOOKUP($A62,Stats!$A$115:$A$143,Stats!E$115:E$143)=1,VLOOKUP($A62,$B$4:$C$33,2,FALSE),0) | F62: =if(LOOKUP($A62,Stats!$A$115:$A$143,Stats!F$115:F$143)=1,VLOOKUP($A62,$B$4:$C$32,2,FALSE),0)
A63: Sacre | B63: =if(LOOKUP($A63,Stats!$A$115:$A$143,Stats!B$115:B$143)=1,VLOOKUP($A63,$B$4:$C$32,2,FALSE),0) | C63: =if(LOOKUP($A63,Stats!$A$115:$A$143,Stats!C$115:C$143)=1,VLOOKUP($A63,$B$4:$C$33,2,FALSE),0) | D63: =if(LOOKUP($A63,Stats!$A$115:$A$143,Stats!D$115:D$143)=1,VLOOKUP($A63,$B$4:$C$32,2,FALSE),0) | E63: =if(LOOKUP($A63,Stats!$A$115:$A$143,Stats!E$115:E$143)=1,VLOOKUP($A63,$B$4:$C$33,2,FALSE),0) | F63: =if(LOOKUP($A63,Stats!$A$115:$A$143,Stats!F$115:F$143)=1,VLOOKUP($A63,$B$4:$C$32,2,FALSE),0)
A64: Impie | B64: =if(LOOKUP($A64,Stats!$A$115:$A$143,Stats!B$115:B$143)=1,VLOOKUP($A64,$B$4:$C$32,2,FALSE),0) | C64: =if(LOOKUP($A64,Stats!$A$115:$A$143,Stats!C$115:C$143)=1,VLOOKUP($A64,$B$4:$C$33,2,FALSE),0) | D64: =if(LOOKUP($A64,Stats!$A$115:$A$143,Stats!D$115:D$143)=1,VLOOKUP($A64,$B$4:$C$32,2,FALSE),0) | E64: =if(LOOKUP($A64,Stats!$A$115:$A$143,Stats!E$115:E$143)=1,VLOOKUP($A64,$B$4:$C$33,2,FALSE),0) | F64: =if(LOOKUP($A64,Stats!$A$115:$A$143,Stats!F$115:F$143)=1,VLOOKUP($A64,$B$4:$C$32,2,FALSE),0)
... A80: Acier | B80: =if(LOOKUP($A80,Stats!$A$115:$A$143,Stats!B$115:B$143)=1,VLOOKUP($A80,$B$4:$C$32,2,FALSE),0) | C80: =if(LOOKUP($A80,Stats!$A$115:$A$143,Stats!C$115:C$143)=1,VLOOKUP($A80,$B$4:$C$33,2,FALSE),0) | D80: =if(LOOKUP($A80,Stats!$A$115:$A$143,Stats!D$115:D$143)=1,VLOOKUP($A80,$B$4:$C$32,2,FALSE),0) | E80: =if(LOOKUP($A80,Stats!$A$115:$A$143,Stats!E$115:E$143)=1,VLOOKUP($A80,$B$4:$C$33,2,FALSE),0) | F80: =if(LOOKUP($A80,Stats!$A$115:$A$143,Stats!F$115:F$143)=1,VLOOKUP($A80,$B$4:$C$32,2,FALSE),0)
A81: Vide | B81: =if(LOOKUP($A81,Stats!$A$115:$A$143,Stats!B$115:B$143)=1,VLOOKUP($A81,$B$4:$C$32,2,FALSE),0) | C81: =if(LOOKUP($A81,Stats!$A$115:$A$143,Stats!C$115:C$143)=1,VLOOKUP($A81,$B$4:$C$32,2,FALSE),0) | D81: =if(LOOKUP($A81,Stats!$A$115:$A$143,Stats!D$115:D$143)=1,VLOOKUP($A81,$B$4:$C$32,2,FALSE),0) | E81: =if(LOOKUP($A81,Stats!$A$115:$A$143,Stats!E$115:E$143)=1,VLOOKUP($A81,$B$4:$C$32,2,FALSE),0) | F81: =if(LOOKUP($A81,Stats!$A$115:$A$143,Stats!F$115:F$143)=1,VLOOKUP($A81,$B$4:$C$32,2,FALSE),0)
A82: . Total | B82: =SUM(Tableau2[SAG]) | C82: =SUM(Tableau2[INT]) | D82: =SUM(Tableau2[VOL]) | E82: =SUM(Tableau2[RUS]) | F82: =SUM(Tableau2[CHA])
A85: Ecole | B85: SAG | C85: INT | D85: VOL | E85: RUS | F85: CHA
A86: Destruction | B86: =if(B100=1,$D$34,0) | C86: =if(C100=1,$D$34,0) | D86: =if(D100=1,$D$34,0) | E86: =if(E100=1,$D$34,0) | F86: =if(F100=1,$D$34,0)
A87: Restauration | B87: =if(B101=1,$E$34,0) | C87: =if(C101=1,$E$34,0) | D87: =if(D101=1,$E$34,0) | E87: =if(E101=1,$E$34,0) | F87: =if(F101=1,$E$34,0)
A88: Evocation | B88: =if(B102=1,$F$34,0) | C88: =if(C102=1,$F$34,0) | D88: =if(D102=1,$F$34,0) | E88: =if(E102=1,$F$34,0) | F88: =if(F102=1,$F$34,0)
A89: Abjuration | B89: =if(B103=1,$G$34,0) | C89: =if(C103=1,$G$34,0) | D89: =if(D103=1,$G$34,0) | E89: =if(E103=1,$G$34,0) | F89: =if(F103=1,$G$34,0)
A90: Bénédiction | B90: =if(B104=1,$H$34,0) | C90: =if(C104=1,$H$34,0) | D90: =if(D104=1,$H$34,0) | E90: =if(E104=1,$H$34,0) | F90: =if(F104=1,$H$34,0)
A91: Malédiction | B91: =if(B105=1,$I$34,0) | C91: =if(C105=1,$I$34,0) | D91: =if(D105=1,$I$34,0) | E91: =if(E105=1,$I$34,0) | F91: =if(F105=1,$I$34,0)
A92: Invocation | B92: =if(B106=1,$J$34,0) | C92: =if(C106=1,$J$34,0) | D92: =if(D106=1,$J$34,0) | E92: =if(E106=1,$J$34,0) | F92: =if(F106=1,$J$34,0)
A93: Divination | B93: =if(B107=1,$K$34,0) | C93: =if(C107=1,$K$34,0) | D93: =if(D107=1,$K$34,0) | E93: =if(E107=1,$K$34,0) | F93: =if(F107=1,$K$34,0)
A94: Conjuration | B94: =if(B108=1,$L$34,0) | C94: =if(C108=1,$L$34,0) | D94: =if(D108=1,$L$34,0) | E94: =if(E108=1,$L$34,0) | F94: =if(F108=1,$L$34,0)
A95: Altération | B95: =if(B109=1,$M$34,0) | C95: =if(C109=1,$M$34,0) | D95: =if(D109=1,$M$34,0) | E95: =if(E109=1,$M$34,0) | F95: =if(F109=1,$M$34,0)
A96: Total | B96: =SUM(B86:B95) | C96: =SUM(C86:C95) | D96: =SUM(D86:D95) | E96: =SUM(E86:E95) | F96: =SUM(F86:F95)
A99: Colonne 1 | B99: SAG | C99: INT | D99: VOL | E99: RUS | F99: CHA | G99: Total Accés
A100: Destruction | C100: 1 | D100: 1 | G100: =SUM(B100:F100)
A101: Restauration | B101: 1 | F101: 1 | G101: =SUM(B101:F101)
A102: Evocation | C102: 1 | F102: 1 | G102: =SUM(B102:F102)
A103: Abjuration | C103: 1 | F103: 1 | G103: =SUM(B103:F103)
A104: Bénédiction | B104: 1 | F104: 1 | G104: =SUM(B104:F104)
A105: Malédiction | B105: 1 | E105: 1 | G105: =SUM(B105:F105)
A106: Invocation | D106: 1 | E106: 1 | G106: =SUM(B106:F106)
A107: Divination | B107: 1 | E107: 1 | G107: =SUM(B107:F107)
A108: Conjuration | D108: 1 | E108: 1 | G108: =SUM(B108:F108)
A109: Altération | C109: 1 | D109: 1 | G109: =SUM(B109:F109)
A110: Total | B110: =SUM(B100:B109) | C110: =SUM(C100:C109) | D110: =SUM(D100:D109) | E110: =SUM(E100:E109) | F110: =SUM(F100:F109)
A113: Domaine | B113: SAG | C113: INT | D113: VOL | E113: RUS | F113: CHA | G113: Total Accés
A114: Guerre | B114: 1 | D114: 1 | G114: =SUM(B114:F114)
A115: Acier | D115: 1 | E115: 1 | G115: =SUM(B115:F115)
A116: Air | B116: 1 | C116: 1 | G116: =SUM(B116:F116)
A117: Arcane | C117: 1 | E117: 1 | G117: =SUM(B117:F117)
A118: Chaos | E118: 1 | F118: 1 | G118: =SUM(B118:F118)
A119: Charme | E119: 1 | F119: 1 | G119: =SUM(B119:F119)
A120: Corps | B120: 1 | F120: 1 | G120: =SUM(B120:F120)
A121: Eau | B121: 1 | C121: 1 | G121: =SUM(B121:F121)
A122: Esprit | B122: 1 | F122: 1 | G122: =SUM(B122:F122)
A123: Faune | B123: 1 | D123: 1 | G123: =SUM(B123:F123)
A124: Feu | C124: 1 | D124: 1 | G124: =SUM(B124:F124)
A125: Flore | B125: 1 | D125: 1 | G125: =SUM(B125:F125)
A126: Foudre | C126: 1 | D126: 1 | G126: =SUM(B126:F126)
A127: Glace | C127: 1 | D127: 1 | G127: =SUM(B127:F127)
A128: Illusion | E128: 1 | F128: 1 | G128: =SUM(B128:F128)
A129: Impie | D129: 1 | E129: 1 | G129: =SUM(B129:F129)
A130: Loi | B130: 1 | F130: 1 | G130: =SUM(B130:F130)
A131: Lumière | B131: 1 | F131: 1 | G131: =SUM(B131:F131)
A132: Magie | C132: 1 | D132: 1 | G132: =SUM(B132:F132)
A133: Mental | E133: 1 | F133: 1 | G133: =SUM(B133:F133)
A134: Mort | C134: 1 | E134: 1 | G134: =SUM(B134:F134)
A135: Nature | B135: 1 | D135: 1 | G135: =SUM(B135:F135)
A136: Ombre | E136: 1 | F136: 1 | G136: =SUM(B136:F136)
A137: Sacre | B137: 1 | D137: 1 | G137: =SUM(B137:F137)
A138: Savoir | C138: 1 | F138: 1 | G138: =SUM(B138:F138)
A139: Terre | B139: 1 | C139: 1 | G139: =SUM(B139:F139)
A140: Toxique | E140: 1 | F140: 1 | G140: =SUM(B140:F140)
A141: Vide | C141: 1 | D141: 1 | G141: =SUM(B141:F141)
A142: Vie | B142: 1 | D142: 1 | G142: =SUM(B142:F142)
A143: Vision | C143: 1 | E143: 1 | G143: =SUM(B143:E143)
B144: =SUM(B114:B143) | C144: =SUM(C114:C143) | D144: =SUM(D114:D143) | E144: =SUM(E114:E143) | F144: =SUM(F114:F143) | G144: =SUM(G115:G143)

Sheet Sorts
A1: Ecole/Domaine | B1: Titre | D1: Description | H1: Mot de Pouvoir (vulguaire) | I1: Clé | K1: Diffusion | L1: Propagation | M1: Structure | N1: Avancé | P1: Liaison 1 | Q1: Liaison 2 | R1: Liaison 3 | S1: Notes | T1: 2nd Mot | U1: Clé 2nd Mot | V1: Mot lié | W1: Clé lié | X1: Description (if any)
A2: Destruction | B2: Trait de Foudre | H2: =Dest!J3 | I2: ='Règles'!C158 | K2: =F!$A$4 | L2: =F!$A$11 | S2: =Dest!N3
A3: Destruction | B3: Cône de Glace | H3: =Dest!J3 | I3: ='Règles'!C157 | K3: =F!$A$3 | L3: =F!$A$17 | S3: =Dest!N3
A4: Destruction | B4: Boule de Feu | H4: =Dest!J3 | I4: ='Règles'!C156 | K4: =F!$A$4 | L4: =F!$A$11 | M4: =F!$A$27 | S4: =Dest!N3
A5: Destruction | B5: Déflagration Psychique | H5: =Dest!J7 | I5: ='Règles'!C174 | K5: =F!$A$2 | L5: =F!$A$13 | P5: =L!$A$4 | S5: =Dest!N7
A6: Destruction | B6: Doigt de Fissure | H6: =Dest!J35 | I6: ='Règles'!C159 | K6: =F!$A$3 | L6: =F!$A$11 | S6: =Dest!N35
A7: Destruction | B7: Doigt de Désintégration | H7: =Dest!J57 | I7: ='Règles'!C156 | K7: =F!$A$3 | L7: =F!$A$11 | S7: =Dest!N57
A8: Destruction | B8: Trou de Mémoire | H8: =Dest!J56 | I8: ='Règles'!C174 | K8: =F!$A$5 | L8: =F!$A$11 | S8: =Dest!N56
A9: Destruction | B9: Mot de Mort | H9: =Dest!J58 | I9: ='Règles'!C169 | K9: =F!$A$6 | L9: =F!$A$11 | S9: =Dest!N58
A10: Destruction | B10: Présage Sanglant | H10: =Dest!J65 | I10: ='Règles'!C167 | K10: =F!$A$5 | L10: =F!$A$11 | S10: =Dest!N65
A11: Destruction | B11: Myriade de Flèches Acide | D11: changer le nom ? | H11: =Dest!J18 | I11: ='Règles'!C179 | K11: =F!$A$4 | L11: =F!$A$11 | M11: =F!$A$38 | S11: =Dest!N18
A12: Destruction | B12: Oeil du Cyclone | H12: =Dest!J16 | I12: ='Règles'!C161 | K12: =F!$A$2 | L12: =F!$A$13 | P12: =L!$A$4 | S12: =Dest!N16
A13: Destruction | B13: Flèche de Feu | H13: =Dest!J3 | I13: ='Règles'!C158 | K13: =F!$A$4 | L13: =F!$A$11 | P13: =L!$A$3 | S13: =Dest!N3
A14: Restauration | B14: Soin du corps | H14: =Rest!J3 | I14: ='Règles'!C168 | K14: =F!$A$5 | L14: =F!$A$11 | S14: =Rest!N3
A15: Restauration | B15: Soin de l'esprit | H15: =Rest!J3 | I15: ='Règles'!C174 | K15: =F!$A$5 | L15: =F!$A$11 | S15: =Rest!N3
A16: Restauration | B16: Soin d'endurance | H16: =Rest!J5 | I16: ='Règles'!C178 | K16: =F!$A$5 | L16: =F!$A$11 | S16: =Rest!N5
A17: Restauration | B17: Cercle de soin | H17: =Rest!J3 | I17: ='Règles'!C168 | K17: =F!$A$2 | L17: =F!$A$18 | S17: =Rest!N3
A18: Restauration | B18: Remède Universel | H18: =Rest!J13 | I18: ='Règles'!C170 | K18: =F!$A$5 | L18: =F!$A$11 | N18: =A!A3 | P18: =L!A6 | S18: Le même mot est utilisé deux fois : Une fois pour le corps, une fois pour l'esprit | T18: =Rest!J13 | U18: 🧠 Esprit: Rasneutays
A19: Restauration | B19: Soin des blessures | H19: =Rest!J19 | I19: ='Règles'!C170 | K19: =F!$A$5 | L19: =F!$A$11 | S19: =Rest!N19
A20: Restauration | B20: Retour à la Vie | H20: =Rest!J21 | I20: ='Règles'!C168 | K20: =F!$A$5 | L20: =F!$A$11 | S20: =Rest!N21
A21: Restauration | B21: Don de Régénération | H21: =Rest!J33 | I21: ='Règles'!C168 | K21: =F!$A$5 | L21: =F!$A$11 | S21: =Rest!N33
A22: Restauration | B22: Premiers Soins | H22: =Rest!J29 | I22: ='Règles'!C168 | K22: =F!$A$5 | L22: =F!$A$11 | S22: =Rest!N29
A23: Restauration | B23: Illusion des Grandeurs | H23: =Rest!J8 | I23: ='Règles'!C180 | K23: =F!$A$5 | L23: =F!$A$11 | S23: =Rest!N8
A24: Restauration | B24: Sanctuaire | H24: =Rest!J5 | I24: ='Règles'!C178 | K24: =F!$A$5 | L24: =F!$A$18 | M24: =F!$A$24 | P24: =L!$A$4 | S24: =Rest!N5
A25: Bénédiction | B25: Croissance Physique | H25: ='Béné'!J52 | I25: ⚕️ Corps: Luxlevoen | K25: =F!$A$5 | L25: =F!$A$11 | S25: ='Béné'!N53
A26: Bénédiction | B26: Croissance Mentale | H26: ='Béné'!J52 | I26: 🧠 Esprit: Luxlevoys | K26: =F!$A$5 | L26: =F!$A$11 | S26: ='Béné'!N53
A27: Bénédiction | B27: Surcroissance Bestiale | H27: ='Béné'!J54 | I27: ='Règles'!C172 | K27: =F!$A$5 | L27: =F!$A$11 | S27: ='Béné'!N54
A28: Bénédiction | B28: Surcroissance Spirituelle | H28: ='Béné'!J55 | I28: ='Règles'!C174 | K28: =F!$A$5 | L28: =F!$A$11 | S28: ='Béné'!N55
A29: Bénédiction | B29: Amplification des Instincts | H29: ='Béné'!J44 | I29: ='Règles'!C178 | K29: =F!$A$5 | L29: =F!$A$11 | S29: ='Béné'!N69
A30: Bénédiction | B30: Bénédiction des Justes | H30: ='Béné'!J113 | I30: ='Règles'!C166 | K30: =F!$A$5 | L30: =F!$A$11 | S30: ='Béné'!N113
A31: Bénédiction | B31: Protection Physique | H31: ='Béné'!J123 | I31: ='Règles'!C184 | K31: =F!$A$5 | L31: =F!$A$11 | S31: ='Béné'!N123
A32: Bénédiction | B32: Célérité des Vents | H32: ='Béné'!J127 | I32: ='Règles'!C161 | K32: =F!$A$5 | L32: =F!$A$11 | S32: ='Béné'!N127
A33: Bénédiction | B33: Echos de la Guerre | H33: ='Béné'!J153 | I33: ='Règles'!C184 | K33: =F!$A$5 | L33: =F!$A$11 | S33: ='Béné'!N153
A34: Bénédiction | B34: Alléger le Fardeau | H34: ='Béné'!J166 | I34: ='Règles'!C178 | K34: =F!$A$5 | L34: =F!$A$11 | S34: ='Béné'!N166
A35: Malédiction | B35: Affaiblissement du Corps | H35: ='Malé'!J70 | I35: ='Règles'!C170 | K35: =F!$A$5 | L35: =F!$A$11 | S35: ='Malé'!N70
A36: Malédiction | B36: Dépérissement de l'Esprit | H36: ='Malé'!J70 | I36: ='Règles'!C171 | K36: =F!$A$5 | L36: =F!$A$11 | S36: ='Malé'!N70
A37: Malédiction | B37: Rayon de Vulnérabilité | H37: ='Malé'!J22 | I37: ='Règles'!C169 | K37: =F!$A$5 | L37: =F!$A$11 | S37: ='Malé'!N22
A38: Malédiction | B38: Mauvais Présage | H38: ='Malé'!J29 | I38: ='Règles'!C167 | K38: =F!$A$5 | L38: =F!$A$11 | S38: ='Malé'!N29
A39: Malédiction | B39: Zone de Privation Sensoriel | H39: ='Malé'!J74 | I39: ='Règles'!C182 | K39: =F!$A$5 | L39: =F!$A$18 | S39: ='Malé'!N74
A40: Malédiction | B40: Fuite de Vitalité | H40: ='Malé'!J93 | I40: ='Règles'!C169 | K40: =F!$A$5 | L40: =F!$A$11 | S40: ='Malé'!N93
A41: Malédiction | B41: Zone de Ralentissement | H41: ='Malé'!J153 | I41: ='Règles'!C185 | K41: =F!$A$5 | L41: =F!$A$18 | S41: ='Malé'!N153
A42: Malédiction | B42: Décrépitude Programmée | H42: ='Malé'!J159 | I42: ='Règles'!C179 | K42: =F!$A$5 | L42: =F!$A$11 | S42: ='Malé'!N159
A43: Malédiction | B43: Mot de Contrainte | H43: ='Malé'!J168 | I43: ='Règles'!C164 | K43: =F!$A$6 | L43: =F!$A$11 | S43: ='Malé'!N168
A44: Malédiction | B44: Mot d'Ordre | H44: ='Malé'!J169 | I44: ='Règles'!C164 | K44: =F!$A$6 | L44: =F!$A$11 | S44: ='Malé'!N169
A45: Invocation | B45: Bête de Feu | K45: =F!$A$3 | L45: =F!$A$11
A46: Invocation | B46: Bête de Glace | K46: =F!$A$3 | L46: =F!$A$11
A47: Invocation | B47: Messager des Alizés | K47: =F!$A$3 | L47: =F!$A$11
A48: Invocation | B48: Eclaireur Syldavien | K48: =F!$A$3 | L48: =F!$A$11
A49: Invocation | B49: Appel du Loups | K49: =F!$A$3 | L49: =F!$A$11
A50: Invocation | B50: Boule Fulgurante? | K50: =F!$A$3 | L50: =F!$A$11
A51: Invocation | B51: Horde Squelettique | K51: =F!$A$3 | L51: =F!$A$11
A52: Invocation | B52: Appel du Trent | K52: =F!$A$3 | L52: =F!$A$11
A53: Invocation | B53: Appel de la Monture | K53: =F!$A$3 | L53: =F!$A$11
A54: Invocation | B54: Appel du Voltomage | K54: =F!$A$3 | L54: =F!$A$11
A55: Abjuration | B55: Retour aux Sources | H55: =Abju!J6 | I55: ='Règles'!C178 | K55: =F!$A$5 | L55: =F!$A$18 | P55: =L!$A$4 | S55: =Abju!N6
A56: Abjuration | B56: Barrière Physique | H56: =Abju!J14 | I56: =Abju!I14 | K56: =F!$A$5 | L56: =F!$A$11 | S56: =Abju!N14
A57: Abjuration | B57: Inversion des Peines | H57: =Abju!J9 | I57: =Abju!I9 | K57: =F!$A$5 | L57: =F!$A$11 | S57: =Abju!N9
A58: Abjuration | B58: Dénis des Intentions | H58: =Abju!J12 | I58: =Abju!I12 | K58: =F!$A$5 | L58: =F!$A$11 | S58: =Abju!N12
A59: Abjuration | B59: Retour de Flamme | H59: =Abju!J13 | I59: =Abju!I13 | K59: =F!$A$5 | L59: =F!$A$11 | S59: =Abju!N13
A60: Abjuration | B60: Mot de Paresse | H60: =Abju!J52 | I60: =Abju!I52 | K60: =F!$A$6 | L60: =F!$A$11 | S60: =Abju!N52
A61: Abjuration | B61: Barrière Globale | H61: =Abju!J17 | I61: =Abju!I17 | K61: =F!$A$5 | L61: =F!$A$11 | S61: =Abju!N17
A62: Abjuration | B62: Echappatoire Inextremis | H62: =Abju!J27 | I62: =Abju!I27 | K62: =F!$A$2 | L62: =F!$A$11 | S62: =Abju!N27
A63: Abjuration | B63: Dénis des Projectiles | H63: =Abju!J34 | I63: =Abju!I34 | K63: =F!$A$5 | L63: =F!$A$11 | S63: =Abju!N34
A64: Abjuration | B64: Es-tu sûr ? | H64: =Abju!J39 | I64: =Abju!I39 | K64: =F!$A$5 | L64: =F!$A$11 | S64: =Abju!N39
A65: Abjuration | B65: Intervention de Bogardan | H65: =Abju!J48 | I65: =Abju!I48 | K65: =F!$A$5 | L65: =F!$A$11 | S65: =Abju!N48
A66: Abjuration | B66: Esquive Soudaine | K66: =F!$A$2 | L66: =F!$A$11
A67: Divination | B67: Vision du Passé | H67: =Divi!J3 | I67: =Divi!I3 | K67: =F!$A$3 | L67: =F!$A$11 | S67: =Divi!N3
A68: Divination | B68: Vision du Futur | H68: =Divi!J4 | I68: =Divi!I4 | K68: =F!$A$3 | L68: =F!$A$11 | S68: =Divi!N4
A69: Divination | B69: Exploration Mémorielle | H69: =Divi!J39 | I69: =Divi!I39 | K69: =F!$A$5 | L69: =F!$A$11 | S69: =Divi!N39
A70: Divination | B70: Oeil de Scrutation | H70: =Divi!J40 | I70: =Divi!I40 | K70: =F!$A$9 | L70: =F!$A$11 | S70: =Divi!N40
A71: Divination | B71: Chemin de la Destiné | H71: =Divi!J49 | I71: =Divi!I49 | K71: Soi | L71: =F!$A$11 | S71: =Divi!N49
A72: Divination | B72: Retrouver une Personne | H72: =Divi!J61 | I72: =Divi!I61 | K72: Soi | L72: =F!$A$11 | S72: =Divi!N61
A73: Divination | B73: Plan Magique | H73: =Divi!J83 | I73: =Divi!I83 | K73: Soi | L73: =F!$A$11 | S73: =Divi!N83
A74: Divination | B74: Analyse des Attributs | H74: =Divi!J65 | I74: =Divi!I65 | K74: Soi | L74: =F!$A$11 | S74: =Divi!N65
A75: Divination | B75: Plonger dans la Mémoire | H75: =Divi!J72 | I75: =Divi!I72 | K75: =F!$A$5 | L75: =F!$A$11 | S75: =Divi!N72
A76: Divination | B76: Vision du Danger | H76: =Divi!J25 | I76: 🛡️ Guerre: Deltueoorr | K76: Soi | L76: =F!$A$11 | S76: =Divi!N25
A77: Conjuration | B77: Servitude des Déchus | H77: =Conj!J59 | I77: =Conj!I59 | K77: =F!$A$3 | L77: =F!$A$11 | S77: =Conj!N59
A78: Conjuration | B78: Conjuration d'Arme | H78: =Conj!J26 | I78: Au choix | K78: Soi | L78: =F!$A$11 | S78: =Conj!N26
A79: Conjuration | B79: Imprégnation d'Armure | H79: =Conj!J128 | I79: Au choix | K79: Soi | L79: =F!$A$11 | S79: =Conj!N128
A80: Conjuration | B80: Conjuration d'instruments | H80: =Conj!J28 | I80: =Conj!I28 | K80: Soi | L80: =F!$A$11 | S80: =Conj!N28
A81: Conjuration | B81: Chaines du Néant | H81: =Conj!J13 | I81: 🌑 Ombre: Colferoth | K81: =F!$A$5 | L81: =F!$A$11 | S81: =Conj!N13
A82: Conjuration | B82: Prison de Verre | H82: =Conj!J35 | I82: ☀️ Lumière: Carlumenion | K82: =F!$A$5 | L82: =F!$A$11 | S82: =Conj!N35
A83: Conjuration | B83: Cerceuil de Racines | H83: =Conj!J15 | I83: 🌿 Flore: Consariln | K83: =F!$A$5 | L83: =F!$A$11 | S83: =Conj!N15
A84: Conjuration | B84: Voix des Esprits | H84: =Conj!J20 | I84: ☠️ Mort: Censpirius | K84: Soi | L84: =F!$A$11 | S84: =Conj!N20
A85: Conjuration | B85: Reflet Animé | H85: =Conj!J19 | I85: 🎭 Illusion: Consimin | K85: Soi | L85: =F!$A$11 | S85: =Conj!N19
A86: Conjuration | B86: Aspect de la Bête | H86: =Conj!J47 | I86: 🐗 Faune: Carmutaorh | K86: Soi | L86: =F!$A$11 | S86: =Conj!N47
A87: Altération | B87: Changement d'état | H87: ='Alté'!J3 | I87: Au choix | K87: =F!$A$5 | L87: =F!$A$11 | S87: ='Alté'!N3
A88: Altération | B88: Transmutation de la matière | H88: ='Alté'!J7 | I88: Au choix | K88: =F!$A$5 | L88: =F!$A$11 | S88: ='Alté'!N7
A89: Altération | B89: Fissure Sismique | H89: ='Alté'!J6 | I89: 🪨 Terre: Aenfindum | K89: =F!$A$5 | L89: =F!$A$11 | S89: ='Alté'!N6
A90: Altération | B90: Mots d'Conditionnements | H90: ='Alté'!J10 | I90: Au choix | K90: =F!$A$6 | L90: =F!$A$11 | S90: ='Alté'!N10
A91: Altération | B91: Mots Venimeux | H91: ='Alté'!J11 | I91: ☢️ Toxique: Altoxex | K91: =F!$A$6 | L91: =F!$A$11 | S91: ='Alté'!N11
A92: Altération | B92: Mots Infectieux | H92: ='Alté'!J12 | I92: ☠️ Mort: Arinficus | K92: =F!$A$6 | L92: =F!$A$11 | S92: ='Alté'!N12
A93: Altération | B93: Création Universelle | H93: ='Alté'!J31 | I93: Au choix | K93: =F!$A$5 | L93: =F!$A$11 | S93: ='Alté'!N31
A94: Altération | B94: Arme éphéméride | H94: ='Alté'!J28 | I94: ⚔️ Acier: Alcreoan | K94: =F!$A$5 | L94: =F!$A$11 | S94: ='Alté'!N28
A95: Altération | B95: Aiguiser l'Acier | H95: ='Alté'!J38 | I95: ⚔️ Acier: Aenroboran | K95: =F!$A$5 | L95: =F!$A$11 | S95: ='Alté'!N38
A96: Altération | B96: Destin de Statufication | H96: ='Alté'!J45 | I96: 🪨 Terre: Aspetraum | K96: =F!$A$5 | L96: =F!$A$11 | S96: ='Alté'!N45
A97: Évocation | B97: Forge de Matière | H97: =Evoc!J13 | I97: Au choix | K97: =F!$A$5 | L97: =F!$A$11 | S97: =Evoc!N13
A98: Évocation | B98: Saut Astral | H98: =Evoc!J36 | I98: ✡️ Arcane: Eruportys | K98: Soi | L98: =F!$A$11 | S98: =Evoc!N36
A99: Évocation | B99: Traction Arcanique | H99: =Evoc!J11 | I99: 💢 Vide: Evtractarh | K99: =F!$A$7 | L99: =F!$A$11 | S99: =Evoc!N11
A100: Évocation | B100: Onde de Répulsion | H100: =Evoc!J7 | I100: 🌪️ Air: Evpelloel | K100: =F!$A$2 | L100: =F!$A$13 | S100: =Evoc!N7
...

Sheet L
A1: Mot | B1: Type de Mot | C1: Type de Sorts | D1: Difficulté | E1: Drain | F1: Description | G1: Conditions | H1: Domaine
A2: Boost | B2: Liaison | C2: Tous | D2: 0 | E2: X | F2: Lorsque le sort est lancé le personnage peux dépenser autant de mana que souhaité pour augmenter la puissance du sort d'autant, maximum 2 par dés
A3: Long | B3: Liaison | C3: Tous | D3: 2 | E3: 2 | F3: La distance de diffusion du sort est doublée | G3: Diffusion avec distance magique
A4: Large | B4: Liaison | C4: Tous | D4: 0 | E4: 2 | F4: La zone de propagation du sort est doublée | G4: Propagation de type AOE
A5: Aléa | B5: Liaison | C5: Tous | D5: X | E5: X | F5: Le sort est associé à X autres mots de pouvoir, lorsque le sort est lancé seul l'un d'eux est sélectionné, PWR +X | G5: X maximum 3 | H5: 🌀 Chaos
A6: Aléatoire | B6: Liaison | C6: Tous | D6: 0 | E6: 0 | F6: Le sort a 50% de chance de s'appliquer sur chaque cible, PWR +2
A7: Filtre | B7: Liaison | C7: Tous | D7: 4 | E7: 0 | F7: Le sort n'affecte pas les alliés du lanceur de sort (ni le lanceur du sort lui même)
A8: Concentration | B8: Liaison | C8: Tous | D8: 2 | E8: 2 | F8: Chaque cases du sort rattaché à sa zone d'effet qui est bloquée par la typologie du lieu où il est lancé augmente la puissance du sort de 1, maximum 2 x dés
A9: Ephémère | B9: Liaison | C9: Tous | D9: 0 | E9: 0 | F9: Le sort d'invocation ne dure qu'un cycle unique, l'invocation est avantagé a ses tests & jets | H9: ⚡ Foudre
A10: Drain | B10: Liaison | C10: Tous | D10: 0 | E10: 0 | F10: Le sort doit inclure deux mots, en duo ou avec une annexe : l'un pour endommager une ressource, l'autre pour soigner celle ci; les dégats aurons alors lieu sur la cible et le soin sur le lanceur du sort, le montant soigné ne peux être supérieur à la perte réelle de la dite ressource par la cible
A11: Combo | B11: Liaison | C11: Tous | D11: 2 | E11: 0 | F11: Le sort doit inclure deux mots, en duo ou avec une annexe : les deux mots doivent avoir un lien évident et explicite formant une combinaison logique; alors le sort reçoit PWR +1
A12: Perçant | B12: Liaison | C12: Attaque | D12: 2 | E12: 2 | F12: L'attaque issus du sort génère des dégats perçants (ignore la moitié de l'absorption de la cible) | H12: 🔥 Feu, ❄️ Glace, ⚡ Foudre
A13: Biorythme | B13: Liaison | C13: Récup | D13: 2 | E13: 4 | F13: Le soin produit par le sort génère deux fois moins de fatigue le cas échéant | H13: ❤️ Vie
A14: Intelligent | B14: Liaison | D14: 4 | E14: 2 | F14: Le sort n'affecte que les alliés ou les ennemis, au choix du lanceur de sort | H14: 🔮 Magie
A15: Némésis | B15: Liaison | D15: 2 | E15: 2 | F15: Le sort n'affecte que les ennemis du lanceur de sort | H15: 🩸 Impie
A16: Sacrifice | B16: Liaison | D16: 0 | E16: 0 | F16: Le lanceur de sort perd autant de PV que le drain minimum du sort, PWR +2 | H16: 🩸 Impie
A17: Nuance | B17: Liaison | D17: 2 | E17: 2 | F17: Si le sort produit ses effets contre ou en rapport avec un domaine ou un élément, cet effet considère l'ensemble des domaines du même cercle (à savoir : Energie, Matière, Prime, Origine, Eternel, Cycle, Nature, Mental, Magie)
A18: Alignement | B18: Liaison | D18: 2 | E18: 2 | F18: Si le sort produit ses effets contre ou en rapport avec un domaine Divin ou Occulte il affecte tous les domaines de ce type (Divin : Sacré, Vie, Lumière, Loi; Occulte : Impie, Mort, Ombre, Chaos)
A19: Présence | B19: Liaison | D19: 4 | E19: 4 | F19: Le sort qui fait apparaitre des entitées magiques deviens un enchantement qui maintient la présence de ces dernières, provoquant un déplacement de ces derniers (selon les règles appropriées du sort) à chaque tour au même rang d'initiative que le moment où le sort a été lancé | H19: 🔮 Magie
A20: Interruption | B20: Liaison | D20: 2 | E20: 2 | F20: Le sort peux être lancé en interruption, mais requière malgré tout les actions simples habituels (et non une ACTR comme les sorts dont le mot de pouvoir est une interruption)
A25: Impersonalisation | B25: Liaison | C25: Tous | D25: 4 | E25: 2 | F25: Le sort remplace les références au "lancer de sort" avec une cible (au contact ou à distance le cas échéant) | H25: Tous
A28: ??? | B28: Liaison | C28: Tous | D28: 2 | E28: 2 | F28: Si la cible du sort est recouvert par l'élément (de façon intense) associé au domaine de la [clé], le sort est assuré (mini 4) et majoré (+1 par dés) | H28: 🔥 Feu (vs FOR), ❄️ Glace (vs DEX), ⚡ Foudre (vs AGI), 🪨 Terre (vs FOR),💧 Eau (vs DEX), 🌪️ Air (vs AGI), ☀️ Lumière (vs PER), 🌑 Ombre (vs PER), 🌿 Flore (vs PER)
A29: ??? | B29: Liaison | C29: Tous | D29: 0 | E29: 0 | F29: Condition supplémentaire : La cible du sort est recouvert par l'élément (de façon intense) associé au domaine de la [clé], le sort est assuré (mini 4) et majoré (+1 par dés) | H29: 🔥 Feu (vs FOR), ❄️ Glace (vs DEX), ⚡ Foudre (vs AGI), 🪨 Terre (vs FOR),💧 Eau (vs DEX), 🌪️ Air (vs AGI), ☀️ Lumière (vs PER), 🌑 Ombre (vs PER), 🌿 Flore (vs PER)
A30: Extinction | B30: Liaison | C30: Négatif | D30: 0 | E30: 0 | F30: L'effet d'alignement négatif produit par le sort voit son jet multipliés par 0.5 x le niveau de gravité de la blessure la plus élevé de la cible | H30: ☠️ Mort
A31: ??? | B31: Liaison | C31: Négatif | D31: 2 | E31: 2 | F31: L'effet d'alignement négatif produit par le sort voit son jet augmenté de 1D6 supplémentaire par niveau de gravité de la blessure la plus élevé de la cible, maximum 1D6 par niveau du sort | H31: ☠️ Mort
A32: ??? | B32: Liaison | C32: Positif | D32: 0 | E32: 0 | F32: L'effet d'alignement positif produit par le sort voit son jet multipliés par 0.5 x le niveau de gravité de la blessure la plus élevé de la cible | H32: ❤️ Vie
A33: ??? | B33: Liaison | C33: Positif | D33: 2 | E33: 2 | F33: L'effet d'alignement positif produit par le sort voit son jet augmenté de 1D6 supplémentaire par niveau de gravité de la blessure la plus élevé de la cible, maximum 1D6 par niveau du sort | H33: ❤️ Vie
A34: ??? | B34: Liaison | C34: Aligné | D34: 0 | E34: 0 | F34: L'effet d'alignement positif ou négatif produit par le sort voit son jet multipliés par 0.5 x le niveau du trauma de la blessure la plus élevé de la cible | H34: 🧩 Mental
A35: ??? | B35: Liaison | C35: Aligné | D35: 2 | E35: 2 | F35: L'effet d'alignement positif ou négatif produit par le sort voit son jet augmenté de 1D6 supplémentaire par niveau de gravité du trauma la plus élevé de la cible, maximum 1D6 par niveau du sort | H35: 🧩 Mental
A36: ??? | B36: Liaison | C36: Tous | D36: 2 | E36: 0 | F36: L'effet produit par le sort voit son jet augmenté de 2 supplémentaire par adversaire autour de la cible, maximum 2 par niveau du sort | H36: 🛡️ Guerre
A37: ??? | B37: Liaison | C37: Tous | D37: 2 | E37: 0 | F37: L'effet produit par le sort voit son jet majoré 1x / 2x ou 3x mais surviens avec un décalage de 1 / 2 / 3 cycle complets, si le lanceur de sort est déconcentré entre temps l'effet est dissipé sans se produire | H37: 💢 Vide
A38: ??? | B38: Liaison | C38: Attaque | D38: 2 | E38: 2 | F38: Les dégats infligés via le sort provoque un soin de l'endurance du lanceur de sort à hauteur de la moitié des ressources (non temporaires) perdues | H38: ☠️ Mort
... A58: ??? | B58: Liaison | C58: Aligné | D58: 2 | E58: 2 | F58: L'effet d'alignement positif ou négatif produit par le sort voit son jet augmenté de 1D6 supplémentaire par niveau de gravité du trauma la plus élevé du lanceur de sort, maximum 1D6 par niveau du sort | H58: 🧩 Mental
A59: Augmentation | B59: Liaison | C59: Attaque | D59: 2 | E59: 2 | F59: L'attaque issus du sort ne fonctionne/n'affecte que le type de cible contre lequel la [clé] choisit est fort, les dégats sont majorés (+1 par dés) et assuré (minimum des dés 3) | H59: ='Règles'!D139
A60: ??? | B60: Liaison | C60: Attaque | D60: 2 | E60: 2 | F60: Les dégats du sort sont localisés (choix de la localisation lors du lancement du sort) | H60: 👁️ Vision
A61: ??? | B61: Liaison | C61: Attaque | D61: -2 | E61: 0 | F61: Les dégats du sort multiplié par 0.5 du rang de la lésion la plus élevée (en deça du rang 3 les dégats sont identiques ou réduits) | H61: ☠️ Mort
A62: ??? | B62: Liaison | C62: Attaque | D62: -2 | E62: 0 | F62: Les dégats du sort n'inflige pas de lésions | H62: ☀️ Lumière, 🌑 Ombre
A63: ??? | B63: Liaison | C63: Attaque | D63: -4 | E63: 0 | F63: Les dégats du sort sont limités par l'endurance actuelle (4 si max) | H63: TODO, 💢 Vide
A64: ??? | B64: Liaison | C64: Attaque | D64: -4 | E64: 0 | F64: Les dégats du sort sont limités par la vitalité actuelle (4 si max) | H64: TODO, 💢 Vide
A65: ??? | B65: Liaison | C65: Attaque | D65: -4 | E65: 0 | F65: Les dégats du sort sont concussant, ils n'inflige donc pas de dégats permanents | H65: ⚖️ Loi, 🌀 Chaos
A66: ??? | B66: Liaison | C66: Attaque | D66: -4 | E66: 0 | F66: DOT (considéré comme une condition physique, implique une sauvegarde robustesse, chaque passe la cible subit 50% des charges totales, peux être réduit par les premiers soins ou compétence d'endurance) | H66: ☢️ Toxique
A67: ??? | B67: Liaison | C67: Attaque | D67: -6 | E67: 0 | F67: Les dégats du sort sont concussant, ils n'inflige donc pas de dégats permanents | H67: ⚔️ Acier
A68: ??? | B68: Liaison | C68: Attaque | D68: -4 | E68: 0 | F68: Les dégats du sort tiennent compte deux fois de la résistance des cibles | H68: 🌿 Flore
A69: ??? | B69: Liaison | C69: Attaque | D69: -8 | E69: 0 | F69: Les dégats du sort n'inflige ni dégats permanents, ni temporaires, uniquement une lésion | H69: ☠️ Mort
A70: ??? | B70: Liaison | C70: Attaque | D70: -10 | E70: 0 | F70: Les dégats du sort sont infligés au lanceur de sort sous forme de dégats ignorant l'armure | H70: 🩸 Impie
A71: ??? | B71: Liaison | C71: Enchantement | D71: 2 | E71: 2 | F71: L'enchantement positif ou négatif génère une charge doublement minorée (-2 par dés), à chaque début de tour la cible reçoit un marqueur, l'enchantement en question voit ses effets appliqués selon la formule [nombre de marqueurs x magnitude finale] | H71: 🌿 Flore
... A83: ??? | B83: Liaison | C83: Condition | D83: 6 | E83: 6 | F83: La condition incluse dans le sort est de nature permanente plutôt qu'éphémère, la cible est avantagée à son test de sauvegarde le cas échéant | H83: ☢️ Toxique
A84: Consécration | B84: Liaison | C84: Tous | D84: 0 | E84: 0 | F84: Si la cible du sort coRespond à un domaine contre lequel l'élément de la [clé] est fort alors le sort fonctionne, sinon il ne fait pas effets, le jet est majoré (+1 par dés) et assuré (minimum des dés 3) | H84: ='Règles'!D135
A85: Diurne | B85: Liaison | C85: Tous | D85: 2 | E85: 2 | F85: Le sort est plus efficace le jour, profitant d'un bonus de 2 par niveau, le bonus passe à 3 sous les rayons du soleil | H85: ☀️ Lumière
A86: Nocturne | B86: Liaison | C86: Tous | D86: 2 | E86: 2 | F86: Le sort est plus efficace la nuit, profitant d'un bonus de 2 par niveau, le bonus passe à 3 sous les rayons de la lune | H86: 🌑 Ombre
A87: Infiltration | B87: Liaison | C87: Attaque | D87: 2 | E87: 2 | F87: Les dégâts causés par le sort ignore toutes les ressources temporaires (qui ne peuvent donc pas être utilisées), ce qui inclus les barrières, la garde ou l'adrénaline (qui ne peux être utilisée pour générer une défense par example) | H87: 🌑 Ombre
A88: Elévation | B88: Liaison | C88: Tous | D88: 2 | E88: 2 | F88: Si la cible est affectée par une condition positive alors la puissance du sort est augmentée de 1 par niveaux et par conditions | H88: ✨ Sacre
A89: Sanction | B89: Liaison | C89: Tous | D89: 2 | E89: 2 | F89: Si la cible est affectée par une condition négative alors la puissance du sort est augmentée de 1 par niveaux et par conditions | H89: 🩸 Impie
A91: Compensation | B91: Liaison | C91: Tous | F91: Augmente le niveau du sort si la cible à des lésions, le bonus est équivalent au niveau de la lésion la plus élevée | H91: ❤️ Vie
A92: Putréfaction | B92: Liaison | C92: Négatif | F92: un sort négatif est plus efficace si la cible a des lésions | H92: ☠️ Mort
A93: Crémation | B93: Liaison | C93: Attaque | F93: Condition : Effets basés sur des dégâts de feu. Description : 50% des dégâts affectent aussi l’endurance | H93: 🔥 Feu
A94: Cautérisation (autre nom) | B94: Liaison | C94: Récup | F94: Condition : Effetsbasés sur des soins.Description : les effets de guérisons infligent moins (ou pas) defatigue mais provoquent des lésions à la place | H94: 🔥 Feu
A95: Congélation | B95: Liaison | C95: Négatif | F95: Le sort reçoit un bonus de puissance similaire si la cible est humide ou est mouillée. | H95: ❄️ Glace
A96: Réfrigération | B96: Liaison | C96: Attaque | F96: Condition : Effets basés sur des dégâts de froid. Description : 50% des dégâts affectent aussi l’initiative | H96: ❄️ Glace
A97: Extérieur | B97: Liaison | C97: Négatif | F97: plus efficace en extérieur (si offensif) | H97: ⚡ Foudre
A98: Consomption | B98: Liaison | C98: Attaque | F98: Condition : Effets basés sur des dégâts de foudre. Effet : 50% des dégâts affectent aussi la maitrise | H98: ⚡ Foudre
A99: Intériorisation | B99: Liaison | C99: Négatif | F99: plus efficace en intérieur, en tout cas naturel (si négatif) comme électrocution quoi, donc revoir le truc, c’est une catégorie de mot en soi. | H99: 🪨 Terre
A100: Hydrocution | B100: Liaison | C100: Négatif | F100: Condition : Le sort doit être d’alignement négatif. Le sort reçoit un bonus de puissance équivalant à son niveau si la cible peut être logiquement sensible au changement brutal de température (par exemple si elle provient d’un environnement chaud ou si elle est en train de brûler). | H100: 💧 Eau
A101: ??? | B101: Liaison | C101: Bénédiction | F101: la bénédiction affecte tous les personnages dans la zone, mais effet réduit ? | H101: 🔮 Magie
A102: ??? | B102: Liaison | C102: Malédiction | F102: la malédiction affecte tous les personnages dans la zone, mais effet réduit ? | H102: 🔮 Magie
... A111: Rétroaction | B111: Liaison | C111: Tous | F111: L'effet se déclanche comme si elle était arrivé plus tôt dans le temps ? Ou conséquence comme si | H111: 💢 Vide
A112: ??? | B112: Liaison | C112: Offensif | D112: 4 | E112: 2 | F112: Bonus pour toucher la cible (ignore une partie de la défense ? ou cible directementla magie ?) | H112: ✡️ Arcane
A113: ??? | B113: Liaison | C113: Offensif | F113: Le sort prend effet avec un tour de retard, ne laisse pas de traces avant activation, niveau effectif +1, difficulté arcanique +2
A114: ??? | B114: Liaison | C114: Offensif | F114: Le sort prend effet avec un tour de retard, laisse une trace avant activation, niveau effectif +2, difficulté arcanique +4
A115: ??? | B115: Liaison | C115: Condition | F115: Liaison pour deux conditions (double test de save), car une seule condition c'est bif bouf bof
A116: ??? | B116: Liaison | C116: Bénédiction | F116: Le sort est stocké sous forme d'enchantement positif et se lance à la mort de la cible, peux uniquement contenir des mots positifs | H116: ❤️ Vie
A117: ??? | B117: Liaison | C117: Malédiction | F117: Le sort est stocké sous forme d'enchantement négatif et se lance à la mort de la cible, peux uniquement contenir des mots négatifs (le sort n'affectera pas les individus autour de la cible si aucun mots ne permet de modifier les effets sous forme de zone) | H117: ☠️ Mort
A118: ??? | B118: Liaison | C118: Invocation | F118: Les invocations sont un pack de petites entités, voir règle des hordes | H118: 🐗 Faune
A119: ??? | B119: Liaison | C119: Invocation | F119: L'invocation peux agir sur le champs, elle n'a pas le mal d'invocation | H119: 🐗 Faune
A120: ??? | B120: Liaison | C120: Enchantement | D120: 0 | E120: 0 | F120: Flore : L'enchantement commence à -2D6 mais fini à +2D6 après 5 tours, donc il up de 1D6 par tours ? | H120: 🌿 Flore
A121: ??? | B121: Liaison | C121: Enchantement | D121: 0 | E121: 0 | F121: Chaos : L'enchantement oscille de -2D6 à +2D6 aléatoirement | H121: 🌀 Chaos
A122: ??? | B122: Liaison | C122: Tous | D122: 4 | E122: 2 | F122: Le test de sauvegarde associé aux effets du sort est désavantagé | H122: 🔮 Magie
A123: ??? | B123: Liaison | C123: Enchantement | F123: L'enchantement associé au sort expire à la fin d'un cycle quoi qu'il arrive, il ne peux être maintenu, cependant les effets (et difficulté arcanique) de ce dernier voient leur niveau augmenté de 2 | H123: 🔮 Magie
A124: ??? | B124: Liaison | C124: Offensif | F124: - Mot de liaison (diff +2) qui boost le niveau du sort de 2 si la cible est associé à l'ombre, le chaos, l'impie, applicable plusieurs fois
A125: ??? | B125: Liaison | C125: Offensif | F125: - Mot de liaison (diff +2) qui boost le niveau du sort de 100% si la cible est associé à l'ombre, le chaos, l'impie, sinon le sort ne fait pas ses effets
A126: ??? | B126: Liaison | C126: Offensif | F126: - Mot de liaison (diff +2) qui boost le niveau du sort de 2 si la cible est associé à la lumière, l'ordre, la sainteté, applicable plusieurs fois
A127: ??? | B127: Liaison | C127: Offensif | F127: - Mot de liaison (diff +2) qui boost le niveau du sort de 100% si la cible est associé à la lumière, l'ordre, la sainteté, sinon le sort ne fait pas ses effets
A128: ??? | B128: Liaison | C128: Tous | F128: * Mot de liaison qui renforce les effets mais avec une description de la cible très précise (race, etc)
A129: ??? | B129: Liaison | C129: Tous | F129: * Mot de liaison qui renforce les effets mais avec une description de la cible très très précise, ce qui rend ce sort uniquement utile sur une cible quasiment | H129: ⚖️ Loi
A130: Scarification | B130: Liaison | C130: Tous | D130: 4 | E130: 2 | F130: Au moment où le sort est lancé le lanceur de sort perd jusqu'à la moitié de ses PV (non temporaires) actuels, la magnitude du sort est augmentée de 1 par PV ainsi perdus, le gain de magnitude ne peux dépasser 50% de la magnitude de base | H130: 🩸 Impie
A131: ??? | B131: Liaison | C131: - | D131: 2 | E131: 2 | F131: Le soin produit par le sort génère de la fatigue chez le lanceur de sort à la place de la cible du soin | H131: ❤️ Vie
A133: ??? | B133: Liaison | C133: - | D133: 4 | E133: 2 | F133: Le soin produit par le sort est augmenté de moitié, ce bonus ne peux dépasser la moitié de la quantité manquante de la ressource (c'est donc plus efficace sur une cible qui a beaucoup perdu) | H133: ❤️ Vie
A134: Transfert | B134: Liaison | C134: - | D134: 0 | E134: 0 | F134: Le soin produit par le sort est moitié plus efficace, mais le lanceur de sort subit une perte équivalante de cette même ressource en contre partie | H134: ❤️ Vie
A135: ??? | B135: Liaison | C135: - | D135: 2 | E135: 2 | F135: Le soin produit par le sort est augmentée de [Magnitude/2] sur les animaux ou sur les plantes, selon la [clé] | H135: 🐗 Faune, 🌿 Flore
A136: ??? | B136: Liaison | C136: - | D136: 4 | E136: 4 | F136: Le soin associé à l'effet du sort prend la forme d'un enchantement positif qui distille le soin à chaque déplacement réalisé, à raison de 1 point de ressource par pas/cases, le jet du sort pour cet effet est alors assuré (minimum 4) et majoré (+1 par dés), la fatigue (si il y en a) est contractée au moment où l'enchantement est reçu | H136: ❤️ Vie
A137: ??? | B137: Liaison | C137: - | D137: 0 | E137: 0 | F137: Les effets de soin sont augmenté de moitié mais la fatigue généré est doublée, cet effet ne fonctionne donc que sur les soins générant de la fatigue | H137: ❤️ Vie
A138: Transfusion | B138: Liaison | C138: - | D138: 2 | E138: 2 | F138: les dégâts du sort transfert des ressources identiques (vitalité ou mental). Génère de la fatigue. | H138: ☠️ Mort
A139: Galvanisation | B139: Liaison | C139: - | D139: 2 | E139: 2 | F139: les dégâts du sort transfert de l’endurance eu lanceur de sort. | H139: ☠️ Mort
A140: ??? | B140: Liaison | C140: - | D140: 4 | E140: 4 | F140: S'associe au mot permettant le stockage ou accés à des objets en milieu interdimentionnel, désormais l'effet peux affecter les objets qui n'appartiennent pas au lanceur de sort, qu'il s'agisse d'un objet dans les mains de la cible ou dans un espace dimentionnel lui appartenant, dans tous les cas ce dernier peux réaliser un test d'opposition pour réduire ou prévenir les effets, il est d'ailleurs au courant de la tentative si l'objet était actuellement sous sa surveillance (ou en tout cas à proximité), si l'objet est actuellement dans les mains de la cible il faut résoudre une tentative de désarmement dont le test est réalisé avec la magie du lanceur de sort et [Magnitude/5] en guise de compétence (vs DEX ou FOR, le plus haut des deux) et la cible peux se défendre de cette tentative avec l'action idoine, si l'objet est dans un espace qui n'est pas le siens on résoue cette tentative de désarmemement en opposant le test à la défense passive de magie de la cible | H140: ✡️ Arcane
A141: ??? | B141: Liaison | C141: - | D141: 2 | E141: 2 | F141: L'effet de recharge du sort se limite à aux enchantments de lieux, la recharge est augmentée de [Magnitude/2] | H141: 🔮 Magie
A142: ??? | B142: Liaison | C142: - | D142: 2 | E142: 2 | F142: L'effet de recharge du sort se limite à aux enchantments d'invocation, la recharge est augmentée de [Magnitude/2] | H142: 🔮 Magie
... A144: ??? | B144: Liaison | C144: - | D144: 2 | E144: 2 | F144: Génère un effet qui permet à une cible de réaliser un saut dont la hauteur est au mieux de [Magnitude/3], au lancement du sort le lanceur de sort peux choisir si cet effet est bénéfique ou néfaste, si l'effet est bénéfique alors la cible n'a pas à réaliser de tests et peux choisir la hauteur de son bond (avec la limitation prévue), si l'effet est néfaste la cible peux réaliser un test de sauvegarde (réflexes) pour réduire les effets et ne peux choisir la hauteur du saut et dans ce cas uniquement la réception au sol peux entrainer des dégats normaux de chutes (la cible ne fait qu'un seul test de réflexes et la réduction de la chute est donc comprise dans la réduction des effets le cas échéant) | H144: 🌪️ Air, ✡️ Arcane
A145: ??? | B145: Liaison | C145: - | D145: 4 | F145: Si ce sort contre un autre sort alors le lanceur de ce sort est soigné de [Magnitude/4] d'une ressource qui dépends de la [clé] associée, maximum équivalant à la moitié du drain du sort contré | H145: ❤️ Vie (PV), 🧩 Mental (PS), 🌀 Chaos (PK), Esprit/Corps (PC), 🪷 Nature (PE), 🔮 Magie (PM)
A146: ??? | B146: Liaison | C146: - | D146: 4 | F146: Si ce sort contre un autre sort alors le lanceur du sort contré perd [Magnitude/4] d'une ressource qui dépends de la [clé] associée, maximum équivalant à la moitié du drain du sort contré | H146: ☠️ Mort (PV), 🧩 Mental (PS), ⚖️ Loi (PK), 🪷 Nature (PC ou PE), ✡️ Arcane (PM)
A147: Tranquilité | B147: Liaison | C147: - | D147: 2 | E147: 2 | F147: L'effet de décharge du sort se limite à aux enchantments de lieux, la décharge est augmentée de [Magnitude/2] | H147: 🪷 Nature
...

Sheet A
A1: Mot | B1: Type de Mot | C1: Type de Sorts | D1: Difficulté | E1: Drain | F1: Description | G1: Conditions | H1: Domaine
A2: Annexe | B2: Avancé | D2: X | E2: X | F2: Le sort est avancé (voir les règles), entre autre il requière une ACTS de plus pour être lancé, de plus le sort est associé à un second mot de pouvoir, cet effet subit PWR-2, le malus de PWR ne peux pas être supérieur à 4 une fois tous les mots associés | G2: Le malus de PWR ne peux pas être supérieur à 4 une fois tous les mots associés
A3: Duo | B3: Avancé | D3: X | E3: X | F3: Le sort est avancé (voir les règles), entre autre il requière une ACTS de plus pour être lancé, de plus le sort est associé à un second mot de pouvoir, les deux effets subissent PWR-1, le malus de PWR ne peux pas être supérieur à 4 une fois tous les mots associés | G3: Le malus de PWR ne peux pas être supérieur à 4 une fois tous les mots associés
A4: Supérieur | B4: Avancé | D4: X | E4: X | F4: Le sort est avancé (voir les règles), entre autre il requière une ACTS de plus pour être lancé, de plus le sort est reçoit PWR +1
B5: Avancé
B6: Avancé
B7: Avancé
B8: Avancé
B9: Avancé
B10: Avancé
B11: Avancé
B12: Avancé
B13: Avancé

Sheet F
A1: Mot | B1: Type de Mot | C1: Type de Forme | D1: Limitations | E1: Difficulté | F1: Drain | G1: Description | H1: Particularités | I1: Domaine
A2: Soi | B2: Forme | C2: Diffusion | D2: Def, Enc, Eff | E2: -2 | F2: -2 | G2: Portée : Sans, Vecteur : Sans, Cible soi possible
A3: Contact | B3: Forme | C3: Diffusion | D3: Off, Def, Enc, Eff, Inv | E3: 0 | F3: 0 | G3: Portée : Mêlée, Vecteur : Touché, Cible soi possible | H3: Défendable, Interceptible
A4: Projectile | B4: Forme | C4: Diffusion | D4: Off | E4: 4 | F4: 2 | G4: Portée : Portée magique x2, Vecteur : Vue | H4: Défendable, Interceptible
A5: Manifestation | B5: Forme | C5: Diffusion | D5: Off, Def, Enc, Eff, Inv | E5: 2 | F5: 2 | G5: Portée : Portée magique x1, Vecteur : Vue, Cible soi possible
A6: Mot | B6: Forme | C6: Diffusion | D6: Off, Def, Enc, Eff | E6: 6 | F6: 4 | G6: Portée : Portée magique x3, Vecteur : Voix | I6: Loi, Sacre
A7: Regard | B7: Forme | C7: Diffusion | D7: Off, Def, Enc, Eff | E7: 6 | F7: 4 | G7: Portée : Portée magique x3, Vecteur : Vue | I7: Chaos, Impie
A8: Reflet | B8: Forme | C8: Diffusion | D8: Off, Def, Eff | E8: 4 | F8: 2 | G8: Portée : Lieu, Vecteur : Reflets | I8: Illusion
A9: Nom | B9: Forme | C9: Diffusion | D9: Off, Def, Enc, Eff | E9: 4 | F9: 2 | G9: Portée : Lieu, Vecteur : Voix | I9: Impie
A10: * | B10: * | C10: * | D10: * | E10: * | F10: * | G10: *
A11: Unique | B11: Forme | C11: Propagation | E11: 0 | F11: 0 | G11: Touche une cible unique
A12: Carré | B12: Forme | C12: Propagation | E12: 2 | F12: 2 | G12: Touche une cible et 1 case à proximité (AOE 3)
A13: Cercle | B13: Forme | C13: Propagation | E13: 0 | F13: 2 | G13: Comme carré mais ignore la cible (n'affecte que les cases à proximité donc, utile pour les novas)
A14: Croix | B14: Forme | C14: Propagation | E14: 2 | F14: 2 | G14: Touche une cible et jusqu'à 2 cases de chaque coté en croix (AOE spéciale)
A15: Rayon | B15: Forme | C15: Propagation | E15: 2 | F15: 2 | G15: Touche une cible et jusqu'à 4 cases derrière celle ci (AOE spéciale)
A16: Ligne | B16: Forme | C16: Propagation | E16: 2 | F16: 2 | G16: Touche une cible et jusqu'à 3 cases sur chaque cotés (face au lanceur de sort) (AOE spéciale)
A17: Cône | B17: Forme | C17: Propagation | E17: 2 | F17: 2 | G17: Touche une cible, 3 cases de largeur et 2 cases de profondeur derrières elles (AOE spéciale)
A18: Zone | B18: Forme | C18: Propagation | E18: 4 | F18: 4 | G18: Touche une cible et 3 cases à proximité (AOE 7)
A19: Ciel | B19: Forme | C19: Propagation | E19: 4 | F19: 4 | G19: Touche une cible et 5 cases à proximité (AOE 9), dans les airs uniquement
A20: Surface | B20: Forme | C20: Propagation | E20: 4 | F20: 4 | G20: Touche une cible et 5 cases à proximité (AOE 9) sur une surface/hauteur identique à la cible
A21: Ombre | B21: Forme | C21: Propagation | E21: 4 | F21: 4 | G21: Touche une cible et 5 cases à proximité (AOE 9) qui partage la même pénombre
A22: Lumière | B22: Forme | C22: Propagation | E22: 4 | F22: 4 | G22: Touche une cible et 5 cases à proximité (AOE 9) qui partage la même luminosité
A23: * | B23: * | C23: * | D23: * | E23: * | F23: * | G23: *
A24: Puit | B24: Forme | C24: Structure | D24: Off, Def, Eff | E24: 0 | F24: 0 | G24: Le sort s'applique au moment où il est lancé puis aux deux rounds d'après, même cible, la cible doit être un lieu | H24: PWR -2/-2/-2 (6)
A25: Echos | B25: Forme | C25: Structure | D25: Off, Def, Eff | E25: 2 | F25: 2 | G25: Le sort s'applique au moment où il est lancé puis aux deux rounds d'après, même cible, la cible doit être un lieu | H25: PWR -1/-2/-3 (6)
A26: Chaine | B26: Forme | C26: Structure | D26: Off | E26: 2X | F26: 2X | G26: Le sort s'applique puis change de cible, la nouvelle cible doit être valide, jusqu'à X fois en tout | H26: PWR +0/-1/-2/... (9) | I26: Foudre
A27: Souffle | B27: Forme | C27: Structure | D27: Off, Eff | E27: 4 | F27: 4 | G27: Le sort s'applique normalement mais une version diminuée du sort affecte également les cibles adjacentes (en AOE la portée de ce souffle est équivalant à la distance d'AOE) | H27: PWR +0/-2 | I27: Feu
A28: Lent | B28: Forme | C28: Structure | D28: Off, Enc, Eff | E28: 2X | F28: 2X | G28: Le sort s'applique après un délai de X rounds, maximum 3 | H28: PWR +X | I28: Glace
A29: Poison | B29: Forme | C29: Structure | D29: Off, Eff | E29: 2 | F29: 2 | G29: Le sort s'applique au moment où il est lancé puis aux deux rounds d'après, même cible (lieu ou cible) | H29: PWR -3/-2/-1 | I29: Poison
A30: Double | B30: Forme | C30: Structure | D30: Off, Eff | E30: 2 | F30: 0 | G30: Le sort s'applique sur deux cibles distincts, ces deux cibles sont nécessaires | H30: PWR -1
A31: Multiple | B31: Forme | C31: Structure | D31: Off, Eff | E31: 2X | F31: 2X | G31: Le sort s'applique sur une cible + X autres cibles distincts | H31: PWR -1
A32: Activable | B32: Forme | C32: Structure | D32: Off, Def, Eff, Enc | E32: 0 | F32: 0 | G32: Le sort ne s'applique pas au moment où il est lancé, la cible/zone devient un enchantement qui déclanche les effets si une cible viable la touche, l'enchantement est défaussé après activation, le sort ne peux pas être lancé directement sur une cible correspondant | H32: PWR +2
A33: Statique | B33: Forme | C33: Structure | D33: Off, Def, Eff | E33: 0 | F33: 0 | G33: Le sort ne s'applique pas au moment où il est lancé, la cible/zone devient un enchantement qui déclanche les effets si une cible viable la touche ou débute son round à son contact, ce qui décharge une fois l'enchantement | H33: PWR -1
A34: Chaos | B34: Forme | C34: Structure | D34: Off, Def, Eff, Enc | E34: 0 | F34: 0 | G34: Le sort s'applique sur X cibles (aléatoires) parmi Y cibles dans la zone d'effet | H34: PWR +Y-X (max 3)
A35: Vague | B35: Forme | C35: Structure | D35: Off, Eff | E35: 0 | F35: 0 | G35: Le sort, nécessairement en AOE, ne touche que les premières cibles d'une même lignes (en provenance de la cible d'origine de l'AOE), celles qui sont derrière ne sont pas affectée | H35: PWR +1 | I35: Eau
A36: Orbe | B36: Forme | C36: Structure | D36: Off, Def, Eff | E36: 2 | F36: 2 | G36: Comme statique mais peux être déplacé via une ACTL du lanceur de sort, AOE maximum 5 | H36: PWR -2
A37: Myriade | B37: Forme | C37: Structure | D37: Off, Eff | E37: 2X | F37: 2X | G37: Le sort s'applique X fois sur la cible | H37: PWR -3
A38: Pluie | B38: Forme | C38: Structure | D38: Off, Def, Eff | E38: 0 | F38: 0 | G38: Le sort s'applique au moment où il est lancé puis aux cinq rounds d'après, même cible, la cible doit être un lieu | H38: PWR -3/-3/-3/-3/-3/-3 (6)
A39: Sol | B39: Forme | C39: Structure | D39: Off, Def, Eff | E39: 0 | F39: 0 | G39: Le sort ne s'applique pas au moment où il est lancé, la cible/zone devient un enchantement qui déclanche les effets si une cible viable la touche ou débute son round à son contact | H39: PWR -3
A40: Epieu | B40: Forme | C40: Structure | D40: Off | E40: 2 | F40: 2 | G40: Le projectile issus du sort traverse chaque cible qui se trouve sur son passage, chaque nouvelle cible subit des effets réduits (PWR -1) | H40: PWR +0/-1/-2/... (9)
A41: Global | B41: Forme | C41: Structure | D41: Enc | E41: 2 | F41: 2 | G41: L'enchantement contenu dans le sort s'applique de façon globale sur la zone de propagation, tant qu'une créature est dans la zone en question elle est affectée par l'enchantement, dés qu'elle en sort ce n'est plus le cas, si un test de sauvegarde doit être réalisé il l'est une fois seulement
A42: * | B42: * | C42: * | D42: * | E42: * | F42: * | G42: *
A43: Lieu | B43: Forme | C43: Propagation | E43: 6 | F43: 6 | G43: Le sort affecte le lieu entier de la scène, le sort doit avoir pour cible un lieu | I43: Terre
G47: Mot qui ajoute un test de sauvegarde sinon le sort a son jet augmenté
G48: Mot de forme ricochet associé à l'élec, mais ça doit déjà exister
G49: Sort qui agit à chaque tour sur une zone (perpétuel)
G50: Auras qui inflige des dégats ou status si on approche de la cible
G54: ::::::: Clés de Propagation
G55: - propagation en aoe autour d'une source élément
G56: -> clé de propagation : sur toutes les cibles plongée dans la lumière d'une lumière unique (lumière)
G57: -> clé de propagation : sur toutes les cibles plongée dans l'ombre d'une lumière unique (ombre)
G58: -> clé de propagation : Ombre / lumière : affecte une cible de plus si elles sont baignées dans l'ombre ou lumière (diff +2 par cibles en plus)
G60: -> mot clé qui n'augmente pas la difficulté mais réduit le drain en mana de 4 et augmente le niveau d'un sort de 1 si le mage peux utiliser une source de matière/énergie à proximité (donc uniquement les domaines où ça a du sens)
G61: meme chose en enchantement qui permet au mage d'ajouter cette clé à la volée lorsqu'il cast un sort
G62: le domaine "magie" peux faire fonctionner cela sur n'importe quel élément mais avec une réduction de drain réduit ?
... G70: Nuage - qui se déplace ou reste statique et délivre des dégats ou un status tel que poison
A71: Fragmentation | G71: Les sorts se propage par fragmentation d’une matière qui explose ?
G72: Le sort produit un piège magique d'une case à la place d'une attaque magique
G73: Pluie -
G74: Terrestre - Mot pour que la magie vienne du sol (cad une collone montante) permet aussi d'ignorer les covers
G75: Céleste - Mot pour que la magie tombe du ciel (si ouvert ou suffisament d'espace) permet d'ignorer les covers

Sheet Dest
A1: ✸
A2: Latin | B2: Mot arcanique | C2: Mot vulguaire | D2: Type de Mot | E2: Type de Cible | F2: Difficulté | G2: Drain | H2: Description | I2: Clés | J2: Prod
A3: Ruptura (Rupture) | B3: Kinrupt (Kin + rupt) | C3: Destruction | D3: Pouvoir | E3: Cible | F3: 2 | G3: 2 | H3: Produit un effet d'attaque physique (armure) infligeant [Magnitude] de dégats physique (PV) basés sur l'élément [clé] | I3: 🔥 Feu: Kinruptar (vs FOR), ❄️ Glace: Kinruptis (vs DEX), ⚡ Foudre: Kinruptor (vs AGI), ☠️ Mort: Kinruptus (vs CON), ☢️ Toxique: Kinruptex (vs CON), ⚔️ Acier: Kinruptan (vs FOR, DEX, AGI, PER), 🌿 Flore: Kinruptiln (vs PER) | J3: =CONCAT(CONCAT(C3, " "),$A$1)
A4: Iungo (Joindre) | B4: Keljung (Kel + jung) | C4: Conjuration | D4: Pouvoir | E4: Cible | F4: 2 | G4: 2 | H4: Produit un effet d'attaque physique (armure) infligeant [Magnitude x0.66] de dégats physique (PV) basés sur l'élément des arcanes | I4: ✡️ Arcane: Keljungys (vs MAG) | J4: =CONCAT(CONCAT(C4, " "),$A$1)
A5: Occulto (Cacher) | B5: Krucclt (Kru + cclt) | C5: Mystification | D5: Pouvoir | E5: Cible | F5: 2 | G5: 2 | H5: Produit un effet d'attaque physique (armure) infligeant [Magnitude] de dégats mentaux (PS) basés sur l'élément [clé] | I5: 🎭 Illusion: Kruccltin (vs VOL) | J5: =CONCAT(CONCAT(C5, " "),$A$1)
A6: Nihil (Rien) | B6: Kranihil (Kra + nihil) | C6: Annihilation | D6: Pouvoir | E6: Cible | F6: 2 | G6: 2 | H6: Produit un effet d'attaque mentale (résolution) infligeant [Magnitude] de dégats physique (PV) basés sur l'élément [clé] | I6: ⚖️ Loi: Kranihilem (vs VOL), 🌀 Chaos: Kranihilix (vs VOL), ✨ Sacre: Kranihiliel (vs SAG), 🩸 Impie: Kranihilun (vs RUS) | J6: =CONCAT(CONCAT(C6, " "),$A$1)
A7: Profano (Souiller) | B7: Kaprofan (Ka + profan) | C7: Profanation | D7: Pouvoir | E7: Cible | F7: 2 | G7: 2 | H7: Produit un effet d'attaque mentale (résolution) infligeant [Magnitude] de dégats mentaux (PS) basés sur l'élément [clé] | I7: 🧩 Mental: Kaprofanend (vs VOL) | J7: =CONCAT(CONCAT(C7, " "),$A$1)
A8: Gressus (Pas, marche) | B8: Kintrans (Kin + trans) | C8: Transgression | D8: Pouvoir | E8: Cible | F8: 2 | G8: 2 | H8: Produit un effet d'attaque mentale (résolution) infligeant [Magnitude] de dégats karmique (PK) basés sur l'élément [clé] | I8: ⚖️ Loi: Kintransem (vs VOL) | J8: =CONCAT(CONCAT(C8, " "),$A$1)
A9: Luo (Payer, laver) | B9: Krulex (Kru + lex) | C9: Expiation | D9: Pouvoir | E9: Cible | F9: 2 | G9: 2 | H9: Produit un effet d'attaque mentale (résolution) infligeant [Magnitude] de dégats pranique (PC) basés sur l'élément [clé] | I9: ☢️ Toxique: Krulexex (vs VOL) | J9: =CONCAT(CONCAT(C9, " "),$A$1)
A10: Torsio (Torsion) | B10: Keltor (Kel + tor) | C10: Distorsion | D10: Pouvoir | E10: Cible | F10: 2 | G10: 2 | H10: Produit un effet d'attaque mentale (résolution) infligeant [Magnitude] de dégats arcanique (PM) basés sur l'élément [clé] | I10: ✡️ Arcane: Keltorys (vs MAG) | J10: =CONCAT(CONCAT(C10, " "),$A$1)
A11: Radix (Racine) | B11: Karadix (Ka + radix) | C11: Eradication | D11: Pouvoir | E11: Cible | F11: 2 | G11: 2 | H11: Produit un effet d'attaque (ni armure, ni résolution) infligeant [Magnitude/2] de dégats physique (PV) basés sur l'élément [clé] | I11: ☀️ Lumière: Karadixion (vs PER), 🌑 Ombre: Karadixoth (vs PER), ☢️ Toxique: Karadixex (vs CON) | J11: =CONCAT(CONCAT(C11, " "),$A$1)
A12: Vasto (Je dévaste) | B12: Kordevast (Kor + devast) | C12: Dévastation | D12: Pouvoir | E12: Cible | F12: 2 | G12: 2 | H12: Produit un effet d'attaque (ni armure, ni résolution) infligeant [Magnitude/2] de dégats mentaux (PS) basés sur l'élément [clé] | I12: ☀️ Lumière: Kordevastion (vs SAG), 🌑 Ombre: Kordevastoth (vs SAG) | J12: =CONCAT(CONCAT(C12, " "),$A$1)
A13: Moveo (Bouger, remuer) | B13: Krucomov (Kru + comov) | C13: Commotion | D13: Pouvoir | E13: Cible | F13: 2 | G13: 2 | H13: Produit un effet d'attaque physique (armure) infligeant [Magnitude x1.5] de dégats physique choquants (condition physique de choc, en état de choc si charge > PV actuelles) basés sur l'élément [clé] (état de choc = épuisé, actions -2) | I13: ✨ Sacre: Krucomoviel (vs SAG), 🩸 Impie: Krucomovun (vs RUS) | J13: =CONCAT(CONCAT(C13, " "),$A$1)
A14: Turbo (Troubler) | B14: Kraturb (Kra + turb) | C14: Perturbation | D14: Pouvoir | E14: Cible | F14: 2 | G14: 2 | H14: Produit un effet d'attaque mentale (résolution) infligeant [Magnitude x1.5] de dégats mentaux choquants (condition mentale de choc, en état de choc si charge > PS actuelles) basés sur l'élément [clé] (état de choc = épuisé, actions -2) | I14: 🎭 Illusion: Kraturbin (vs VOL) | J14: =CONCAT(CONCAT(C14, " "),$A$1)
... A76: ??? | B76: ??? | C76: Conséquence | D76: Interruption | E76: Cible | F76: 2 | G76: 2 | H76: Produit un effet d'attaque (ni armure, ni résolution) infligeant [Magnitude] de dégats temporaires (PE) basés sur l'élément [clé], le sort ne peux être lancé que si une créature dans la zone a perdu des PV ou des PS suite à une attaque, la cible doit être l'auteur et unique | I76: ⚖️ Loi | J76: =CONCAT(CONCAT(C76, " "),$A$1)

Sheet Rest
A1: ⌖
A2: Latin | B2: Mot arcanique | C2: Mot vulguaire | D2: Type de Mot | E2: Type de Cible | F2: Difficulté | G2: Drain | H2: Description
A3: Instauro (Je rétablis) | B3: Restaura (Re + staura) | C3: Restauration | D3: Pouvoir | E3: Cible | F3: 2 | G3: 2 | H3: Produit un soin de [Magnitude/2] visant une ressource qui dépends de la [clé], ce soin n'est pas dispensé des règles des soins naturels et de la fatigue (voir guérison dans les règles de base) | I3: ❤️ Vie: Restaurair (PV), 🧩 Mental: Restauraend (PS), 🌀 Chaos: Restauraix (PK), ⚕️ Corps: Restauraen (PC), 🧠 Esprit: Restaurays (PC), 🔮 Magie: Restaurairn (PM), 🪷 Nature: Restauraeiln (PC/PE/fatigue) | J3: =CONCAT(CONCAT(C3, " "),$A$1)
A4: Vita (Vie) | B4: Renvita (Ren + vita) | C4: Vivification | D4: Pouvoir | E4: Cible | F4: 2 | G4: 2 | H4: Produit un soin de [Magnitude/2] pour les PV & PS ainsi qu'une recharge d'autant de charges de l'invocation ciblée (dont le type correspond à la [clé] utilisée) | I4: ='Règles'!C143 | J4: =CONCAT(CONCAT(C4, " "),$A$1)
A5: Vigor (Force, Vigueur) | B5: Ryuvigo (Ryu + vigo) | C5: Revitalisation | D5: Pouvoir | E5: Cible | F5: 2 | G5: 2 | H5: Produit un soin de l'endurance (PE) équivalant à la moitié des PE manquants, avec pour maximum [Magnitude], ce soin est dispensé des règles des soins naturels et de la fatigue | I5: 🪷 Nature: Ryuvigoeiln | J5: =CONCAT(CONCAT(C5, " "),$A$1)
A6: Roboro (Je fortifie) | B6: Rhorobor (Rho + robor) | C6: Réinvigoration | D6: Pouvoir | E6: Cible | F6: 2 | G6: 2 | H6: Produit un soin de [Magnitude/2] visant l'endurance (PE), ce soin est dispensé des règles des soins naturels et de la fatigue | I6: 🪷 Nature: Rhoroboreiln | J6: =CONCAT(CONCAT(C6, " "),$A$1)
A7: Fundo (Je verse) | B7: Refund (Re + fund) | C7: Transfusion | D7: Pouvoir | E7: Cible | F7: 2 | G7: 2 | H7: Produit un soin qui convertis [Magnitude/2] chi (PC) en [Magnitude] endurance (PE), ce soin est dispensé des règles des soins naturels et de la fatigue | I7: 🪷 Nature: Refundeiln | J7: =CONCAT(CONCAT(C7, " "),$A$1)
A8: Magnus (Grand) | B8: Relmagnus (Rel + magnus) | C8: Grandiloquence | D8: Pouvoir | E8: Cible | F8: 2 | G8: 2 | H8: Produit un soin de [Magnitude] de n'importe quelle ressource, à la fin de la scène ces ressources sont immédiatement perdus (ce qui peux entrainer la mort ou le passage en négatif d'une ressource), ce soin est dispensé des règles des soins naturels et de la fatigue | I8: 🎭 Illusion: Relmagnusin | J8: =CONCAT(CONCAT(C8, " "),$A$1)
A9: Vigor (Force, Vigueur) | B9: Rasvigore (Ras + vigore) | C9: Revigoration | D9: Pouvoir | E9: Cible | F9: 2 | G9: 2 | H9: Produit un soin de [Magnitude/3] visant la fatigue | I9: 🪷 Nature: Rasvigoreiln | J9: =CONCAT(CONCAT(C9, " "),$A$1)
A10: Purgo (Je nettoie) | B10: Rhopurgo (Rho + purgo) | C10: Purification | D10: Pouvoir | E10: Cible | F10: 2 | G10: 2 | H10: Produit un soin de [Magnitude/4] visant la corruption | I10: 🪷 Nature: Rhopurgoeiln | J10: =CONCAT(CONCAT(C10, " "),$A$1)
A11: Canalis (Conduit) | B11: Recana (Re + cana) | C11: Canalisation | D11: Pouvoir | E11: Cible | F11: 2 | G11: 2 | H11: Produit un soin qui convertis un maximum de [Magnitude] points de garde/adrénaline/rage ou leurs équivalants mentaux (selon la [clé] utilisée) en 2 PE chaques, l'éxcédant est acquis en PE temporaires | I11: 🛡️ Guerre: Recanaorr, 🧩 Mental: Recanaend | J11: =CONCAT(CONCAT(C11, " "),$A$1)
A12: Solvo (Délier) | B12: Rensolvo (Ren + solvo) | C12: Dissolution | D12: Pouvoir | E12: Cible | F12: 2 | G12: 2 | H12: Génère un soin de [Magnitude x2] visant une condition négative de nature spécifique (la nature de la condition doit être éligible à la [clé]) affectant la cible | I12: ⚕️ Corps: Rensolvoen, 🧠 Esprit: Rensolvoys | J12: =CONCAT(CONCAT(C12, " "),$A$1)
A13: Neuter (Ni l'un ni l'autre) | B13: Rasneuta (Ras + neuta) | C13: Neutralisation | D13: Pouvoir | E13: Cible | F13: 2 | G13: 2 | H13: Génère un soin de [Magnitude] visant une condition négative au choix (physique ou mentale selon la [clé]) affectant la cible | I13: ⚕️ Corps: Rasneutaen, 🧠 Esprit: Rasneutays | J13: =CONCAT(CONCAT(C13, " "),$A$1)
A14: Absolvo (Je délie) | B14: Rhoabsol (Rho + absol) | C14: Absolution | D14: Pouvoir | E14: Cible | F14: 2 | G14: 2 | H14: Génère un soin de [Magnitude/2] visant toutes les conditions négatives (physique et mentale) affectant la cible | I14: 🪷 Nature: Rhoabsoleiln | J14: =CONCAT(CONCAT(C14, " "),$A$1)
A15: Integrare | B15: Aenintegr | C15: Intégration | D15: Pouvoir | E15: Cible | F15: 2 | G15: 2 | H15: Produit un effet soignant [Magnitude]/5 points d'un attribut du corps associé à [clé] | I15: ⚕️ Corps: Resoliden (Force, Dextérité, Agilité, Perception, Constitution) | J15: =CONCAT(CONCAT(C15, " "),$A$1)
A16: Solidus (Solide) | B16: Resolid (Re + solid) | C16: Consolidation | D16: Pouvoir | E16: Cible | F16: 2 | G16: 2 | H16: Produit un effet soignant [Magnitude]/5 points d'un attribut de l'esprit associé à [clé] | I16: 🧠 Esprit: Relumenys (Charisme, Intelligence, Ruse, Sagesse, Volonté) | J16: =CONCAT(CONCAT(C16, " "),$A$1)
... A36: Sanguis (Sang) | B36: Haemosang (Hae + mosang) | C36: Emoglobine | D36: Pouvoir | E36: Cible | F36: 2 | G36: 2 | H36: Génère un effet qui soigne [Magnitude/5] PV la cible pour chaque fois où le sang a été versé durant la scène et dans la zone, après quoi ces itérations ne peuvent plus compter pour des effets du genre, le gain de fatigue à ces soins est divisé par deux | I36: 🩸 Impie | J36: =CONCAT(CONCAT(C36, " "),$A$1)

Sheet Abju
A1: ⛊
A2: Latin | B2: Mot arcanique | C2: Mot vulguaire | D2: Type de Mot | E2: Type de Cible | F2: Difficulté | G2: Drain | H2: Description
A3: Imbueo (Imprégner) | B3: Borimbue (Bor + imbue) | C3: Imprégnation | D3: Interruption | E3: Cible | F3: 2 | G3: 2 | H3: Génère un effet qui augmente la difficulté arcanique d'un autre sort en cours de lancement de [Magnitude/5] | I3: 🔮 Magie: Borimbueirn | J3: =CONCAT(CONCAT(C3, " "),$A$1)
A4: Deverto (Détourner) | B4: Brivert (Bri + vert) | C4: Déviation | D4: Interruption | E4: Cible | F4: 2 | G4: 2 | H4: Génère un effet qui génère [Magnitude] de la déviation physique ou mentale chez la cible lorsqu'elle est la cible d'une attaque ou tactique physique ou mentale (selon la clé), la clé de magie permet donc de générer de la déviation à l'égard de toute forme de magie | I4: 🛡️ Guerre: Brivertorr, 🧩 Mental: Brivertend, 🔮 Magie: Briverteirn | J4: =CONCAT(CONCAT(C4, " "),$A$1)
A5: Minuo (Diminuer) | B5: Basminu (Bas + minu) | C5: Réduction | D5: Interruption | E5: Cible | F5: 2 | G5: 2 | H5: Génère un effet qui réduit la magnitude de [Magnitude] le niveau du sort qui affecte la cible | I5: ✡️ Arcane: Basminuys | J5: =CONCAT(CONCAT(C5, " "),$A$1)
A6: Fallo (Tromper) | B6: Brenfallo (Bren + fallo) | C6: Désenchantement | D6: Pouvoir | E6: Lieu/Cible | F6: 2 | G6: 2 | H6: Génère un effet qui provoque une décharge de [Magnitude/2] à tous les enchantements affectant la cible (lieu ou cible) | I6: 🪷 Nature: Brenfalloeiln | J6: =CONCAT(CONCAT(C6, " "),$A$1)
A7: Premo (Presser, supprimer) | B7: Barpremo (Bar + premo) | C7: Suppression | D7: Pouvoir | E7: Cible | F7: 2 | G7: 2 | H7: Génère un effet qui provoque une décharge de [Magnitude] à un enchantement ciblé | I7: ✡️ Arcane: Barpremoys | J7: =CONCAT(CONCAT(C7, " "),$A$1)
A8: Vitio (Corrompre) | B8: Borviti (Bor + viti) | C8: Corruption | D8: Pouvoir | E8: Cible | F8: 2 | G8: 2 | H8: Génère un effet qui retire jusqu'à [Magnitude/2] charges à un enchantement positif ciblé, la cible contracte à la place une condition négative (issus du répertoire d'un des domaines naturels : Nature, toxique ou bois), la cible peux réaliser un test de sauvegarde concernant cette condition | I8: ☢️ Toxique: Borvitiex | J8: =CONCAT(CONCAT(C8, " "),$A$1)
A9: Muto (Changer) | B9: Basmutatio (Bas + mutatio) | C9: Convertion | D9: Pouvoir | E9: Cible | F9: 2 | G9: 2 | H9: Génère un effet qui retire jusqu'à [Magnitude/2] charges à un enchantement négatif ciblé, la cible contracte à la place une condition positif (issus du répertoire d'un des domaines naturels : Nature, toxique ou bois) | I9: 🪷 Nature: Basmutatioeiln | J9: =CONCAT(CONCAT(C9, " "),$A$1)
A10: Confisco (Confisquer) | B10: Brinfisc (Bri + fisc) | C10: Confiscation | D10: Pouvoir | E10: Cible | F10: 2 | G10: 2 | H10: Génère un effet qui octroie le contrôle de l'enchantement ciblé si ce dernier a une charge restante inférieure à [Magnitude], prendre le contrôle d'un enchantement n'y met pas fin ou ne permet pas de le déplacer, cependant une invocation considère les ordres de ce nouveau maitre à la place par example (voir les règles des Arcanes) | I10: 🔮 Magie: Brinfisceirn | J10: =CONCAT(CONCAT(C10, " "),$A$1)
A11: Locus (Lieu) | B11: Barlocus (Bar + locus) | C11: Délocalisation | D11: Pouvoir | E11: Cible | F11: 2 | G11: 2 | H11: Génère un effet qui permet de déplacer l'enchantement de cible (qui doit rester une cible valide au regard du sort à son origine) si ce dernier a une charge restante inférieure à [Magnitude], déplacer le contrôle d'un enchantement n'en donne pas le contrôle, on ne peux déplacer un enchantement d'invocation (voir les règles des Arcanes) | I11: 🔮 Magie: Barlocuseirn | J11: =CONCAT(CONCAT(C11, " "),$A$1)
A12: Casso (Détruire, annuler) | B12: Belcasso (Bel + casso) | C12: Annulation | D12: Interruption | E12: Cible | F12: 2 | G12: 2 | H12: Génère un effet qui annule l'action à venir de la cible cette dernière a moins de [Magnitude] en endurance actuelle, un test de sauvegarde de détermination peux permettre de réduire les effets, l'action entreprise est perdue si annulée | I12: ⚜️ Charme: Belcassoynh | J12: =CONCAT(CONCAT(C12, " "),$A$1)
A13: Ago (Agir) | B13: Basago (Bas + ago) | C13: Rétroaction | D13: Interruption | E13: Cible | F13: 4 | G13: 4 | H13: Génère un effet qui retourne l'action à venir de la cible contre elle même à moins qu'elle ne dispose de [Magnitude/2] en endurance actuelle, un test de sauvegarde de détermination peux permettre de réduire les effets | I13: ⚜️ Charme: Basagoynh | J13: =CONCAT(CONCAT(C13, " "),$A$1)
A14: Tego (Protéger, couvrir) | B14: Brentu (Bren + tu) | C14: Protection | D14: Barrière | E14: Cible | F14: 2 | G14: 2 | H14: Génère un enchantement neutre de type barrière physique pouvant absorber jusqu'à [Magnitude] dégats (attention car les barrières s'appliquent avant la réduction de dégats et autre ressors défensif des cibles) | I14: ✡️ Arcane: Brentuys | J14: =CONCAT(CONCAT(C14, " "),$A$1)
... A55: ??? | B55: ??? | C55: Sacrilège | D55: Interruption | E55: Cible | F55: 2 | G55: 2 | H55: Génère un effet qui inverse les effets de soins du sort ciblé, convertis une maximum de [Magnitude] du sort ciblé en question (inverse 2 de soins sur un total de 4 provoque donc un soin de 0 au final) | I55: 🩸 Impie | J55: =CONCAT(CONCAT(C55, " "),$A$1)

Sheet Evoc
A1: ⧉
A2: Latin | B2: Mot arcanique | C2: Mot vulguaire | D2: Type de Mot | E2: Type de Cible | F2: Difficulté | G2: Drain | H2: Description
A3: Vibro (Agiter, secouer) | B3: Evvibro (Ev + vibro) | C3: Galvanisation | D3: Pouvoir | E3: Cible | F3: 2 | G3: 2 | H3: Génère un effet octroyant [Magnitude/2] points temporaires d'une ressource qui dépends de la [clé] | I3: ❤️ Vie: Evvibroir (PV), 🧩 Mental: Evvibroend (PS), 🌀 Chaos: Evvibroix (PK), ⚕️ Corps: Evvibroen (PC), 🧠 Esprit: Evvibroys (PC), 🔮 Magie: Evvibroirn (PM), 🪷 Nature: Evvibroeiln (PE/fatigue) | J3: =CONCAT(CONCAT(C3, " "),$A$1)
A4: Corruptio (Briser, détruire) | B4: Enruptio (En + ruptio) | C4: Corruption | D4: Pouvoir | E4: Cible | F4: 2 | G4: 2 | H4: Génère un effet octroyant [Magnitude/5] points de corruption temporaires | I4: ✡️ Arcane: Enruptioys | J4: =CONCAT(CONCAT(C4, " "),$A$1)
A5: Energia (Force) | B5: Eloenrgi (Elo + enrgi) | C5: Énergisation | D5: Pouvoir | E5: Cible | F5: 2 | G5: 2 | H5: Génère un effet octroyant [Magnitude] points d'endurance (PE) temporaires | I5: 🪷 Nature: Eloenrgieiln | J5: =CONCAT(CONCAT(C5, " "),$A$1)
A6: Traho (Tirer) | B6: Eruatrat (Eru + atrat) | C6: Attraction | D6: Pouvoir | E6: Cible (point) | F6: 2 | G6: 2 | H6: Génère un effet d'attraction agissant comme l'action tactique de déplacement forcé avec un jet de [Magnitude] et attirant en son centre toutes les cibles dans la zone d'effet, de fait le sort doit inclure une zone d'effet, la cible doit être touchée (défense passive FOR dépassée) et peux s'en défendre normalement (comme s'il s'agissait d'une tactique) | I6: 💢 Vide: Eruatratarh | J6: =CONCAT(CONCAT(C6, " "),$A$1)
A7: Pello (Pousser, chasser) | B7: Evpello (Ev + pello) | C7: Répulsion | D7: Pouvoir | E7: Cible (point) | F7: 2 | G7: 2 | H7: Génère un effet de répulsion agissant comme l'action tactique de déplacement forcé avec un jet de [Magnitude] et repoussant de son centre toutes les cibles dans la zone d'effet, de fait le sort doit inclure une zone d'effet, la cible doit être touchée (défense passive AGI dépassée) et peux s'en défendre normalement (comme s'il s'agissait d'une tactique) | I7: 🌪️ Air: Evpelloel | J7: =CONCAT(CONCAT(C7, " "),$A$1)
A8: Leves (Léger) | B8: Enleves (En + leves) | C8: Lévitation | D8: Interruption | E8: Cible (point) | F8: 2 | G8: 2 | H8: Réduit la chute de la cible de [Magnitude/2] mètres | I8: 🌪️ Air: Enlevesel | J8: =CONCAT(CONCAT(C8, " "),$A$1)
A9: Precipito (Lancer en avant) | B9: Elopreci (Elo + preci) | C9: Précipitation | D9: Interruption | E9: Cible (point) | F9: 2 | G9: 2 | H9: Augmente la chute de la cible de [Magnitude/2] mètres | I9: 🪨 Terre: Eloprecium | J9: =CONCAT(CONCAT(C9, " "),$A$1)
A10: Pello (Pousser en avant) | B10: Erupuls (Eru + puls) | C10: Propulsion | D10: Pouvoir | E10: Cible (point) | F10: 2 | G10: 2 | H10: Génère un effet de déplacement agissant comme l'action tactique de déplacement forcé avec un jet de [Magnitude] sur une cible dans la direction opposée au lanceur du sort | I10: 🌪️ Air: Erupulsel | J10: =CONCAT(CONCAT(C10, " "),$A$1)
A11: Traho (Tirer) | B11: Evtract (Ev + tract) | C11: Traction | D11: Pouvoir | E11: Cible (point) | F11: 2 | G11: 2 | H11: Génère un effet de déplacement agissant comme l'action tactique de déplacement forcé avec un jet de [Magnitude] sur une cible dans la direction du lanceur du sort | I11: 💢 Vide: Evtractarh | J11: =CONCAT(CONCAT(C11, " "),$A$1)
A12: Fero (Porter) | B12: Enlata (En + lata) | C12: Translation | D12: Pouvoir | E12: Cible (point) | F12: 2 | G12: 2 | H12: Déplace une cible inerte de [Magnitude] mètres, sur une cible non inerte le sort agit comme un déplacement forcé avec la moitié de la magnitude (vs robustesse), les distances de collision sont divisées par deux le cas échéant | I12: ✡️ Arcane: Enlatays | J12: =CONCAT(CONCAT(C12, " "),$A$1)
A13: ??? | B13: ??? | C13: Émergence | D13: Pouvoir | E13: Cible | F13: 2 | G13: 2 | H13: Produit un effet qui génère [Magnitude/5] d'unités solide, [Magnitude] d'unités gazeux ou [Magnitude/2] d'unités liquide, une unité vaux 1 case x 1 case, d'un élément vulgaire qui dépends de la [clé] | I13: 🪨 Terre: Elomaterum, 💧 Eau: Elomateryn, 🌪️ Air: ElomaTerrel | J13: =CONCAT(CONCAT(C13, " "),$A$1)
A14: Manus (Main) | B14: Erumanu (Eru + manu) | C14: Manipulation | D14: Pouvoir | E14: Cible | F14: 2 | G14: 2 | H14: Réalise une action manuelle avec [Magnitude] de Force et Dextérité, l'action peux être une attaque ou n'importe quoi d'autre | I14: ✡️ Arcane: Erumanuys | J14: =CONCAT(CONCAT(C14, " "),$A$1)
... A87: Libero (Libérer) | B87: Aliber (Al + liber) | C87: Libération | D87: Pouvoir | E87: Cible | F87: 2 | G87: 2 | H87: Génère un effet qui déclanche chez la cible un test visant à recouvrir la liberté (en fonction de comment cette notion de liberté est menacée) avec un bonus de [Magnitude/3], ce sort peux être lancé en interruption lorsqu'un allié subit une perte/privation de liberté | I87: 🌀 Chaos | J87: =CONCAT(CONCAT(C87, " "),$A$1)
C89: Ignition | D89: Pouvoir | E89: Cible | F89: 2 | G89: 2 | H89: déclancher les objets dans l'inventaire adverse
C90: Inversion | D90: Pouvoir | E90: Cible | F90: 2 | G90: 2 | H90: déclancher les objets mais inverse leurs effets ?
H91: inverse le moral | I91: ⚜️ Charme
H92: Génère des pts de stratégie avec un plan (en gros équivalant à une stratégie)

Sheet Béné
A1: ✧
A2: Latin | B2: Mot arcanique | C2: Mot vulguaire | D2: Type de Mot | E2: Type de Cible | F2: Difficulté | G2: Drain | H2: Description
A3: Vigor (Force, vigueur) | B3: Lokvigor (Lok + vigor) | C3: Revigoration | D3: Pouvoir | E3: Cible | F3: 2 | G3: 2 | H3: Génère un enchantement positif qui augmente toutes les récupérations de [Magnitude/10], notons que pour en profiter lors d'un repos il est nécessaire que le lanceur de sort ai procédé à un rituel ou qu'il reste éveillé pour maintenir le sort | I3: 🪷 Nature: Lokvigoreiln | J3: =CONCAT(CONCAT(C3, " "),$A$1)
A4: Reddo (Rendre, restituer) | B4: Luxreddo (Lux + reddo) | C4: Restitution | D4: Pouvoir | E4: Cible | F4: 2 | G4: 2 | H4: Génère un enchantement positif qui augmente la récupération d'une ressource qui dépends de la [clé] associée de [Magnitude/5], notons que pour en profiter lors d'un repos il est nécessaire que le lanceur de sort ai procédé à un rituel ou qu'il reste éveillé pour maintenir le sort | I4: ❤️ Vie: Luxreddoir (PV), 🧩 Mental: Luxreddoend (PS), 🌀 Chaos: Luxreddoix (PK), ⚕️ Corps: Luxreddoen (PC), 🧠 Esprit: Luxreddoys (PC), 🔮 Magie: Luxreddoirn (PM), 🪷 Nature: Luxreddoeiln (PE/fatigue) | J4: =CONCAT(CONCAT(C4, " "),$A$1)
A5: Benedico (Dire du bien) | B5: Lembene (Lem + bene) | C5: Bénédiction | D5: Pouvoir | E5: Cible | F5: 2 | G5: 2 | H5: Génère un enchantement positif qui augmente de [Magnitude/10] la plage des singularités positives (exploits) | I5: ✨ Sacre: Lembeneiel | J5: =CONCAT(CONCAT(C5, " "),$A$1)
A6: ??? | B6: ??? | C6: Assainissement | D6: Pouvoir | E6: Cible | F6: 2 | G6: 2 | H6: Produit un enchantement positif qui réduit les charges de [Magnitude/2] des conditions négatives reçues, il est possible de concentrer l'effet sur un domaine de magie unique pour lequel l'effet sera doublé (via [clé]) (les autres domaines n'en profitent alors plus | I6: 🪷 Nature: Lirpurgoeiln | J6: =CONCAT(CONCAT(C6, " "),$A$1)
A7: ??? | B7: ??? | C7: Exhaussement | D7: Pouvoir | E7: Cible | F7: 2 | G7: 2 | H7: Produit un enchantement positif qui double les charges, maximum [Magnitude], les effets des conditions positives, il est possible de concentrer l'effet sur un domaine de magie unique pour lequel l'effet sera doublé (via [clé]) (les autres domaines n'en profitent alors plus | I7: 🪷 Nature: Lynallus eiln | J7: =CONCAT(CONCAT(C7, " "),$A$1)
A8: Actus (Action) | B8: Luxactus (Lux + actus) | C8: Réactivation | D8: Pouvoir | E8: Cible | F8: 2 | G8: 2 | H8: Produit un effet d'enchantement positif provoquant à chaque tour les effets d'un autre [mot de pouvoir] prodiguant des soins avec une magnitude divisée par deux | I8: 🪷 Nature: Luxactus eiln | J8: =CONCAT(CONCAT(C8, " "),$A$1)
A9: Leves (Léger) | B9: Lemleves (Lem + leves) | C9: Allégement | D9: Pouvoir | E9: Cible | F9: 2 | G9: 2 | H9: Génère un enchantement positif qui réduit le poids effectif de la cible de [Magnitude]% (arrondis supérieur) | I9: 💢 Vide: Lemlevesarh | J9: =CONCAT(CONCAT(C9, " "),$A$1)
A10: Onus (Fardeau) | B10: Lironus (Lir + onus) | C10: Délestement | D10: Pouvoir | E10: Cible | F10: 2 | G10: 2 | H10: Génère un enchantement positif qui réduit le poids effectif de la cible de [Magnitude/4] | I10: 🌪️ Air: Lironusel | J10: =CONCAT(CONCAT(C10, " "),$A$1)
A11: ??? | B11: ??? | C11: Consolidement | D11: Pouvoir | E11: Cible | F11: 2 | G11: 2 | H11: Génère un enchantement positif qui augmente le poids maximum de la cible de [Magnitude/4] | I11: ⚕️ Corps: Lynfirmen | J11: =CONCAT(CONCAT(C11, " "),$A$1)
A12: ??? | B12: ??? | C12: Dissipation | D12: Pouvoir | E12: Cible | F12: 2 | G12: 2 | H12: Génère un enchantement positif qui réduit la distance des chutes de [Magnitude/4], maximum la moitié | I12: 🌪️ Air: Luxmorsel | J12: =CONCAT(CONCAT(C12, " "),$A$1)
A13: Liber (Libre) | B13: Lemliber (Lem + liber) | C13: Libération | D13: Pouvoir | E13: Cible | F13: 2 | G13: 2 | H13: Génère un enchantement positif qui permet d'ignorer jusqu'à [Magnitude/10] pénalité lié au déplacement | I13: 🌪️ Air: Lemliberel | J13: =CONCAT(CONCAT(C13, " "),$A$1)
A14: ??? | B14: ??? | C14: Équilibrage | D14: Pouvoir | E14: Cible | F14: 2 | G14: 2 | H14: Génère un enchantement positif qui réduit de [Magnitude/3] le jet de déplacement forcé subit | I14: 🪨 Terre: Lirstabum | J14: =CONCAT(CONCAT(C14, " "),$A$1)
... A179: Bestialis (Bestial) | B179: Lembestia (Lem + bestia) | C179: Bestialisation | D179: Pouvoir | E179: Cible | F179: 2 | G179: 2 | H179: Génère un enchantement positif qui augmente un attribut (définit à la création du sort selon la [clé]) de [Magnitude/4], si l'attribut est physique alors tous les attributs mentaux sont réduits de 4 et inversement | I179: 🐗 Faune: Lembestiarh (FOR, CON, DEX, AGI, PER, CHA, VOL, INT, RUS, SAG) | J179: =CONCAT(CONCAT(C179, " "),$A$1)
H181: Coups de chance bonus +M/5 ?
H182: régénère les pts d'une stratégie
H183: enchantement qui up les attaques magiques ? attention, y a peut être un équivalant ci dessus (y a quand même 180 béné lol)
H184: le personnage peux lancer des sorts de niveau plus élevés
H185: Tant que la cible n'attaque pas elle a un bonus de défense
H186: Béné qui up les actions focales
H187: Béné qui up l'entrainement de la cible à un sujet, pouvant aller au delà de 2 (le max naturel)

Sheet Malé
A1: ⧖
A2: Latin | B2: Mot arcanique | C2: Mot vulguaire | D2: Type de Mot | E2: Type de Cible | F2: Difficulté | G2: Drain | H2: Description
A3: ??? | B3: ??? | C3: Blâme | D3: Pouvoir | E3: Cible | F3: 2 | G3: 2 | H3: Génère un enchantement négatif qui réduit toutes les récupérations de [Magnitude/10], notons que pour que cela affecte un repos il est nécessaire que le lanceur de sort ai procédé à un rituel ou qu'il reste éveillé pour maintenir le sort | I3: 🪷 Nature: Maldamnoeiln | J3: =CONCAT(CONCAT(C3, " "),$A$1)
A4: ??? | B4: ??? | C4: Drainage | D4: Pouvoir | E4: Cible | F4: 2 | G4: 2 | H4: Génère un enchantement négatif qui réduit la récupération d'une ressource qui dépends de la [clé] associée de [Magnitude/5], notons que pour que cela soit actif lors d'un repos il est nécessaire que le lanceur de sort ai procédé à un rituel ou qu'il reste éveillé pour maintenir le sort | I4: ☠️ Mort: Morsiccus (PV), 🧩 Mental: Morsiccoend (PS), ⚖️ Loi: Morsiccoem (PK), ⚕️ Corps: Morsiccoen (PC), 🧠 Esprit: Morsiccoys (PC), ✡️ Arcane: Morsiccoys (PM), 🪷 Nature: Morsiccoeiln (PE/fatigue) | J4: =CONCAT(CONCAT(C4, " "),$A$1)
A5: Execror (Maudire) | B5: Mugxecro (Mug + xecro) | C5: Malédiction | D5: Pouvoir | E5: Cible | F5: 2 | G5: 2 | H5: Génère un enchantement négatif qui augmente de [Magnitude/10] la plage des singularités négatives (maladresses) | I5: 🩸 Impie: Mugxecroun | J5: =CONCAT(CONCAT(C5, " "),$A$1)
A6: Disipo (Disperser) | B6: Mundisi (Mun + disi) | C6: Dissipation | D6: Pouvoir | E6: Cible | F6: 2 | G6: 2 | H6: Produit un enchantement négatif qui réduit les charges de [Magnitude/2] des conditions positives, il est possible de concentrer l'effet sur un domaine de magie unique pour lequel l'effet sera doublé (via [clé]) (les autres domaines n'en profitent alors plus | I6: ☢️ Toxique: Mundisiex | J6: =CONCAT(CONCAT(C6, " "),$A$1)
A7: Acerbus (Acre, amer) | B7: Malacerb (Mal + acerb) | C7: Exacerbation | D7: Pouvoir | E7: Cible | F7: 2 | G7: 2 | H7: Produit un enchantement négatif qui double les charges, maximum [Magnitude], les effets des conditions négatives, il est possible de concentrer l'effet sur un domaine de magie unique pour lequel l'effet sera doublé (via [clé]) (les autres domaines n'en profitent alors plus | I7: ☢️ Toxique: Malacerbex | J7: =CONCAT(CONCAT(C7, " "),$A$1)
A8: Mutilo (Mutiler) | B8: Mormuti (Mor + muti) | C8: Mutilation | D8: Pouvoir | E8: Cible | F8: 2 | G8: 2 | H8: Produit un effet d'enchantement négatif provoquant à chaque tour les effets d'un autre [mot de pouvoir] infligeant des dégats avec une magnitude divisée par deux, un test de sauvegarde permet d'en réduire les effets (robustesse si dégats physiques, détermination si dégats mentaux, etc) | I8: ☢️ Toxique: Mormutiex | J8: =CONCAT(CONCAT(C8, " "),$A$1)
A9: ??? | B9: ??? | C9: Lestage | D9: Pouvoir | E9: Cible | F9: 2 | G9: 2 | H9: Génère un enchantement négatif qui augmente le poids effectif de la cible de [Magnitude]% (arrondis supérieur) | I9: 💢 Vide: Muggravarh | J9: =CONCAT(CONCAT(C9, " "),$A$1)
A10: Massa (Masse) | B10: Munmas (Mun + mas) | C10: Massification | D10: Pouvoir | E10: Cible | F10: 2 | G10: 2 | H10: Génère un enchantement négatif qui augmente le poids effectif de la cible de [Magnitude/4] | I10: 🪨 Terre: Munmasum | J10: =CONCAT(CONCAT(C10, " "),$A$1)
A11: Debilito (Affaiblir) | B11: Maldeb (Mal + deb) | C11: Affaiblissement | D11: Pouvoir | E11: Cible | F11: 2 | G11: 2 | H11: Génère un enchantement négatif qui réduit le poids maximum de la cible de [Magnitude/4] | I11: ⚕️ Corps: Maldeben | J11: =CONCAT(CONCAT(C11, " "),$A$1)
A12: Pello (Pousser) | B12: Morexp (Mor + exp) | C12: Expulsion | D12: Pouvoir | E12: Cible | F12: 2 | G12: 2 | H12: Génère un enchantement négatif qui accroit la distance des déplacements forcés de [Magnitude/4], maximum le double | I12: 🌪️ Air: Morexpel | J12: =CONCAT(CONCAT(C12, " "),$A$1)
A13: Ruina (Chute) | B13: Mugruin (Mug + ruin) | C13: Effondrement | D13: Pouvoir | E13: Cible | F13: 2 | G13: 2 | H13: Génère un enchantement négatif qui accroit la distance des chutes de [Magnitude/4], maximum le double | I13: 🪨 Terre: Mugruinum | J13: =CONCAT(CONCAT(C13, " "),$A$1)
A14: Impedio (Empêcher) | B14: Muniped (Mun + iped) | C14: Inertie | D14: Pouvoir | E14: Cible | F14: 2 | G14: 2 | H14: Génère un enchantement négatif qui permet d'augmenter de [Magnitude/10] les pénalités liés au déplacement | I14: 🪨 Terre: Munipedum | J14: =CONCAT(CONCAT(C14, " "),$A$1)
... A80: Rodo (Ronger) | B80: Morerode (Mor + erode) | C80: Usure | D80: Pouvoir | E80: Cible (objet) | F80: 2 | G80: 2 | H80: Génère un enchantement négatif qui double la déterioration que subit l'objet, tous les 2 points augmentés de cet manière réduisent la charge de cet enchantement de 1 | I80: ⚔️ Acier: Morerodean | J80: =CONCAT(CONCAT(C80, " "),$A$1)
A81: Fritus (Brisé) | B81: Mugfrite (Mug + frite) | C81: Effritement | D81: Pouvoir | E81: Cible (objet) | F81: 2 | G81: 2 | H81: Génère un enchantement négatif qui éffrite l'objet ciblé, ce dernier subissant un malus de solidité de [Magnitude/5] | I81: ⚔️ Acier: Mugfritean | J81: =CONCAT(CONCAT(C81, " "),$A$1) | K81: Pouvoir | L81: Cible (objet) | M81: 2 | N81: 2 | O81: Génère un enchantement positif qui renforce l'objet ciblé, ce dernier profitant d'un bonus de solidité de [Magnitude/5] | P81: ⚔️ Acier | Q81: Solidication | R81: Pouvoir | S81: Cible (objet) | T81: 2 | U81: 2 | V81: Génère un enchantement positif qui renforce l'objet ciblé, ce dernier profitant d'un bonus de solidité de [Magnitude/5] | W81: ⚔️ Acier | X81: Solidication | Y81: Pouvoir | Z81: Cible (objet) | AA81: 2 | AB81: 2 | AC81: Génère un enchantement positif qui renforce l'objet ciblé, ce dernier profitant d'un bonus de solidité de [Magnitude/5] | AD81: ⚔️ Acier
A82: ??? | B82: ??? | C82: Amoindrissement | D82: Pouvoir | E82: Cible (objet) | F82: 2 | G82: 2 | H82: Génère un enchantement négatif qui fragilise l'objet ciblé, ce dernier réalisant ses test de solidité avec un malus de [Magnitude/3] | I82: ⚔️ Acier: Munfirmuan | J82: =CONCAT(CONCAT(C82, " "),$A$1) | K82: Pouvoir | L82: Cible (objet) | M82: 2 | N82: 2 | O82: Génère un enchantement positif qui protège l'objet ciblé, ce dernier réalisant ses test de solidité avec un bonus de [Magnitude/3] | P82: ⚔️ Acier | R82: Pouvoir | S82: Cible (objet) | T82: 2 | U82: 2 | V82: Génère un enchantement positif qui protège l'objet ciblé, ce dernier réalisant ses test de solidité avec un bonus de [Magnitude/3] | W82: ⚔️ Acier | Y82: Pouvoir | Z82: Cible (objet) | AA82: 2 | AB82: 2 | AC82: Génère un enchantement positif qui protège l'objet ciblé, ce dernier réalisant ses test de solidité avec un bonus de [Magnitude/3] | AD82: ⚔️ Acier
A83: Frango (Briser) | B83: Malafran (Mal + afran) | C83: Fracturation | D83: Pouvoir | E83: Cible (objet) | F83: 2 | G83: 2 | H83: Génère un enchantement négatif qui émousse l'objet ciblé, ce dernier imposant des test de solidité réduits de [Magnitude/3] | I83: ⚔️ Acier: Malafranan | J83: =CONCAT(CONCAT(C83, " "),$A$1) | K83: Pouvoir | L83: Cible (objet) | M83: 2 | N83: 2 | O83: Génère un enchantement positif qui acère l'objet ciblé, ce dernier imposant des test de solidité augmentés de [Magnitude/3] | P83: ⚔️ Acier | R83: Pouvoir | S83: Cible (objet) | T83: 2 | U83: 2 | V83: Génère un enchantement positif qui acère l'objet ciblé, ce dernier imposant des test de solidité augmentés de [Magnitude/3] | W83: ⚔️ Acier | Y83: Pouvoir | Z83: Cible (objet) | AA83: 2 | AB83: 2 | AC83: Génère un enchantement positif qui acère l'objet ciblé, ce dernier imposant des test de solidité augmentés de [Magnitude/3] | AD83: ⚔️ Acier
A84: Obturo (Boucher) | B84: Morobtur (Mor + obtur) | C84: Obturation | D84: Pouvoir | E84: Cible (objet) | F84: 2 | G84: 2 | H84: Génère un enchantement négatif qui rend l'objet cassant, ce dernier subissant la moitié de ses jets à chaque usage sous forme de détérioration, maximum [Magnitude/3] | I84: ⚔️ Acier: Morobtu ran | J84: =CONCAT(CONCAT(C84, " "),$A$1) | K84: Pouvoir | L84: Cible (objet) | M84: 2 | N84: 2 | O84: Génère un enchantement positif qui acère l'objet ciblé, ce dernier imposant des test de solidité augmentés de [Magnitude/3] | P84: ⚔️ Acier | R84: Pouvoir | S84: Cible (objet) | T84: 2 | U84: 2 | V84: Génère un enchantement positif qui acère l'objet ciblé, ce dernier imposant des test de solidité augmentés de [Magnitude/3] | W84: ⚔️ Acier | Y84: Pouvoir | Z84: Cible (objet) | AA84: 2 | AB84: 2 | AC84: Génère un enchantement positif qui acère l'objet ciblé, ce dernier imposant des test de solidité augmentés de [Magnitude/3] | AD84: ⚔️ Acier
A85: Littera (Lettre) | B85: Muglitera (Mug + litera) | C85: Oblitération | D85: Pouvoir | E85: Cible | F85: 2 | G85: 2 | H85: Génère un enchantement négatif qui réduit la mémoire de la cible de [Magnitude/4], tout ce qui a été appris en dernier et qui ne rentre plus dans la mémoire actuelle est considéré comme oublié du temps de l'enchantement, de plus la cible oublie un nombre d'élément clé (de nature très précise) équivalant au malus (par example l'existance d'une clé, ou ce qu'il était en train de faire bien que cela ne l'empêche pas de vouloir faire la chose si son raisonnement l'y amène) | I85: 📚 Savoir: Mugliteraaum | J85: =CONCAT(CONCAT(C85, " "),$A$1)
A86: Arceo (Arcer) | B86: Munarceo (Mun + arceo) | C86: Interdiction | D86: Pouvoir | E86: Cible | F86: 2 | G86: 2 | H86: Génère un enchantement négatif qui impose une pénalité de [Magnitude/4] aux actions visant à agresser une cible (attaque ou tactique, mais pas uniquement, c'est au MD de trancher si une action constitue une agression ou non) | I86: ⚖️ Loi: Munarceoem | J86: =CONCAT(CONCAT(C86, " "),$A$1)
A87: Tribuo (Donner) | B87: Maltribu (Mal + tribu) | C87: Rétribution | D87: Pouvoir | E87: Cible | F87: 2 | G87: 2 | H87: Génère un enchantement négatif qui inflige des dégats temporaires (ignorant toute défenses) équivalant à [Magnitude/3] si la cible entreprend une action visant à agresser une cible (attaque ou tactique, mais pas uniquement, c'est au MD de trancher si une action constitue une agression ou non) | I87: ✨ Sacre: Maltribuiel | J87: =CONCAT(CONCAT(C87, " "),$A$1)
A88: Contrarius (Contraire) | B88: Morcontra (Mor + contra) | C88: Contrariation | D88: Pouvoir | E88: Cible | F88: 2 | G88: 2 | H88: Génère un enchantement négatif qui octroie un malus aux jets des actions dont la nature dépends de la clé de [Magnitude/3], chaque occurence provoque une décharge de l'enchantement | I88: 🔥 Feu: Morcontraar (défense), ❄️ Glace: Morcontrais (attaque), ⚡ Foudre: Morcontraor (tactique) | J88: =CONCAT(CONCAT(C88, " "),$A$1)
A89: Precipito (Lancer) | B89: Mugpreci (Mug + preci) | C89: Précipitation | D89: Pouvoir | E89: Cible | F89: 2 | G89: 2 | H89: Génère un enchantement négatif qui inflige des dégats temporaires (ignorant toute défenses) équivalant à [Magnitude/3] à la cible à la fin de n'importe quel tour où la cible n'a pas entrepris d'action de déplacement profitant de l'aLure | I89: ⚡ Foudre: Mugprecior | J89: =CONCAT(CONCAT(C89, " "),$A$1)
A90: Precor (Prier) | B90: Munprec (Mun + prec) | C90: Déprécation | D90: Pouvoir | E90: Cible | F90: 2 | G90: 2 | H90: Génère un enchantement négatif qui octroie à la cible des pénalités très marquée contre un élément donné, cela se traduit par une réduction de [Magnitude/4] en absorption, [Magnitude/6] en protection et [Magnitude/6] de malus aux sauvegardes | I90: 🔥 Feu: Munprecar, ❄️ Glace: Munprecis, ⚡ Foudre: Munprecor, 🪨 Terre: Munprecum, 💧 Eau: Munprecyn, 🌪️ Air: Munprecel, ☀️ Lumière: Munprecion, 🌑 Ombre: Munprecoth, ⚖️ Loi: Munprecem, 🌀 Chaos: Munprecix, ✨ Sacre: Munpreciel, 🩸 Impie: Munprecun, ❤️ Vie: Munprecir, ☠️ Mort: Munprecus, ⚕️ Corps: Munprece n, 🧠 Esprit: Munprecys, 🐗 Faune: Munprecorh, 🌿 Flore: Munpreciln, 🧩 Mental: Munprecend, ⚜️ Charme: Munprecynh, ✡️ Arcane: Munprecys, 🔮 Magie: Munprecirn, 🪷 Nature: Munpreceiln, ☢️ Toxique: Munprecex, 🎭 Illusion: Munprecin, 📚 Savoir: Munprecaum, 👁️ Vision: Munpreceth, ⚔️ Acier: Munprecan, 🛡️ Guerre: Munprecorr, 💢 Vide: Munprecarh | J90: =CONCAT(CONCAT(C90, " "),$A$1)
A91: Dico (Dire) | B91: Malabdi (Mal + abdi) | C91: Abdication | D91: Pouvoir | E91: Cible | F91: 2 | G91: 2 | H91: Génère un enchantement négatif qui résigne la cible à ne plus intervenir dans une confrontation, elle ne se laisse pas faire mais ne s'implique plus non plus, cet effet s'applique si la cible a moins de [Magnitude] d'endurance et des pénalités de lésions cumulées supérieurs à 8 - [Magnitude/5] | I91: ⚜️ Charme: Malabdiy nh | J91: =CONCAT(CONCAT(C91, " "),$A$1)
A92: Reprobus (Réprouvé) | B92: MoRepro (Mor + repro) | C92: Réprobation | D92: Pouvoir | E92: Cible | F92: 2 | G92: 2 | H92: Génère un enchantement négatif qui duplique les lésions physiques en lésions mentales ou les lésions mentales en lésions physiques, les copies ne peuvent dépasser un total de gravité de [Magnitude] ni être individuellement d'un niveau de gravité supérieure à [Magnitude/7] | I92: ☠️ Mort: MoReprous | J92: =CONCAT(CONCAT(C92, " "),$A$1)
A93: Gigno (Engendrer) | B93: Mugdegen (Mug + degen) | C93: Dégénération | D93: Pouvoir | E93: Cible | F93: 2 | G93: 2 | H93: Produit un enchantement négatif qui réduit à chaque tour [Magnitude/5] points de ressources (selon la clé) | I93: ☠️ Mort: Mugdegenus (PV), 🧩 Mental: Mugdegenend (PS), ⚖️ Loi: Mugdegenem (PK), ⚕️ Corps: Mugdegenen (PC), 🧠 Esprit: Mugdegenys (PC), ✡️ Arcane: Mugdegenys (PM), 🪷 Nature: Mugdegeneiln (PE/fatigue) | J93: =CONCAT(CONCAT(C93, " "),$A$1)
A94: Vehemens (Violent) | B94: Munvehe (Mun + vehe) | C94: Intensification | D94: Pouvoir | E94: Cible | F94: 2 | G94: 2 | H94: Génère un enchantement négatif augmentant les effets des conditions négatives dont les charges sont inférieures à [Magnitude] sur la cible (les conditions normales ont les effets de conditions améliorées et les conditions améliorées ont des effets encore améliorés d'un cran, si numériquement applicable) | I94: 🩸 Impie: Munveheun | J94: =CONCAT(CONCAT(C94, " "),$A$1)
A95: ??? | B95: ??? | C95: Blocage | D95: Pouvoir | E95: Cible | F95: 2 | G95: 2 | H95: Génère un enchantement négatif réduisant les effets des conditions positives dont les charges sont inférieures à [Magnitude] sur la cible (les conditions normales ne font plus effet et les de conditions améliorées ont des effets normaux) | I95: 🩸 Impie: Malneutun | J95: =CONCAT(CONCAT(C95, " "),$A$1)
A96: Sacro (Rendre sacré) | B96: Morsacro (Mor + sacro) | C96: Désacralisation | D96: Pouvoir | E96: Cible | F96: 2 | G96: 2 | H96: Génère un enchantement négatif qui augmente de [Magnitude/10] le cout des relances en karma d'un même test | I96: 🩸 Impie: Morsacroun | J96: =CONCAT(CONCAT(C96, " "),$A$1)
... A104: ??? | B104: ??? | C104: Suractivation | D104: Pouvoir | E104: Cible | F104: 2 | G104: 2 | H104: Génère un enchantement négatif qui force les enchantements négatifs affectants la cible de se recharger de [Magnitude/4] à la fin de chaque tour | I104: 💢 Vide: Moramploarh | J104: =CONCAT(CONCAT(C104, " "),$A$1)
A105: Voco (Appeler) | B105: Mugvoca (Mug + voca) | C105: Révocation | D105: Pouvoir | E105: Cible | F105: 2 | G105: 2 | H105: Génère un enchantement négatif qui force la cible à relancer (l'ensemble d')un test affichant un exploit, chaque occurence provoque une décharge de l'enchantement | I105: ⚖️ Loi: Mugvocaem | J105: =CONCAT(CONCAT(C105, " "),$A$1) | O105: Génère un enchantement positif qui permet à la cible de relancer (l'ensemble d')un test affichant une maladresse, chaque occurence provoque une décharge de l'enchantement | P105: 🌀 Chaos | V105: Génère un enchantement positif qui permet à la cible de relancer (l'ensemble d')un test affichant une maladresse, chaque occurence provoque une décharge de l'enchantement | W105: 🌀 Chaos | AC105: Génère un enchantement positif qui permet à la cible de relancer (l'ensemble d')un test affichant une maladresse, chaque occurence provoque une décharge de l'enchantement | AD105: 🌀 Chaos
A106: Lumen (Lumière) | B106: Munlumen (Mun + lumen) | C106: Illumination | D106: Pouvoir | E106: Cible | F106: 2 | G106: 2 | H106: Génère un enchantement négatif qui rend la cible plus visible, réduisant la difficulté pour le percevoir visuellement de [Magnitude/4] | I106: ☀️ Lumière: Munlumenion | J106: =CONCAT(CONCAT(C106, " "),$A$1)
A107: Clamor (Clameur) | B107: Malclam (Mal + clam) | C107: Résonation | D107: Pouvoir | E107: Cible | F107: 2 | G107: 2 | H107: Génère un enchantement négatif qui rend la cible plus bruyante, réduisant la difficulté pour l'entendre de [Magnitude/4] | I107: ☀️ Lumière: Malclamion | J107: =CONCAT(CONCAT(C107, " "),$A$1)
A108: Mano (Couler, émaner) | B108: Mormana (Mor + mana) | C108: Émanation | D108: Pouvoir | E108: Cible | F108: 2 | G108: 2 | H108: Génère un enchantement positif qui rend la cible plus odorante et plus perceptible, réduisant la difficulté pour la sentir (odeur ou touché) de [Magnitude/4] | I108: ☀️ Lumière: Mormanaion | J108: =CONCAT(CONCAT(C108, " "),$A$1)
A109: Focus (Foyer) | B109: Mugfocus (Mug + focus) | C109: Focalisation | D109: Pouvoir | E109: Cible | F109: 2 | G109: 2 | H109: Génère un enchantement négatif qui révèle la vraie nature de la cible, on parle ici du karma notament (alignement, etc), la vraie nature est alors plus simple à percevoir pour ceux qui en sont capable ou la cible ne peux se dérober à l'observation, la difficulté associée à son étude étant réduite de [Magnitude/4] | I109: ☀️ Lumière: Mugfocusion | J109: =CONCAT(CONCAT(C109, " "),$A$1)
A110: Pono (Placer) | B110: Munponi (Mun + poni) | C110: Exposition | D110: Pouvoir | E110: Cible | F110: 2 | G110: 2 | H110: Génère un enchantement négatif qui rend la cible moins difficile à dicerner avec précision, ses défenses passives sont réduites de [Magnitude/6] | I110: ☀️ Lumière: Munponiion | J110: =CONCAT(CONCAT(C110, " "),$A$1)
A111: ??? | B111: ??? | C111: Divulgation | D111: Pouvoir | E111: Cible | F111: 2 | G111: 2 | H111: Créer un enchantement négatif qui réduit la capacité de la cible à se couvrir via des obstacles, le % de couverture est divisé par deux, avec une réduction maximale de [Magnitude] | I111: ☀️ Lumière: Malveloion | J111: =CONCAT(CONCAT(C111, " "),$A$1)
A112: Limes (Limite) | B112: Morlimes (Mor + limes) | C112: Limitation | D112: Pouvoir | E112: Cible | F112: 2 | G112: 2 | H112: Génère un enchantement négatif qui réduit le maximum des dés de tous les jets de la cible de [Magnitude/8], avec un minimum ainsi modifié de 2 (pour ce qui est de cet enchantement en tout cas) | I112: 🩸 Impie: Morlimesun | J112: =CONCAT(CONCAT(C112, " "),$A$1)
A113: Optimus (Le meilleur) | B113: Mugopti (Mug + opti) | C113: Désoptimisation | D113: Pouvoir | E113: Cible | F113: 2 | G113: 2 | H113: Génère un enchantement négatif qui réduit le maximum des dés de tous les tests de la cible de [Magnitude/8], cet effet n'affecte que le premier lancé et donc pas les relances via karma, lorsque l'enchantement est lancé le lanceur de sort peux décider que cet effet affecte X relance en plus si il décide de réduire la Magnitude de 10 par X | I113: 🩸 Impie: Mugoptiun | J113: =CONCAT(CONCAT(C113, " "),$A$1)
A114: Turbo (Troubler) | B114: Munturb (Mun + turb) | C114: Perturbation | D114: Pouvoir | E114: Cible | F114: 2 | G114: 2 | H114: Génère un enchantement négatif qui rend la cible plus sensibles aux émotions négatives, impose un malus pour y résister de [Magnitude/3] | I114: ⚜️ Charme: Munturbynh | J114: =CONCAT(CONCAT(C114, " "),$A$1)
A115: Condemno (Condamner) | B115: Malconde (Mal + conde) | C115: Condamnation | D115: Pouvoir | E115: Cible | F115: 2 | G115: 2 | H115: Génère un enchantement négatif qui attends la mort de la cible afin de déclencher les effets d'un autre [mot de pouvoir] avec la magnitude du sort qui doit être nécessairement un effet de dégats, l'effet a une rayon de 1m, le lanceur de sort peux décider de réduire la magnitude du sort de 1/5, 1/4 ou 1/3 afin de respectivement augmenter ce rayon à 2, 4 ou 8. Les dégats sont sujets aux règles de dégats de zone, etc... | I115: ☠️ Mort: Malcondeus | J115: =CONCAT(CONCAT(C115, " "),$A$1)
A116: Flagro (Brûler) | B116: Morflagro (Mor + flagro) | C116: Déflagration | D116: Pouvoir | E116: Cible | F116: 4 | G116: 2 | H116: Génère un enchantement négatif qui attends la mise hors d'état de la cible (PV <= 0) afin de déclencher les effets d'un autre [mot de pouvoir] avec les 2/3 de la magnitude du sort qui doit être nécessairement un effet de dégats, l'effet a une rayon de 1m, le lanceur de sort peux décider de réduire la magnitude du sort de 1/5, 1/4 ou 1/3 afin de respectivement augmenter ce rayon à 2, 4 ou 8. Les dégats sont sujets aux règles de dégats de zone, etc... La cible de l'enchantement est elle même affectée par le sort mais pour elle ce ne sont pas des dégats de zone. | I116: ☠️ Mort: Morflagrous | J116: =CONCAT(CONCAT(C116, " "),$A$1)
A117: Frustra (En vain) | B117: Mugfrustr (Mug + frustr) | C117: Frustration | D117: Pouvoir | E117: Cible | F117: 2 | G117: 2 | H117: Génère un enchantement négatif qui ajoute aux lésions de la cible [Magnitude/3] de gravité, au mieux la gravité peux être ainsi doublée | I117: ☠️ Mort: Mugfrustrus | J117: =CONCAT(CONCAT(C117, " "),$A$1)
... A184: Furor (Fureur) | B184: Mugfuror (Mug + furor) | C184: Rage | D184: Pouvoir | E184: Cible | F184: 2 | G184: 2 | H184: Génère un enchantement qui induit une rage magique, sachant que cet enchantement ne peux être maintenu et dispose de [Magnitude/2] charges, la cible ne pense plus et s'attaque (avec les moyens les plus sévères) à la cible la plus proche d'elle (elle exclus), cet effet ne fonctionne pas sur les adversaires dont le rang est égal ou supérieur à celui du lanceur de sort | I184: ⚜️ Charme | J184: =CONCAT(CONCAT(C184, " "),$A$1)
H185: enchantement qui down les attaques magiques ? attention, y a peut être un équivalant ci dessus
H186: le personnage peux lancer des sorts de niveau plus élevés <= inverse, donc réduit
H187: Prive la cible de l'envie d'attaquer (pacifisme)
H188: Malé qui up les critiques reçus par la cible ? (existe déjà ?) (vérifier si l'inverse existe en béné)
H189: Malé qui réduit la MR nécessaire pour recevoir un critique (qui arrive donc plus souvent) (existe déjà ?) (vérifier si l'inverse existe en béné)

Sheet Invoc
A1: ✪
A2: Latin | B2: Mot arcanique | C2: Mot vulguaire | D2: Type de Mot | E2: Type de Cible | F2: Difficulté | G2: Drain | H2: Description
A3: Elementum (Élément) | B3: Voele (Vo + ele) | C3: Elémentaire | D3: Pouvoir | E3: Cible (lieu) | F3: 4 | G3: 6 | H3: Génère un enchantement qui invoque une créature de type élémentaire au choix parmis les archétypes existants via une [clé], la charge est de [Magnitude] | I3: 🔥 Feu: Voelear, ❄️ Glace: Voeleis, ⚡ Foudre: Voeleor, 🪨 Terre: Voeleum, 💧 Eau: Voeleyn, 🌪️ Air: Voeleel, ☀️ Lumière: Voeleion, 🌑 Ombre: Voeleoth, ⚖️ Loi: Voeleem, 🌀 Chaos: Voeleix, 💢 Vide: Voele arh, ❤️ Vie: Voeleir, ☢️ Toxique: Voeleex | J3: =CONCAT(CONCAT(C3, " "),$A$1)
A4: Ignis (Feu) | B4: Vanignis (Van + ignis) | C4: Empyréen | D4: Pouvoir | E4: Cible (lieu) | F4: 4 | G4: 6 | H4: Génère un enchantement qui invoque une créature de type empyréen au choix parmis les archétypes existants via une [clé], la charge est de [Magnitude] | I4: ✨ Sacre: Vanignisiel | J4: =CONCAT(CONCAT(C4, " "),$A$1)
A5: Terra (Terre) | B5: Vorterra (Vor + terra) | C5: Hypogéen | D5: Pouvoir | E5: Cible (lieu) | F5: 4 | G5: 6 | H5: Génère un enchantement qui invoque une créature de type hypogéen au choix parmis les archétypes existants via une [clé], la charge est de [Magnitude] | I5: 🩸 Impie: Vorterraun | J5: =CONCAT(CONCAT(C5, " "),$A$1)
A6: Spiritus (Souffle) | B6: Vaspiri (Vas + spiri) | C6: Esprit | D6: Pouvoir | E6: Cible (lieu) | F6: 4 | G6: 6 | H6: Génère un enchantement qui invoque une créature de type esprit au choix parmis les archétypes existants via une [clé], la charge est de [Magnitude] | I6: 🪷 Nature: Vaspirieiln | J6: =CONCAT(CONCAT(C6, " "),$A$1)
A7: Signum (Signe) | B7: Vosign (Vo + sign) | C7: Zodiaque | D7: Pouvoir | E7: Cible (lieu) | F7: 4 | G7: 6 | H7: Génère un enchantement qui invoque une créature de type zodiacal au choix parmis les archétypes existants via une [clé], la charge est de [Magnitude] | I7: 🪷 Nature: Vosign eiln | J7: =CONCAT(CONCAT(C7, " "),$A$1)
A8: Arcanum (Secret) | B8: Vanarca (Van + arca) | C8: Arcane | D8: Pouvoir | E8: Cible (lieu) | F8: 4 | G8: 6 | H8: Génère un enchantement qui invoque une créature de type arcanique au choix parmis les archétypes existants via une [clé], la charge est de [Magnitude] | I8: ✡️ Arcane: Vanarcays | J8: =CONCAT(CONCAT(C8, " "),$A$1)
A9: Anima (Âme) | B9: Voranim (Vor + anim) | C9: Objet (animé) | D9: Pouvoir | E9: Cible (lieu) | F9: 4 | G9: 6 | H9: Génère un enchantement qui invoque une créature de type objet au choix parmis les archétypes existants via une [clé], la charge est de [Magnitude] | I9: ⚔️ Acier: Voraniman | J9: =CONCAT(CONCAT(C9, " "),$A$1)
A10: Appareo (Apparaître) | B10: Vasapar (Vas + apar) | C10: Manifestation | D10: Pouvoir | E10: Cible (lieu) | F10: 4 | G10: 6 | H10: Génère un enchantement qui invoque une créature de type manifestation au choix parmis les archétypes existants via une [clé], la charge est de [Magnitude] | I10: 🛡️ Guerre: Vasaparorr | J10: =CONCAT(CONCAT(C10, " "),$A$1)
A11: Fera (Bête sauvage) | B11: Vofera (Vo + fera) | C11: Bête | D11: Pouvoir | E11: Cible (lieu) | F11: 4 | G11: 6 | H11: Génère un enchantement qui invoque une créature de type bête au choix parmis les archétypes existants via une [clé], la charge est de [Magnitude] | I11: 🐗 Faune: Voferaorh | J11: =CONCAT(CONCAT(C11, " "),$A$1)
A12: Herba (Herbe, plante) | B12: Vanherba (Van + herba) | C12: Plante | D12: Pouvoir | E12: Cible (lieu) | F12: 4 | G12: 6 | H12: Génère un enchantement qui invoque une créature de type plante au choix parmis les archétypes existants via une [clé], la charge est de [Magnitude] | I12: 🌿 Flore: Vanherba iln | J12: =CONCAT(CONCAT(C12, " "),$A$1)
A13: Crepusculum (Crépuscule) | B13: Vorcrep (Vor + crep) | C13: Crépusculaire | D13: Pouvoir | E13: Cible (lieu) | F13: 4 | G13: 6 | H13: Génère un enchantement qui invoque une créature de type crépusculaire au choix parmis les archétypes existants via une [clé], ces choix inclus tous les choix de la liste des bêtes, des guerriers et des mystique, mais dans une version mort vivant, la charge est de [Magnitude] | I13: ☠️ Mort: Vorcrepus | J13: =CONCAT(CONCAT(C13, " "),$A$1)
A14: Illusio (Moquerie) | B14: Vasilusi (Vas + ilusi) | C14: Illusion | D14: Pouvoir | E14: Cible (lieu) | F14: 4 | G14: 6 | H14: Génère un enchantement qui invoque une créature de type iLusoire au choix parmis les archétypes existants via une [clé], ces choix inclus tous les choix de la liste des bêtes et des guerriers, mais dans une version iLusoire, la charge est de [Magnitude] | I14: 🎭 Illusion: Vasilusiin | J14: =CONCAT(CONCAT(C14, " "),$A$1)
... A28: Ultimus (Dernier) | B28: Vanultim (Van + ultim) | C28: Ultime | D28: Liaison | E28: / | F28: 6 | G28: 6 | H28: L'invocation voit tous ses attributs augmentés de 6, le sort doit être de niveau 5 minimum, un seul mot du même type à la fois | I28: 🔮 Magie: Vanultimirn | J28: =CONCAT(CONCAT(C28, " "),$A$1)

Sheet Divi
A1: ⊙
A2: Latin | B2: Mot arcanique | C2: Mot vulguaire | D2: Type de Mot | E2: Type de Cible | F2: Difficulté | G2: Drain | H2: Description | I2: Colonne 1
A3: Retro (Arrière) + Nosco (Connaître) | B3: Diretro (Di + retro) | C3: Rétrocognition | D3: Pouvoir | E3: Cible | F3: 2 | G3: 2 | H3: Génère un effet permettant au lanceur de sort de consulter le passé de la cible, jusqu'à [Magnitude]² minutes dans le passé, la vision en question n'est pas lié aux sens de la cible mais en est totalement indépendant | I3: 👁️ Vision: Diretroeth | J3: =CONCAT(CONCAT(C3, " "),$A$1)
A4: Prae (Avant) + Nosco (Connaître) | B4: Dornosc (Dor + nosc) | C4: Précognition | D4: Pouvoir | E4: Cible | F4: 2 | G4: 2 | H4: Génère un effet permettant au lanceur de sort de consulter le futur de la cible, jusqu'à [Magnitude]² minutes dans l'avenir, cette vision ne se fait pas pars le prisme des sens ou de la perception de la cible mais d'une façon plus extérieur et neutre, ce futur peux changer si quelque chose le préviens mais la nature du monde cherchera à contourner tout changement trop important, le changement doit donc être drastique pour forcer la main du destin | I4: 👁️ Vision: Dornosceth | J4: =CONCAT(CONCAT(C4, " "),$A$1)
A5: Memoria (Mémoire) | B5: Delmemo (Del + memo) | C5: Remémoration | D5: Pouvoir | E5: Cible | F5: 2 | G5: 2 | H5: Génère un effet permettant au lanceur de sort de consulter la mémoire de la cible, jusqu'à [Magnitude]² minutes dans le temps, ne permet pas de voir ou entendre ce que le personnage n'a pas compris ou réellement vécu via ses sens | I5: 👁️ Vision: Delmemoeth | J5: =CONCAT(CONCAT(C5, " "),$A$1)
A6: Scrutator (Examiner) | B6: Darsrut (Dar + srut) | C6: Scrutation | D6: Pouvoir | E6: Cible | F6: 4 | G6: 0 | H6: Génère un effet permettant à la cible de consulter ce qui se passe à l'instant T à un lieu précis dont la distance est mieux de [Magnitude]² mètres, le phénomène est trop rapide pour que les cibles épiées puissent le sentir, mais aussi trop court pour entendre toute une conservation entre deux interlocuteur (au mieux le curieux peux recevoir les informations sur une grosse minute de temps) | I6: 👁️ Vision: Darsruteth | J6: =CONCAT(CONCAT(C6, " "),$A$1)
A7: Idem (Le même) | B7: Diidem (Di + idem) | C7: Identification | D7: Pouvoir | E7: Cible | F7: 2 | G7: 2 | H7: Génère un effet permettant au lanceur de sort de savoir des choses sur la cible (détails du à quoi ça sert, ou d'une personne tel que son noms/positions/align, etc) jusqu'à un maximum de [Magnitude/10] détails | I7: 📚 Savoir: Diidemaum | J7: =CONCAT(CONCAT(C7, " "),$A$1)
A8: Firmo (Affirmer) | B8: Dorfirmo (Dor + firmo) | C8: Confirmation | D8: Pouvoir | E8: Cible | F8: 2 | G8: 2 | H8: Génère un effet permettant au lanceur de sort de valider des choses sur la cible (détails du à quoi ça sert, ou d'une personne tel que son noms/positions/align, etc) jusqu'à un maximum de [Magnitude/5] détails, la réponse à chaque question est "oui" ou "non", parfois "oui et non" si non applicable | I8: 📚 Savoir: Dorfirmo aum | J8: =CONCAT(CONCAT(C8, " "),$A$1)
A9: Pono (Poser) | B9: Delponi (Del + poni) | C9: Supposition | D9: Pouvoir | E9: Cible | F9: 2 | G9: 2 | H9: Génère un effet permettant au lanceur de sort de consulter le futur de la cible selon le prisme d'une hypothèse/d'une action/d'un choix, jusqu'à [Magnitude] minutes dans le passé, la vision en question n'est pas lié aux sens de la cible mais en est totalement indépendant | I9: 👁️ Vision: Delponieth | J9: =CONCAT(CONCAT(C9, " "),$A$1)
A10: Oraculum (Oracle) | B10: Darora (Dar + ora) | C10: Oraculation | D10: Pouvoir | E10: Cible | F10: 2 | G10: 2 | H10: Génère un effet permettant au lanceur de sort de connaitre la solution à un problème (une piste de résolution pour un problème donné) avec des détails dépendants d'un potenciel fixé par la [Magnitude], tout d'abord le lanceur de sort définit la nature (0 : seulement les éléments connus uniquement, 5 : parmi des éléments connus indirectement, 10 : même parmi des éléments inconnus) et la précision (0 : sybillin, 5 : imprécis, 10 : précis) de la solution qu'il recherche, ce qui réduit le potenciel selon le choix, puis le nombre de mots maximum est de 5 par points de potenciel restant | I10: 📚 Savoir: Darora aum | J10: =CONCAT(CONCAT(C10, " "),$A$1)
A11: Rogo (Questionner) | B11: Diroga (Di + roga) | C11: Interrogation | D11: Pouvoir | E11: Cible | F11: 2 | G11: 2 | H11: Génère un effet permettant au lanceur de sort de discuter sommairement avec un élément (la flamme d'une bougie, une flaque, une lame, etc), la nature de cet élément dépends de la [clé] employée, les informations qui peuvent être transmise sont foncièrement simple comme l'élément en question n'a pas la vision du monde qu'on les hommes etc... Il est possible d'échanger (dire ou recevoir) jusqu'à [Magnitude] mots. Le domaine du savoir peux questionner tous les éléments mais la magnitude est divisée par deux. | I11: 📚 Savoir: Diroga aum (tout), 🔥 Feu: Dirogaar (feu), ❄️ Glace: Dirogais (glace), ⚡ Foudre: Dirogaor (source d'énergie), 🪨 Terre: Dirogaum (minéraux), 💧 Eau: Dirogayn (eau), 🌪️ Air: Dirogael (vents, donc pas juste l'air), ☀️ Lumière: Dirogaion (source de lumière), 🌑 Ombre: Dirogaoth (source d'ombre), ⚖️ Loi: Dirogaem (objet au comportement cyclique), 🌀 Chaos: Dirogaix (objet au comportement aléatoire), ❤️ Vie: Dirogair (humanoïde, même incapable de parler), ☢️ Toxique: Dirogaex (élément toxique), ☠️ Mort: Dirogaus (cadavres), ⚔️ Acier: Dirogaan (métal), 🌿 Flore: Dirogailn (arbres), ✡️ Arcane: Dirogays (enchantements et objets magiques), ✨ Sacre: Dirogaiel (choses sacrés), 🩸 Impie: Dirogaun (choses impies, sang), 🐗 Faune: Dirogaorh (animaux), 🔮 Magie: Dirogairn (enchantements et monstres) | J11: =CONCAT(CONCAT(C11, " "),$A$1)
A12: Lux (Lumière) | B12: Dorlux (Dor + lux) | C12: Élucidation | D12: Pouvoir | E12: Cible | F12: 2 | G12: 2 | H12: Génère un effet permettant au lanceur de sort de connaitre la solution à un problème (une piste de résolution pour un problème donné) avec des détails dépendants d'un potenciel fixé par la [Magnitude], tout d'abord le lanceur de sort définit la nature (0 : seulement les éléments connus uniquement, 5 : parmi des éléments connus indirectement, 10 : même parmi des éléments inconnus) et la précision (0 : sybillin, 5 : imprécis, 10 : précis) de la solution qu'il recherche, ce qui réduit le potenciel selon le choix, puis le nombre de mots maximum est de 5 par points de potenciel restant | I12: 📚 Savoir: Dorluxaum | J12: =CONCAT(CONCAT(C12, " "),$A$1)
A13: Trudo (Pousser) | B13: Deltrud (Del + trud) | C13: Intrusion | D13: Pouvoir | E13: Cible | F13: 2 | G13: 2 | H13: Génère un enchantement qui permet à la cible de voir les pensés des autres en temps réelles (émotion, réelles intentions, etc) | I13: 👁️ Vision: Deltrudeth | J13: =CONCAT(CONCAT(C13, " "),$A$1)
A14: Locus (Lieu) | B14: Darlocus (Dar + locus) | C14: Localisation | D14: Pouvoir | E14: Cible | F14: 4 | G14: 0 | H14: Génère un effet permettant à la cible de connaitre la direction et la distance de son objectif (définit au lancement du sort), si l'objectif est à une distance inférieure à [Magnitude] mètres alors la direction donnée par le sort est parfaite, c'est une ligne droite en somme, si l'objectif est à une distance inférieure à [Magnitude x 10] mètres alors la direction donnée par le sort est de l'ordre de 45°, puis pareil avec 100 et 90°, 1km et 180°, au delà de 10km le sort n'échoue pas mais ne donne pas d'indications sauf que l'objectif existe quelque part, au delà de 100km le sort n'échoue pas mais ne donne pas d'indications tout court | I14: 👁️ Vision: Darlocus eth | J14: =CONCAT(CONCAT(C14, " "),$A$1)
... A88: Revelo (Révéler) | B88: Direvel (Di + revel) | C88: Découverte | D88: Liaison | E88: Cible | F88: 2 | G88: 2 | H88: Génère un effet qui permet au lanceur de sort de savoir si la cible fait l'objet d'une marque, ce sort échoue si sa magnitude est inférieure à la moitié de la puissance de la marque, le sort réussie au delà mais n'indique pas qui est celui qui a marqué la cible, si le sort a une magnitude supérieure à la marque alors l'identité (ou du moins la signature magique du mage) devient visible, si le sort a une magnitude deux fois supérieure alors l'identité est révélée (en plus de la signature) | I88: 📚 Savoir | J88: =CONCAT(CONCAT(C88, " "),$A$1)

Sheet Alté
A1: ≈
A2: Latin | B2: Mot arcanique | C2: Mot vulguaire | D2: Type de Mot | E2: Type de Cible | F2: Difficulté | G2: Drain | H2: Description
A3: Sublimis (Élevé) | B3: Alsublim (Al + sublim) | C3: Sublimification | D3: Pouvoir | E3: Cible | F3: 2 | G3: 2 | H3: Produit un effet qui change l'état (gaz, liquide ou solide) de [Magnitude x 2] unités d'un élément qui dépends de la [clé] | I3: 🪨 Terre: Alsublimum, 💧 Eau: Alsublimyn, 🌪️ Air: Alsublimel | J3: =CONCAT(CONCAT(C3, " "),$A$1)
A4: Fructus (Fruit) | B4: Arfruct (Ar + fruct) | C4: Fructification | D4: Pouvoir | E4: Cible | F4: 2 | G4: 2 | H4: L'effet du sort provoque la pousse de fruits comestible pour [Magnitude/10] personnes, si le sort est lancé sur un arbre la pousse est de [Magnitude/5] à la place | I4: 🌿 Flore: Arfructiln | J4: =CONCAT(CONCAT(C4, " "),$A$1)
A5: Arbor (Arbre) | B5: Asarbor (As + arbor) | C5: Arborisation | D5: Pouvoir | E5: Cible | F5: 2 | G5: 2 | H5: L'effet du sort provoque la pousse de [Magnitude/5] arbres, divisé par 3 pour des arbustes, divisé par 10 pour des gros arbres | I5: 🌿 Flore: Asarboriln | J5: =CONCAT(CONCAT(C5, " "),$A$1)
A6: Findo (Fendre) | B6: Aenfind (Aen + find) | C6: Fendaison | D6: Pouvoir | E6: Cible | F6: 2 | G6: 2 | H6: L'effet du sort génère une crevasse sur un sol de terre ou de pierre, la largeur x longueur x profondeur doit être inférieure à [Magnitude], aucun de ces paramètres ne peux pas dépasser [Magnitude/4], si une créature se trouve là où la crevasse a lieu elle peux réaliser un test de réflexe, en cas de réussite critique elle échappe à la chute en se déplaçant vers le bord de son choix, en cas de réussite elle glisse sur le bord de la crevasse à mi hauteur, en cas d'échec elle se retrouve au fond de la crevasse, en cas d'échec critique elle se retrouve au fond de la crevasse et subit les dégats de chute (elle a le droit à son test d'acrobatie pour réduire les dégats de celle ci), une cible dans la crevasse doit réussir un test d'acrobatie (si parois étroites) ou escalade pour remonter (difficulté basé sur la difficulté des effets du sort, voir règle idoines), cet effet fonctionne sur les autres sols mais avec une magnitude divisée par 2 | I6: 🪨 Terre: Aenfindum | J6: =CONCAT(CONCAT(C6, " "),$A$1)
A7: Muto (Changer) | B7: Almutat (Al + mutat) | C7: Transmutation | D7: Pouvoir | E7: Cible | F7: 2 | G7: 2 | H7: L'effet du sort convertis jusqu'à [Magnitude/10] unités (définit par l'encombrement si on parle d'équipement) d'un type qui dépends de la [clé] vers une autre du même type (example : acier vers bronze), le niveau de qualité du minerai doit être le même ou inférieur, le résultat sera forcément du niveau de la matière initiale, si le prix des deux produits diffèrent alors il est obligatoire de compenser via la quantité (en somme le sort ne peux produire de la richesse) | I7: ⚔️ Acier: Almutatan (Métaux), 🐗 Faune: Almutatorh (Cuir), 🌿 Flore: Almutatiln (Bois), 🌿 Flore: Almutatiln (Tissu) | J7: =CONCAT(CONCAT(C7, " "),$A$1)
A8: Fero (Porter/Façonner) | B8: Arfero (Ar + fero) | C8: Reforgation | D8: Pouvoir | E8: Cible | F8: 2 | G8: 2 | H8: L'effet du sort change le type d'une arme jusqu'à [Magnitude/10] unités (définit par l'encombrement de l'équipement) pour un autre type (épée, hache, lance...), l'objet conserve donc sa qualité, ses améliorations etc | I8: ⚔️ Acier: Arfero an (Métaux), 🌿 Flore: Arferoiln (Bois) | J8: =CONCAT(CONCAT(C8, " "),$A$1)
A9: Condicio (Condition) | B9: Ascondi (As + condi) | C9: Conditionnement | D9: Pouvoir | E9: Cible | F9: 2 | G9: 2 | H9: Génère un effet qui force un changement de condition à la cible pour lui appliquer une condition positive (qui correspond à l'une des conditions associable à la [clé]) avec une charge de [Magnitude] | I9: Voir liste des conditions | J9: =CONCAT(CONCAT(C9, " "),$A$1)
A10: Fligo (Frapper) | B10: Aenfligo (Aen + fligo) | C10: Affliction | D10: Pouvoir | E10: Cible | F10: 2 | G10: 2 | H10: Génère un effet qui force un changement de condition à la cible pour lui appliquer une condition négative (qui correspond à l'une des conditions associable à la [clé]) avec une charge de [Magnitude], la cible peux réaliser un test de sauvegarde contre la condition en question (ou opposition si supérieure) | I10: Voir liste des conditions | J10: =CONCAT(CONCAT(C10, " "),$A$1)
A11: Toxum (Poison, grec) | B11: Altox (Al + tox) | C11: Intoxication | D11: Pouvoir | E11: Cible | F11: 2 | G11: 2 | H11: Génère un effet qui force un changement de condition à la cible pour lui appliquer une condition négative, nécessairement temporaire (une décharge par jour) de type venin avec une charge de [Magnitude], la cible peux réaliser un test de sauvegarde contre la condition en question (ou opposition si supérieure) | I11: ☢️ Toxique: Altoxex | J11: =CONCAT(CONCAT(C11, " "),$A$1)
A12: Inficio (Souiller) | B12: Arinfic (Ar + infic) | C12: Infection | D12: Pouvoir | E12: Cible | F12: 2 | G12: 2 | H12: Génère un effet qui force un changement de condition à la cible pour lui appliquer une condition négative, nécessairement temporaire (une décharge par jour) de type maladie grave avec une charge de [Magnitude], la cible peux réaliser un test de sauvegarde contre la condition en question (ou opposition si supérieure) | I12: ☠️ Mort: Arinficus | J12: =CONCAT(CONCAT(C12, " "),$A$1)
A13: Verto (Tourner) | B13: Asvert (As + vert) | C13: Conversion | D13: Pouvoir | E13: Cible | F13: 2 | G13: 2 | H13: Génère un effet qui convertis un maximum de [Magnitude/2] charge d'une condition négative au choix en charge de la condition positive opposée avec le double des charges ainsi converties, variante : Ce mot peux affecter toutes les conditions de la cible avec une difficulté augmentée de 4 | I13: ⚖️ Loi: Asvertem | J13: =CONCAT(CONCAT(C13, " "),$A$1)
A14: Rumpo (Briser) | B14: Aenrump (Aen + rump) | C14: Corruption | D14: Pouvoir | E14: Cible | F14: 2 | G14: 2 | H14: Génère un effet qui convertis un maximum de [Magnitude/2] charge d'une condition positive au choix en charge de la condition négative opposée avec le double des charges ainsi converties, la cible peux réaliser un test de sauvegarde appropriée pour ce type de condition (ou opposition si supérieure), variante : Ce mot peux affecter toutes les conditions de la cible avec une difficulté augmentée de 4 | I14: 🌀 Chaos: Aenrumpix | J14: =CONCAT(CONCAT(C14, " "),$A$1)
... A51: Vita (Vie) | B51: Arvita (Ar + vita) | C51: Revitalisation | D51: Pouvoir | E51: Cible | F51: 2 | G51: 2 | H51: L'effet du sort provoque la pousse de [Magnitude/5] petit(s) fruit, si le sort est lancé sur un arbre la pousse est de [Magnitude/3] à la place, ces fruits ne rassasis pas mais restaure 1D6 PE sur-le-champs lorsque consommés, plusieurs fruits peuvent être consommés à la fois évidemment, ces fruits ne font plus effet au bout d'un cycle entier (soit 24h) | I51: 🌿 Flore: Arvitailn | J51: =CONCAT(CONCAT(C51, " "),$A$1)
A52: Densus (Dense) | B52: Aendenso (Aen + denso) | C52: Condensation | I52: Aendensex | J52: =CONCAT(CONCAT(C52, " "),$A$1)
A53: Meteoros (Céleste, grec) | B53: Almeteo (Al + meteo) | C53: Météorisation | H53: Cet enchantement permet de modifier le climat environnant en adéquation avec la clé associée. La magnitude du changement dépend du niveau du sort. | I53: 🔥 Feu: Almeteoar, ❄️ Glace: Almeteo is, ⚡ Foudre: Almeteo or, 💧 Eau: Almeteoyn, 🌪️ Air: Almeteoel, ☀️ Lumière: Almeteoion, 🌑 Ombre: Almeteooth | J53: =CONCAT(CONCAT(C53, " "),$A$1)
A54: Fissura (Fissure) | B54: Arfissu (Ar + fissu) | C54: Fissuration | H54: Génère une fissure dans le sol dont la largeur, profondeur et hauteur dépend des choix du personnage (comme un mur mais vers le bas en gros). | I54: 🪨 Terre: Arfissuum | J54: =CONCAT(CONCAT(C54, " "),$A$1)
A55: Lapsus (Chute) | B55: Aslapsus (As + lapsus) | C55: Éboulement | H55: Fait tomber des roches sur la cible, il doit donc y avoir de la roche à faire tomber au dessus, dégats de chute + ? | I55: 🪨 Terre: Aslapsusum | J55: =CONCAT(CONCAT(C55, " "),$A$1)
A56: Foro (Percer) | B56: Aenforo (Aen + foro) | C56: Forage | H56: Génère de l’huile inflammable ? (forage) | I56: 🪨 Terre: Aenforoum | J56: =CONCAT(CONCAT(C56, " "),$A$1)
A57: Purgo (Nettoyer) | B57: Alpurgo (Al + purgo) | C57: Purification | H57: * Purifie de l'eau | I57: 💧 Eau: Alpurgo yn | J57: =CONCAT(CONCAT(C57, " "),$A$1)
A58: Mundo (Nettoyer) | B58: Armundo (Ar + mundo) | C58: Épuration | H58: * Dissiper les gazs et airs dans un espace donnéµ : note y a un truc genre épurer une matière ? eau, air ou Terre | I58: 🌪️ Air: Armundoel | J58: =CONCAT(CONCAT(C58, " "),$A$1)
A59: Lapis (Pierre) | B59: Aslapi (As + lapi) | C59: Pétréification | H59: * Forme solide | I59: 🪨 Terre: Aslapium | J59: =CONCAT(CONCAT(C59, " "),$A$1)
A60: Aqua (Eau) | B60: Aenaqua (Aen + aqua) | C60: Aquasification | H60: * Forme aquatique | I60: 💧 Eau: Aenaquayn | J60: =CONCAT(CONCAT(C60, " "),$A$1)
A61: Aeros (Air, grec) | B61: Alaero (Al + aero) | C61: Aérosification | H61: * Forme de gaz | I61: 🌪️ Air: Alaeroel | J61: =CONCAT(CONCAT(C61, " "),$A$1)
A62: Spiro (Souffler) | B62: Arspira (Ar + spira) | C62: Aspiration | H62: * Retire l'air d'une zone, règle de suffocation | I62: 🌪️ Air: Arspirael | J62: =CONCAT(CONCAT(C62, " "),$A$1)
A63: Iungo (Joindre) | B63: Asjungo (As + jungo) | C63: Dijonction | H63: ench (malé) qui provoque des problèmes techno | I63: ✡️ Arcane: Asjungoys | J63: =CONCAT(CONCAT(C63, " "),$A$1)
A64: Sera (Verrou) | B64: Aensera (Aen + sera) | C64: Verrouillage | H64: Verouillage/Dévérouillage | I64: ✡️ Arcane: Aenserays | J64: =CONCAT(CONCAT(C64, " "),$A$1)
... A78: Cogo (Assembler) | B78: Arcogo (Ar + cogo) | C78: Coagulation | H78: Coagluation => l'inverse, bloque la récup de pv pour x tour ? | I78: 🩸 Impie: Arcogoun | J78: =CONCAT(CONCAT(C78, " "),$A$1)
A79: Forma (Forme) | B79: Asformis (As + formis) | C79: Transformation | D79: Pouvoir | H79: enchantement positif qui change la cible en une autre créature | I79: Pas d'élémentaire trouvé | J79: =CONCAT(CONCAT(C79, " "),$A$1)
A80: Cutis (Peau) | B80: Aencutis (Aen + cutis) | C80: Épidermisation | H80: enchantement positif qui change la peau de la cible sous une forme qui dépends du domaine | I80: Pas d'élémentaire trouvé | J80: =CONCAT(CONCAT(C80, " "),$A$1)
A81: Manus (Main) | B81: Almanu (Al + manu) | C81: Manipulation | H81: enchantement positif qui change les mains de la cible sous une forme qui dépends du domaine | I81: Pas d'élémentaire trouvé | J81: =CONCAT(CONCAT(C81, " "),$A$1)
A82: Trans (À travers) | B82: Artrans (Ar + trans) | C82: Transmogrification | H82: enchantement négatif qui change la cible en une créature plus faible | I82: Pas d'élémentaire trouvé | J82: =CONCAT(CONCAT(C82, " "),$A$1)
A83: Lito (Assouplir) | B83: Aslito (As + lito) | C83: Sublimation | H83: enchantement qui ajoute une propriété à l'air selon le domaine (poison = gaz) | I83: Pas d'élémentaire trouvé | J83: =CONCAT(CONCAT(C83, " "),$A$1)
A84: Vapor (Vapeur) | B84: Aenvapo (Aen + vapo) | C84: Vaporisation | H84: forme gazeuse | I84: 🌪️ Air: Aenvapoel | J84: =CONCAT(CONCAT(C84, " "),$A$1)
A85: Liquor (Liquide) | B85: Alliqui (Al + liqui) | C85: Liquéfaction | H85: forme aqueuse | I85: 💧 Eau: Alliquiyn | J85: =CONCAT(CONCAT(C85, " "),$A$1)
A86: Miner (Mine) | B86: Arminer (Ar + miner) | C86: Minéralisation | H86: forme solide | I86: 🪨 Terre: Arminereum | J86: =CONCAT(CONCAT(C86, " "),$A$1)
A87: Calor (Chaleur) | B87: Ascalo (As + calo) | C87: Thermisation | H87: Conditions: Chaud, froid, magnétisé ? | I87: 🔥 Feu: Ascaloar, ❄️ Glace: Ascalois, ⚡ Foudre: Ascaloor | J87: =CONCAT(CONCAT(C87, " "),$A$1)
A88: Bestia (Bête) | B88: Aenbestia (Aen + bestia) | C88: Bestialisation | H88: Prend la forme d'une bête (Rang de la bête = SPow / 7 ?) (pas de guérison si quitte la forme en question) | I88: 🐗 Faune: Aenbestiaorh | J88: =CONCAT(CONCAT(C88, " "),$A$1)
A89: Elementum (Élément) | B89: Alele (Al + ele) | C89: Élémentalisation | H89: Prend la forme d'un élémentaire (Rang de la bête = SPow / 7 ?) (pas de guérison si quitte la forme en question) | I89: 🔥 Feu: Alelear, ❄️ Glace: Aleleis, ⚡ Foudre: Aleleor, 🪨 Terre: Aleleum, 💧 Eau: Aleleyn, 🌪️ Air: Aleleel, ☢️ Toxique: Aleleex, 🌿 Flore: Aleleiln, ✨ Sacre: Aleleiel, 🩸 Impie: Aleleun, ☀️ Lumière: Aleleion, 🌑 Ombre: Aleleoth | J89: =CONCAT(CONCAT(C89, " "),$A$1)
A90: Forma (Forme) | B90: Asforma (As + forma) | C90: Formisation | H90: Forme (élémentaire ou matière) | I90: 🔥 Feu: Asformaar, ❄️ Glace: Asformais, ⚡ Foudre: Asformaor, 🪨 Terre: Asformaum, 💧 Eau: Asformayn, 🌪️ Air: Asformael, 🌿 Flore: Asformailn, ✨ Sacre: Asformaiel, 🩸 Impie: Asformaun, ☀️ Lumière: Asformaion, 🌑 Ombre: Asformaoth | J90: =CONCAT(CONCAT(C90, " "),$A$1)
A91: Pellis (Peau) | B91: Aenpelli (Aen + pelli) | C91: Épidermisation | H91: Peau (élémentaire ou matière) | I91: 🔥 Feu: Aenpelli ar, ❄️ Glace: Aenpelliis, ⚡ Foudre: Aenpellior, 🪨 Terre: Aenpellium, 💧 Eau: Aenpelliyn, 🌪️ Air: Aenpelliel, 🌿 Flore: Aenpe lliiln, ✨ Sacre: Aenpelliiel, 🩸 Impie: Aenpelliun, ☀️ Lumière: Aenpelliion, 🌑 Ombre: Aenpellioth | J91: =CONCAT(CONCAT(C91, " "),$A$1)
A92: Manu (Main) + Forma (Forme) | B92: Almanf (Al + manf) | C92: Manuformation | H92: Mains (élémentaire ou matière) | I92: 🔥 Feu: Almanfar, ❄️ Glace: Almanfis, ⚡ Foudre: Almanfor, 🪨 Terre: Almanfum, 💧 Eau: Almanfyn, 🌪️ Air: Almanfel, 🌿 Flore: Almanfiln, ✨ Sacre: Almanfiel, 🩸 Impie: Almanfun, ☀️ Lumière: Almanfion, 🌑 Ombre: Almanfoth | J92: =CONCAT(CONCAT(C92, " "),$A$1)

Sheet Conj
A1: ⧗
A2: Latin | B2: Mot arcanique | C2: Mot vulguaire | D2: Type de Mot | E2: Type de Cible | F2: Difficulté | G2: Drain | H2: Description
A3: Volatus (Vol) | B3: Convol (Con + vol) | C3: Vol | D3: Pouvoir | E3: Cible | F3: 2 | G3: 2 | H3: Génère un enchantement qui permet à la cible de voler, elle le fait avec une allure de [Magnitude/4] ou améliorée de [Magnitude/5] | I3: 🌪️ Air: Convolel | J3: =CONCAT(CONCAT(C3, " "),$A$1)
A4: Plaudo (Applaudir, battre des ailes) | B4: Cemplaud (Cen + plaud) | C4: Planement | D4: Pouvoir | E4: Cible | F4: 2 | G4: 2 | H4: Génère un enchantement qui permet à la cible de planer, elle le fait avec une allure de [Magnitude/3] ou améliorée de [Magnitude/5] | I4: 🌪️ Air: Cemplaudel | J4: =CONCAT(CONCAT(C4, " "),$A$1)
A5: Aqua (Eau) | B5: Colaqua (Col + aqua) | C5: Marcheflots | D5: Pouvoir | E5: Cible | F5: 2 | G5: 2 | H5: Génère un enchantement qui permet à la cible marcher sur l'eau, elle le fait avec une allure de [Magnitude/3] ou améliorée de [Magnitude/5] | I5: 💧 Eau: Colaquayn | J5: =CONCAT(CONCAT(C5, " "),$A$1)
A6: Nato (Nager) | B6: Carnato (Car + nato) | C6: Nage | D6: Pouvoir | E6: Cible | F6: 2 | G6: 2 | H6: Génère un enchantement qui permet à la cible de nager, elle le fait avec une allure de [Magnitude/4] ou améliorée de [Magnitude/5] | I6: 💧 Eau: Carnatoyn | J6: =CONCAT(CONCAT(C6, " "),$A$1)
A7: Ascendo (Monter) | B7: Conasc (Con + asc) | C7: Ascension | D7: Pouvoir | E7: Cible | F7: 2 | G7: 2 | H7: Génère un enchantement qui permet à la cible de grimper, elle le fait avec une allure de [Magnitude/3] ou améliorée de [Magnitude/5] | I7: 🪨 Terre: Conascum | J7: =CONCAT(CONCAT(C7, " "),$A$1)
A8: Terra (Terre) | B8: Centerra (Cen + terra) | C8: Terremarche | D8: Pouvoir | E8: Cible | F8: 2 | G8: 2 | H8: Génère un enchantement qui permet à la cible de marcher sur le sol, elle le fait avec une allure de [Magnitude/3] | I8: 🪨 Terre: Centerraum | J8: =CONCAT(CONCAT(C8, " "),$A$1)
A9: Traho (Tirer) | B9: Coltraho (Col + traho) | C9: Attraction | D9: Pouvoir | E9: Cible | F9: 2 | G9: 2 | H9: Génère un enchantement d'attraction agissant chaque tour comme l'action tactique de déplacement forcé avec un jet de [Magnitude/2] et attirant en son centre toutes les cibles dans la zone d'effet, de fait le sort doit inclure une zone d'effet | I9: 💢 Vide: Coltrahoarh | J9: =CONCAT(CONCAT(C9, " "),$A$1)
A10: Pello (Pousser) | B10: Carpello (Car + pello) | C10: Répulsion | D10: Pouvoir | E10: Cible | F10: 2 | G10: 2 | H10: Génère un enchantement répulsif agissant comme l'action tactique de déplacement forcé avec un jet de [Magnitude/2] et repoussant de son centre toutes les cibles dans la zone d'effet, de fait le sort doit inclure une zone d'effet | I10: 🌪️ Air: Carpelloel | J10: =CONCAT(CONCAT(C10, " "),$A$1)
A11: Aedifico (Édifier) | B11: Conedi (Con + edi) | C11: Edification | D11: Pouvoir | E11: Cible | F11: 2 | G11: 2 | H11: Génère un enchantement sous la forme d'un mur tangible ou intangible (selon la clé), la [Magnitude] permet d'en mesurer la distance et/ou l'intensité, voir la règle des murs magiques, de la [clé] dépends les effets associé au mur | I11: 🔥 Feu: Conediar, ❄️ Glace: Conediis, ⚡ Foudre: Conedior, 🪨 Terre: Conedium, 💧 Eau: Conediyn, 🌪️ Air: Conediel, ☀️ Lumière: Conediion, 🌑 Ombre: Conedioth, ⚖️ Loi: Conediem, 🌀 Chaos: Conediix, ✨ Sacre: Conediiel, 🩸 Impie: Conediun, ❤️ Vie: Conediir, ☠️ Mort: Conedius, 🌿 Flore: Conediiln, ✡️ Arcane: Conediys, 🎭 Illusion: Conediin, ⚔️ Acier: Conedian, 💢 Vide: Conediarh | J11: =CONCAT(CONCAT(C11, " "),$A$1)
A12: Vestis (Vêtement) | B12: Cenvest (Cen + vest) | C12: Revêtement | D12: Pouvoir | E12: Cible | F12: 2 | G12: 2 | H12: Génère un enchantement sous la forme d'un revêtement au sol tangible ou intangible (selon la clé), la [Magnitude] permet d'en mesurer la distance et/ou l'intensité, voir la règle des sols magiques, de la [clé] dépends les effets associé au sol | I12: 🔥 Feu: Cenvestar, ❄️ Glace: Cenvestis, ⚡ Foudre: Cenvestor, 🪨 Terre: Cenvestum, 💧 Eau: Cenvestyn, 🌪️ Air: Cenvestel, ☀️ Lumière: Cenvestion, 🌑 Ombre: Cenvestoth, ⚖️ Loi: Cenvestem, 🌀 Chaos: Cenvestix, ✨ Sacre: Cenvestiiel, 🩸 Impie: Cenvestun, ❤️ Vie: Cenvestir, ☠️ Mort: Cenvestus, 🌿 Flore: Cenvestiln, ✡️ Arcane: Cenvestys, 🎭 Illusion: Cenvestin, 🛡️ Guerre: Cenvestorr | J12: =CONCAT(CONCAT(C12, " "),$A$1)
A13: Ferrum (Fer) | B13: Colfer (Col + fer) | C13: Fers | D13: Pouvoir | E13: Cible | F13: 2 | G13: 2 | H13: Génère un enchantement (sous formes de chaines tangibles ou intangibles) qui emprisonne un membre de la cible, la [Magnitude] permet d'en mesurer l'intégrité, si intangible la difficulté pour se soustraire à l'effet est augmenté de 5, la cible peux réduire/endommager les charges de l'enchantement comme il le ferait avec une structure (catégorie 0 si intangible sinon 5), il peux aussi réaliser une évaluation (diff 10) de musculation ou évasion (on considère que le jet endommage l'enchantement) | I13: ☠️ Mort: Colferus, ⚔️ Acier: Colferan, 🌿 Flore: Colferiln, ✡️ Arcane: Colferys, ☀️ Lumière: Colferion, 🌑 Ombre: Colferoth, ⚖️ Loi: Colferem, 🌀 Chaos: Colferix, ✨ Sacre: Colferiiel, 🩸 Impie: Colferun | J13: =CONCAT(CONCAT(C13, " "),$A$1)
A14: Carcer (Prison) | B14: Carcarce (Car + carce) | C14: Incarcération | D14: Pouvoir | E14: Cible | F14: 4 | G14: 4 | H14: Génère un enchantement (sous formes de cage tangibles ou intangibles) qui emprisonne entièrement la cible, fonctionne comme les fers mais prive de déplacement et réduire drastiquement les actions possibles (la cage étant serrée, l'usage de la plupart des armes est impossible, sauf armes légères) | I14: ☠️ Mort: Carcarceus, ⚔️ Acier: Carcarcean, 🌿 Flore: Carcarceiln, ✡️ Arcane: Carcarceys, ☀️ Lumière: Carcarceion, 🌑 Ombre: Carcarceoth, ⚖️ Loi: Carcarceem, 🌀 Chaos: Carcarceix, ✨ Sacre: Carcarceiel, 🩸 Impie: Carcarceun | J14: =CONCAT(CONCAT(C14, " "),$A$1)
... A45: Scutum (Bouclier) | B45: Censcutu (Cen + scutu) | C45: Couronne de boucliers | D45: Pouvoir | E45: Cible | F45: 2 | G45: 2 | H45: Génère un enchantement qui prend la forme de [Magnitude/5] boucliers autour du lanceur de sort, lorsque la cible le souhaite elle peux dépenser une action libre pour se défendre avec l'un de ces boucliers, il est possible de défendre (d'une agression dont la nature dépends de la [clé] employée) un allié adjacent de cette manière, la cible utilise alors sa compétence de magie et son attribut de magie pour le test en question, le jet associé est alors fixé à [Magnitude/3], une fois le bouclier utilisé ce dernier disparait jusqu'à ce que la cible utilise une action simple pour recharger le tout, si le personnage le souhaite il peux utiliser une action simple ou rapide à la place de libre et l'action sera avantagée | I45: ⚔️ Acier: Censcutuan (Physique), 🧩 Mental: Censcutuend (Mental), 🪷 Nature: Censcutu eiln (Magie) | J45: =CONCAT(CONCAT(C45, " "),$A$1)
A46: Fulgur (Foudre) | B46: Colfulgur (Col + fulgur) | C46: Appel de la foudre | D46: Pouvoir | E46: Cible | F46: 2 | G46: c | H46: Génère un enchantement de lieu qui charge les nuages au dessus (que l'origine soit magique ou pas, limité à la zone d'effet de l'enchantement le cas échéant), lorsque le lanceur de sort le souhaite il peux dépenser une action simple pour provoquer la foudre qui frappe la cible de son choix dans la zone, le lanceur de sort utilise sa compétence de magie et son attribut de magie pour le test en question, les dégats sont de [Magnitude] et font l'objet d'un test de sauvegarde (vs Réflexes), à chaque frappes l'enchantement subit une décharge, évidemment les conditions de fonctionnement de ce sort implique des éléments qu'il appartient au MJ de considérer | I46: ⚡ Foudre: Colfulguror | J46: =CONCAT(CONCAT(C46, " "),$A$1)
A47: Muto (Changer) | B47: Carmuta (Car + muta) | C47: Transmutation | D47: Pouvoir | E47: Cible | F47: 2 | G47: 2 | H47: Génère un enchantement qui prend la forme de membres ou d'une particularité physiologique issus d'un animal au choix, ce gain entraine l'amélioration d'une compétence qui dépends logiquement du membre (examples : nagoire de requin pour natation, peau de croco pour armure, griffe d'ours pour attaquer, etc), dans le cas où la logique pourrait entrainer l'amélioration de plusieurs compétences une seule est affectée (au choix du lanceur de sort), l'utilisation de la compétence se fait alors avec un bonus de [Magnitude/7] ou avec un minimum (Groupe+Compétence) de [Magnitude/5] | I47: 🐗 Faune: Carmutaorh | J47: =CONCAT(CONCAT(C47, " "),$A$1)
A48: Locus (Lieu) + Muto (Changer) | B48: Conloco (Con + loco) | C48: Locomutation | D48: Pouvoir | E48: Cible | F48: 2 | G48: 2 | H48: Génère un enchantement qui prend la forme de membres ou d'une particularité physiologique issus d'un animal au choix, ce gain entraine la possibilité de se déplacer différement: Voler, Marcher sur les parois, Marcher sur des surfaces qui ne permettent pas ou qui réduisent l'aLure, Nager... Le déplacement en question se fait avec une allure de [Magnitude/3] (remplace l'allure normale) | I48: 🐗 Faune: Conlocoorh | J48: =CONCAT(CONCAT(C48, " "),$A$1)
A49: Mimicus (Mime) | B49: Cenmimic (Cen + mimic) | C49: Mimétisation | D49: Pouvoir | E49: Cible | F49: 2 | G49: 2 | H49: Génère un enchantement donne à sa cible les traits (visuel, sonore, odeurs) d'une autre personne, si ces traits sont ceux d'une personne connu du lanceur de sort alors seuls les détails que ce dernier connait vraiment sont parfaits (le reste révèle la nature fausse de la chose à quiquonque connait celui ci chez la personne d'origine), ces effets sont sujets aux règles inhérentes aux Illusions | I49: 🎭 Illusion: Cenmimicin | J49: =CONCAT(CONCAT(C49, " "),$A$1)
A50: Spatium (Espace) | B50: Colspati (Col + spati) | C50: Espace de poche | D50: Pouvoir | E50: Lieu | F50: 2 | G50: 2 | H50: Génère un effet qui ouvre une porte afin de stocker ou récupérer dans l'espace interdimentionnel personel (chaque personne en dispose d'un unique) un ou des objets, la totalité des objets pouvant être stocké et sortis est limité à un encombrement total de [Magnitude/2], les objets sont catalogués juqu'à ou récupérés depuis l'index de référencement maximum [Magnitude/2], par exemple un objet d'encombrement 3 peux occuper l'espace de 16 à 18, il faudra alors une magnitude de 36 pour le récupérer ensuite | I50: ✡️ Arcane: Colspatiys | J50: =CONCAT(CONCAT(C50, " "),$A$1)
A51: Onero (Charger) | B51: Carnero (Car + nero) | C51: Surcharge | D51: Pouvoir | E51: Lieu | F51: 2 | G51: 2 | H51: Génère un enchantement de lieu qui augmente le drain des sorts lancés dans la zone de [Magnitude/4], la sauvegarde de détermination permettant de réduire cet effet | I51: 🪷 Nature: Carneroeiln | J51: =CONCAT(CONCAT(C51, " "),$A$1)
A52: Sanguis (Sang) | B52: Consang (Con + sang) | C52: Saignée arcanique | D52: Pouvoir | E52: Lieu | F52: 2 | G52: 2 | H52: Génère un enchantement de lieu qui inflige aux lanceurs de sort l'équivalant du drain des sorts en attrition (perte de PE) dans la zone, la perte étant limité à [Magnitude/2], la sauvegarde de détermination permettant de réduire cet effet | I52: 🪷 Nature: Consangeiln | J52: =CONCAT(CONCAT(C52, " "),$A$1)
A53: Turbo (Troubler) | B53: Centurb (Cen + turb) | C53: Perturbation | D53: Pouvoir | E53: Lieu | F53: 2 | G53: 2 | H53: Génère un enchantement de lieu qui augmente la difficulté de sorts lancés dans la zone de [Magnitude/5], la sauvegarde de détermination permettant de réduire cet effet | I53: 🪷 Nature: Centurbeiln | J53: =CONCAT(CONCAT(C53, " "),$A$1)
A54: Harmonia (Harmonie) | B54: Colharmo (Col + harmo) | C54: Harmonisation | D54: Pouvoir | E54: Lieu | F54: 2 | G54: 2 | H54: Génère un enchantement de lieu qui réduit la difficulté de sorts lancés dans la zone de [Magnitude/5] | I54: 🔮 Magie: Colharmoirn | J54: =CONCAT(CONCAT(C54, " "),$A$1)
A55: Leves (Léger) | B55: Carleves (Car + leves) | C55: Allégement | D55: Pouvoir | E55: Lieu | F55: 2 | G55: 2 | H55: Génère un enchantement de lieu qui réduit le drain des sorts lancés dans la zone de [Magnitude/4], ce qui n'affecte pas le cout minimum des sorts | I55: 🔮 Magie: Carlevesirn | J55: =CONCAT(CONCAT(C55, " "),$A$1)
A56: Astra (Étoile) | B56: Conastra (Con + astra) | C56: Fenêtre astrale | D56: Pouvoir | E56: Lieu | F56: 2 | G56: 2 | H56: Génère un enchantement de lieu qui prend la forme d'une fenêtre vers un autre lieu, on ne peux y passer mais il est possible d'épier à travers, un test d'intuition réussis permet à ceux qui sont épiés de se sentir observés puis un test d'acuité peux permettre de repérer la fenêtre (ou en tout cas d'où viens la sensation), le lieu ainsi épié peux être à une distance maximale de [Magnitude]² mètres | I56: 👁️ Vision: Conastra eth | J56: =CONCAT(CONCAT(C56, " "),$A$1)
A57: Celo (Cacher) | B57: Cencelo (Cen + celo) | C57: Invisibilité | D57: Pouvoir | E57: Cible | F57: 2 | G57: 4 | H57: Génère un enchantement sur cible qui tord la lumière et rend le sujet invisible, un test d'intuition réussis permet de savoir que quelque chose ne va pas et un test d'acuité permet de voir la cible malgrés tout, ce sort ne peux être lancé à un niveau inférieur à 2, toute action d'agression met un terme à l'enchantement | I57: 🎭 Illusion: Cenceloin | J57: =CONCAT(CONCAT(C57, " "),$A$1)
A58: Silentium (Silence) | B58: Colsil (Col + sil) | C58: Silence | D58: Pouvoir | E58: Cible | F58: 2 | G58: 4 | H58: Génère un enchantement sur cible qui étouffe le son et rend le sujet difficile à entendre, un test d'intuition réussis permet de savoir que quelque chose ne va pas et un test d'acuité permet de voir la cible malgrés tout, ce sort ne peux être lancé à un niveau inférieur à 2, toute action d'agression met un terme à l'enchantement | I58: 🎭 Illusion: Colsilin | J58: =CONCAT(CONCAT(C58, " "),$A$1)
... A65: Arcus (Arche) | B65: Cenarch (Cen + arch) | C65: Arche | D65: Miracle | E65: Lieu | F65: 8 | G65: 8 | H65: Le sort génère un enchantement de type portail sur le lieu ciblé avec un potenciel de [Magnitude], le lanceur de sort répartie le potenciel entre X, Y et Z, le portail en question occupe 1 case et permet au lanceur de sort ou à n'importe qui d'autre de passer à travers afin d'atteindre un lieu déterminé lors du lancement de sort, connu de ce dernier (un test de mémoire peux être nécessaire si le lieu a été visité il y a quelques temps, le MJ détermine la difficulté selon ses critères) à une distance maximale de X fois 100m, si le lieu en question fait l'objet d'une marque magique alors la distance maximale est de X fois 5km à la place, ce portail permet de faire passer jusqu'à Y/5 individus et le retour est possible si Z vaux au moins 10 | I65: 💢 Vide: Cenarcharh | J65: =CONCAT(CONCAT(C65, " "),$A$1)
A66: Notifico (Notifier) | B66: Cennotif (Cen + notif) | C66: Notification | D66: Pouvoir | H66: enchantement qui signale au lanceur de sort un passage ou autre (alarme) | I66: 👁️ Vision: Cennotifeth | J66: =CONCAT(CONCAT(C66, " "),$A$1)
A67: Color (Couleur) | B67: Colcolo (Col + colo) | C67: Coloration | D67: Pouvoir | H67: L’enchantement (neutre) modifie la couleur d’un objet. Le niveau du sort permet de fixé le degré de variation de la couleur et surtout la taille de l’objet (charge maximale de l’objet = niveau du sort x 4). | I67: ☀️ Lumière: Colcoloion | J67: =CONCAT(CONCAT(C67, " "),$A$1)
A68: Video (Voir) | B68: Carvidi (Car + vidi) | C68: Visualisation | D68: Pouvoir | H68: Créé un enchantement statique qui iLumine les lieux et augmente pour tous la perception des 5e sens, octroyant un bonus de 1 + 1 par niveau à tous les tests de perception en vu de percevoir quelque chose ou quelqu'un dans le même lieu | I68: ☀️ Lumière: Carvidiion | J68: =CONCAT(CONCAT(C68, " "),$A$1)
A69: Velum (Voile) | B69: Convelo (Con + velo) | C69: Révélation | D69: Pouvoir | H69: Met un terme aux Illusions ou déguisement, révèle à tous la vraie nature de la cible, si l’origine de cette désinformation est magique alors le sort doit battre la difficulté associée | I69: ☀️ Lumière: Conveloion | J69: =CONCAT(CONCAT(C69, " "),$A$1)
A70: Tenebrae (Ténèbres) | B70: Centeneb (Cen + teneb) | C70: Obscurisation | D70: Pouvoir | H70: Créé un enchantement statique qui plonge dans l'obscurité les lieux et réduit pour toutes la perception des 5e sens, octroyant un malus de 1 + 1 par niveau à tous les tests de perception en vu de percevoir quelque chose ou quelqu'un dans le même lieu | I70: 🌑 Ombre: Centeneboth | J70: =CONCAT(CONCAT(C70, " "),$A$1)
A71: Color (Couleur) | B71: Coldecol (Col + decol) | C71: Décoloration | D71: Pouvoir | H71: Créer un enchantement (neutre) qui altère la couleur d’un objet en le privant de couleur. La taille maximum de l’objet dépends du niveau du sort (le poids de l’objet doit être inférieur ou égal au niveau du sort) | I71: 🌑 Ombre: Coldecoloth | J71: =CONCAT(CONCAT(C71, " "),$A$1)
A72: Unda (Onde) | B72: Carund (Car + und) | C72: Inondation | D72: Pouvoir | H72: Conjuration qui génère une couche d’eau dans des locaux | I72: 💧 Eau: Carundyn | J72: =CONCAT(CONCAT(C72, " "),$A$1)
A73: Bruma (Brume) | B73: Conbruma (Con + bruma) | C73: Brumisation | D73: Pouvoir | H73: * Lève un brouillard qui réduit la visibilité | I73: 💧 Eau: Conbrumayn | J73: =CONCAT(CONCAT(C73, " "),$A$1)
A74: Fauces (Gorge) | B74: Cenfauce (Cen + fauce) | C74: Suffocation | D74: Pouvoir | H74: Conjure une bulle d’eau sur la tête de la cible l’obligeant à retenir sa respiration puis à se noyer si rien n’est fait | I74: 🌪️ Air: Cenfauceel | J74: =CONCAT(CONCAT(C74, " "),$A$1)
A75: Oculus (Œil) | B75: Colocul (Col + ocul) | C75: Œil du cyclone | D75: Pouvoir | H75: - [Magie] Oeil du Cyclone : Le personnage deviens l'oeil d'un cyclone qui emporte tout autour de lui. les objets percutent ceux qui ne réussissent/ne font pas un tst d'agilité. | I75: 🌪️ Air: Coloculel | J75: =CONCAT(CONCAT(C75, " "),$A$1)
A76: Spirare (Souffler) | B76: Carspire (Car + spire) | C76: Respiration | D76: Pouvoir | H76: Permet de ne pas avoir besoin de respirer (positif) | I76: 🌪️ Air: Carspirel | J76: =CONCAT(CONCAT(C76, " "),$A$1)
A77: Leves (Léger) | B77: Conlev (Con + lev) | C77: Lévitation | D77: Pouvoir | H77: enchantement qui permet de marcher à quelques pas du sol, comme un coussin d’air (hauteur max selon niveau) | I77: 🌪️ Air: Conlevel | J77: =CONCAT(CONCAT(C77, " "),$A$1)
... A102: Dolor (Douleur) | B102: Cardolor (Car + dolor) | C102: Chaîne de souffrance | D102: Pouvoir | H102: Chaine de souffrance : la cible subit une partie des dégats qu'elle inflige sous forme de degatd physiques | I102: 🩸 Impie: Cardolorun | J102: =CONCAT(CONCAT(C102, " "),$A$1)
A103: Forum (Place publique) | B103: Conforum (Con + forum) | C103: Agora | D103: Pouvoir | G103: -4 | H103: conjure un espace d'échange (table de stratégie, tableau d'enseignement, etc) qui octroie un bonus de qualité , comme le ferait un outils adapté, à un test de compétence visant trés justement à échanger (idées, infos, stratégie) avec des alliés (bonus = magnetiude/3) | I103: Pas d'élémentaire trouvé | J103: =CONCAT(CONCAT(C103, " "),$A$1)
A104: Gradior (Marcher) | B104: Cengradi (Cen + gradi) | C104: Pas élémentaires | D104: Pouvoir | H104: Marcher = froid, feu ou électricité au sol (donc génère des sols comme le mot ci dessus) | I104: 🔥 Feu: Cengradiar, ❄️ Glace: Cengradiis, ⚡ Foudre: Cengradior | J104: =CONCAT(CONCAT(C104, " "),$A$1)
A105: Macaber (Macabre) | B105: Colmaca (Col + maca) | C105: Piège macabre | D105: Pouvoir | H105: Enchantement de lieu : Cadavres, déclanche un sort de destruction en approchant, façon piège ? | I105: ☠️ Mort: Colmacaus | J105: =CONCAT(CONCAT(C105, " "),$A$1)
A106: Testor (Témoigner) | B106: Cartesta (Car + testa) | C106: Testament explosif | D106: Pouvoir | H106: Enchantement de cible : Si elle décède alors déclanche un sort de destruction en zone, plus puissant que la norme x1,5 ? | I106: ☠️ Mort: Cartestaus | J106: =CONCAT(CONCAT(C106, " "),$A$1)
A107: Ardeo (Brûler) | B107: Conardeo (Con + ardeo) | C107: Ardeur arcanique | D107: Pouvoir | H107: Enchantement de cible : La cible peux dépenser du mana pour augmenter le jet de ses attaques | I107: ⚔️ Acier: Conardeoan | J107: =CONCAT(CONCAT(C107, " "),$A$1)
A108: Aegis (Égide) | B108: Cenaegis (Cen + aegis) | C108: Égide arcanique | D108: Pouvoir | H108: Enchantement de cible : La cible peux dépenser du mana pour augmenter le jet de ses défenses ? genre esquive | I108: ⚔️ Acier: Cenaegisan | J108: =CONCAT(CONCAT(C108, " "),$A$1)
A109: Ardor (Chaleur) | B109: Colardor (Col + ardor) | C109: Ardeur sanguine | D109: Pouvoir | H109: Enchantement de cible : Elle peux dépenser des PV pour gagner un bonus en attaque, tactique ou défense physique | I109: 🩸 Impie: Colardorun | J109: =CONCAT(CONCAT(C109, " "),$A$1)
A110: Ferveo (Bouillir) | B110: Carferv (Car + ferv) | C110: Ferveur psychique | D110: Pouvoir | H110: Enchantement de cible : Elle peux dépenser des PS pour gagner un bonus en attaque, tactique ou défense mentale | I110: 🧩 Mental: Carfervend | J110: =CONCAT(CONCAT(C110, " "),$A$1)
A111: Tutum (Sécurité) | B111: Contutu (Con + tutu) | C111: Totem gardien | D111: Pouvoir | H111: Un sort qui conjure une armure/totem qui, tant qu'elle est présente, protège un certain nombre de créature, elle peux être attaqué/détruite prématurément du coup | I111: Pas d'élémentaire trouvé | J111: =CONCAT(CONCAT(C111, " "),$A$1)
A112: Anima (Âme) | B112: Cenanima (Cen + anima) | C112: Animation | D112: Pouvoir | H112: Anime la matière, comme une invocation, mais en plus fort (vu qu'il y a le prérequis de la matière présente, qui ne doit pas être magique ou en quantité très notable ?), mais du coup ce n'est pas une invocation justement | I112: Pas d'élémentaire trouvé | J112: =CONCAT(CONCAT(C112, " "),$A$1)
A113: Replico (Remplir) | B113: Colreple (Col + reple) | C113: Recharge | D113: Pouvoir | E113: Cible | F113: 2 | G113: 2 | H113: Enchantement qui restaure les charges des autres enchantements sur la cible (sauf lui même) | I113: 🔮 Magie: Colrepleirn | J113: =CONCAT(CONCAT(C113, " "),$A$1)
A114: Siphos (Tube, grec) | B114: Carsipho (Car + sipho) | C114: Siphon | D114: Pouvoir | E114: Cible | F114: 2 | G114: 2 | H114: Enchantement qui draine les charges des autres enchantements sur la cible (sauf lui même) | I114: 🔮 Magie: Carsiphoirn | J114: =CONCAT(CONCAT(C114, " "),$A$1)
A115: Frigus (Froid) | B115: Confrig (Con + frig) | C115: Cryofracture | D115: Pouvoir | H115: Rend l'objet fragile dû au froid, à chaque usage il doit réaliser un test de solidité | I115: ❄️ Glace: Confrigis | J115: =CONCAT(CONCAT(C115, " "),$A$1)
A116: Gelus (Glace) | B116: Cengelus (Cen + gelus) | C116: Gelure | D116: Pouvoir | H116: Rend la cible fragile dû au froid, à chaque action elle doit réaliser un test sinon blessure | I116: ❄️ Glace: Cengelusis | J116: =CONCAT(CONCAT(C116, " "),$A$1)
A117: Parasitus (Parasite) | B117: Colparas (Col + paras) | C117: Parasitisme arcanique | D117: Pouvoir | H117: Enchantement qui permet d'utiliser la mana des adversaires à proximité comme mana temporaire | I117: 🔮 Magie: Colparasirn | J117: =CONCAT(CONCAT(C117, " "),$A$1)
A118: Lacus (Étang) | B118: Carlacu (Car + lacu) | C118: Flaque conjurée | D118: Pouvoir | H118: Génère une flaque (eau, poison, magma, sang ?) | I118: 💧 Eau: Carlacuyn, ☢️ Toxique: Carlacuex, 🔥 Feu: Carlacuar, 🩸 Impie: Carlacuun | J118: =CONCAT(CONCAT(C118, " "),$A$1)
A119: Rodo (Ronger) | B119: Conrodo (Con + rodo) | C119: Corrosion | D119: Pouvoir | H119: Corrosion vs structure : chaque tour dégradation ? | I119: ☢️ Toxique: Conrodoex | J119: =CONCAT(CONCAT(C119, " "),$A$1)
A120: Velum (Voile) | B120: Censelec (Cen + selec) | C120: Voile sélectif | D120: Pouvoir | H120: Dissimule aux regards de x ( undead, beast, demon, humans ? ) | I120: Pas d'élémentaire trouvé | J120: =CONCAT(CONCAT(C120, " "),$A$1)
A121: Entropia (Grec) | B121: Colentr (Col + entr) | C121: Entropisation | D121: Pouvoir | H121: Zone où les attributs sont réduits en % | I121: 💢 Vide: Colentrarh | J121: =CONCAT(CONCAT(C121, " "),$A$1)
A122: Haema (Sang) | B122: Conhaem (Con + haem) | C122: Hémophagie | D122: Pouvoir | H122: Buff qui capte la vie perdue par les ennemis pour en faire de l'endu/mana/vitalité ou mental temporaire | I122: 🩸 Impie: Conhaemun | J122: =CONCAT(CONCAT(C122, " "),$A$1)
A123: Anima (Âme) | B123: Cenmes (Cen + mes) | C123: Moisson d’âmes | D123: Pouvoir | H123: Buff qui redonne endu/mana/vitalité ou mental temporaire à la mort des cibles environnantes | I123: ☠️ Mort: Cenmesus | J123: =CONCAT(CONCAT(C123, " "),$A$1)
A124: Sarmentum (Sarment) | B124: Colsarme (Col + sarme) | C124: Sarments entraveurs | D124: Pouvoir | H124: - [Magie] Feuille qui s'enroule sur un ennemi qui est de fait ralentis/gêné (ou bien qui le stop sur place et le mec doit se débattre pour virer la contrainte, façon chaines etc) | I124: 🌿 Flore: Colsarmeniln | J124: =CONCAT(CONCAT(C124, " "),$A$1)
A125: Phantasma (Apparition) | B125: Carphant (Car + phant) | C125: Fantasmagorique | D125: Pouvoir | H125: Fait apparaitre l'objet de la peur de la cible, l'intensité peux accroitre sa phobie et ses effets (qui de base est trigger, selon sa nature, le cas échéant) si la cible a pas de phobie le malus est bien moindre ? (sorte d'épouventard en fait) | I125: 🎭 Illusion: Carphantin | J125: =CONCAT(CONCAT(C125, " "),$A$1)
A126: Imbueo (Imprégner) | B126: Conimbu (Con + imbu) | C126: Arme imprégnée | D126: Pouvoir | H126: Arme (élémentaire ou matière) | I126: 🔥 Feu: Conimbuar, ❄️ Glace: Conimbuis, ⚡ Foudre: Conimbuor, 🪨 Terre: Conimbuum, 💧 Eau: Conimbuyn, 🌪️ Air: Conimbuel, ☠️ Mort: Conimbuus, ✡️ Arcane: Conimbuys, ☢️ Toxique: Conimbuex, ⚔️ Acier: Conimbuan, 🌿 Flore: Conimbuiln, ✨ Sacre: Conimbuiel, 🩸 Impie: Conimbuun, ☀️ Lumière: Conimbuion, 🌑 Ombre: Conimbuoth | J126: =CONCAT(CONCAT(C126, " "),$A$1)
... A134: Focus (Foyer) | B134: Confocus (Con + focus) | C134: Focalisateur | D134: Pouvoir | H134: Invoque un focalisateur | I134: 🔮 Magie: Confocusirn | J134: =CONCAT(CONCAT(C134, " "),$A$1)
